Workbook
Name AnnoGestione: PARAMETRI!$B$11
Name ListaCommesseDashboard: PARAMETRI!$D$3:$D$303
Name ListaCommessePregresse: PARAMETRI!$F$4:$F$303
Name ListaCommessePregresseDashboard: PARAMETRI!$F$3:$F$303
Name ListaCommesseSelezione: ANAGRAFICA!$Q$6:$Q$305
Name ListaMesi: PARAMETRI!$G$3:$G$14
Name ListaTipiMovimento: PARAMETRI!$H$3:$H$9

Sheet ANAGRAFICA
A1: ANAGRAFICA COMMESSE — REV.14
A2: Unica fonte master. Utilizzare i filtri della tabella (tecnico e date): il conteggio delle commesse visibili si aggiorna automaticamente.
A3: COMMESSE TOTALI | B3: =COUNTA($B$6:$B$305) -> 4
A4: VISIBILI DOPO I FILTRI | B4: =SUBTOTAL(103,$B$6:$B$305) -> 3
A5: DATA DI INSERIMENTO * | B5: CODICE COMMESSA | C5: CLIENTE | D5: DESCRIZIONE / CANTIERE | E5: RAMO DI ATTIVITÀ | F5: TECNICO | G5: PREPOSTO | H5: DATA DI INIZIO PREVISTO | I5: DATA DI INIZIO EFFETTIVO | J5: DATA DI FINE PREVISTA | K5: DATA DI FINE EFFETTIVA | L5: STATO CANTIERE | M5: RITENUTE PREVISTE | N5: CONTRATTO INIZIALE | O5: INTEGRAZIONI | P5: CONTRATTO AGGIORNATO | Q5: CODICE | CLIENTE | CANTIERE | R5: CAUSA AGGIORNAMENTO DATA FINE | S5: CONTROLLO DUPLICAZIONE
B6: C042 | C6: CARRON BAU | D6: MURATURE IN LATERIZIO C/O COSMO SPA - PESCHIERA DEL GARDA | E6: MURATURA | F6: DAVIDE | G6: AHMET MOUSTAFA | I6: 46181 | J6: 46259 | L6: In corso | M6: SI | N6: 143061.41 | P6: =IF($B6="","",IF(AND($N6="",$O6=""),"",SUM($N6:$O6))) -> 143061.41 | Q6: =IF($B6="","",$B6&" | "&$C6&" | "&$D6) -> C042 | CARRON BAU | MURATURE IN LATERIZIO C/O COSMO SPA - PESCHIERA DEL GARDA | R6: Proroga/Sospensione autorizzata | S6: =IF($B6="","",IF(COUNTIF($B$6:$B$305,$B6)>1,"DUPLICATO","OK")) -> DUPLICATO | T6: 46249
B7: C011 | C7: CARRON | D7: ZABARELLA 2023 - COD. CANTIERE 774 | E7: MURATURA+ECONOMIE | F7: ALBAN | G7: NA | I7: 46037 | J7: 46112 | L7: Finito ritenute non previste | M7: NO | N7: 55228 | O7: 127530 | P7: =IF($B7="","",IF(AND($N7="",$O7=""),"",SUM($N7:$O7))) -> 182758 | Q7: =IF($B7="","",$B7&" | "&$C7&" | "&$D7) -> C011 | CARRON | ZABARELLA 2023 - COD. CANTIERE 774 | S7: =IF($B7="","",IF(COUNTIF($B$6:$B$305,$B7)>1,"DUPLICATO","OK")) -> OK | T7: 46112
B8: TEST10 | C8: COMMESSA DIMOSTRATIVA | D8: TEST REV.10 - PERDITE SAL E COSTI MENSILI | E8: TEST | F8: DIREZIONE | G8: PREPOSTO TEST | I8: 46023 | J8: 46387 | L8: In corso | M8: NO | N8: 100000 | O8: 0 | P8: =IF($B8="","",IF(AND($N8="",$O8=""),"",SUM($N8:$O8))) -> 100000 | Q8: =IF($B8="","",$B8&" | "&$C8&" | "&$D8) -> TEST10 | COMMESSA DIMOSTRATIVA | TEST REV.10 - PERDITE SAL E COSTI MENSILI | R8: Nessuna variazione | S8: =IF($B8="","",IF(COUNTIF($B$6:$B$305,$B8)>1,"DUPLICATO","OK")) -> OK | T8: 46387
B9: C042 | P9: =IF($B9="","",IF(AND($N9="",$O9=""),"",SUM($N9:$O9))) | Q9: =IF($B9="","",$B9&" | "&$C9&" | "&$D9) -> C042 | | | S9: =IF($B9="","",IF(COUNTIF($B$6:$B$305,$B9)>1,"DUPLICATO","OK")) -> DUPLICATO
P10: =IF($B10="","",IF(AND($N10="",$O10=""),"",SUM($N10:$O10))) | Q10: =IF($B10="","",$B10&" | "&$C10&" | "&$D10) | S10: =IF($B10="","",IF(COUNTIF($B$6:$B$305,$B10)>1,"DUPLICATO","OK"))
P11: =IF($B11="","",IF(AND($N11="",$O11=""),"",SUM($N11:$O11))) | Q11: =IF($B11="","",$B11&" | "&$C11&" | "&$D11) | S11: =IF($B11="","",IF(COUNTIF($B$6:$B$305,$B11)>1,"DUPLICATO","OK"))
P12: =IF($B12="","",IF(AND($N12="",$O12=""),"",SUM($N12:$O12))) | Q12: =IF($B12="","",$B12&" | "&$C12&" | "&$D12) | S12: =IF($B12="","",IF(COUNTIF($B$6:$B$305,$B12)>1,"DUPLICATO","OK"))
P13: =IF($B13="","",IF(AND($N13="",$O13=""),"",SUM($N13:$O13))) | Q13: =IF($B13="","",$B13&" | "&$C13&" | "&$D13) | S13: =IF($B13="","",IF(COUNTIF($B$6:$B$305,$B13)>1,"DUPLICATO","OK"))
P14: =IF($B14="","",IF(AND($N14="",$O14=""),"",SUM($N14:$O14))) | Q14: =IF($B14="","",$B14&" | "&$C14&" | "&$D14) | S14: =IF($B14="","",IF(COUNTIF($B$6:$B$305,$B14)>1,"DUPLICATO","OK"))
P15: =IF($B15="","",IF(AND($N15="",$O15=""),"",SUM($N15:$O15))) | Q15: =IF($B15="","",$B15&" | "&$C15&" | "&$D15) | S15: =IF($B15="","",IF(COUNTIF($B$6:$B$305,$B15)>1,"DUPLICATO","OK"))
P16: =IF($B16="","",IF(AND($N16="",$O16=""),"",SUM($N16:$O16))) | Q16: =IF($B16="","",$B16&" | "&$C16&" | "&$D16) | S16: =IF($B16="","",IF(COUNTIF($B$6:$B$305,$B16)>1,"DUPLICATO","OK"))
P17: =IF($B17="","",IF(AND($N17="",$O17=""),"",SUM($N17:$O17))) | Q17: =IF($B17="","",$B17&" | "&$C17&" | "&$D17) | S17: =IF($B17="","",IF(COUNTIF($B$6:$B$305,$B17)>1,"DUPLICATO","OK"))
P18: =IF($B18="","",IF(AND($N18="",$O18=""),"",SUM($N18:$O18))) | Q18: =IF($B18="","",$B18&" | "&$C18&" | "&$D18) | S18: =IF($B18="","",IF(COUNTIF($B$6:$B$305,$B18)>1,"DUPLICATO","OK"))
P19: =IF($B19="","",IF(AND($N19="",$O19=""),"",SUM($N19:$O19))) | Q19: =IF($B19="","",$B19&" | "&$C19&" | "&$D19) | S19: =IF($B19="","",IF(COUNTIF($B$6:$B$305,$B19)>1,"DUPLICATO","OK"))
P20: =IF($B20="","",IF(AND($N20="",$O20=""),"",SUM($N20:$O20))) | Q20: =IF($B20="","",$B20&" | "&$C20&" | "&$D20) | S20: =IF($B20="","",IF(COUNTIF($B$6:$B$305,$B20)>1,"DUPLICATO","OK"))
P21: =IF($B21="","",IF(AND($N21="",$O21=""),"",SUM($N21:$O21))) | Q21: =IF($B21="","",$B21&" | "&$C21&" | "&$D21) | S21: =IF($B21="","",IF(COUNTIF($B$6:$B$305,$B21)>1,"DUPLICATO","OK"))
... P305: =IF($B305="","",IF(AND($N305="",$O305=""),"",SUM($N305:$O305))) | Q305: =IF($B305="","",$B305&" | "&$C305&" | "&$D305) | S305: =IF($B305="","",IF(COUNTIF($B$6:$B$305,$B305)>1,"DUPLICATO","OK"))

Sheet SALDI AL 31.12.2025
A1: SALDI AL 31.12.2025 — REV.14
A2: COMMESSA | C2: SAL MATURATO | D2: FATTURATO LORDO | E2: RITENUTE | F2: SVINCOLI | G2: PERDITE SAL | H2: ORE | I2: COSTI DIRETTI | J2: RIGHE
A3: TUTTE | C3: =IF($A$3="TUTTE",SUM($C$6:$C$505),SUMIF($A$6:$A$505,$A$3,$C$6:$C$505)) -> 0 | D3: =IF($A$3="TUTTE",SUM($D$6:$D$505),SUMIF($A$6:$A$505,$A$3,$D$6:$D$505)) -> 0 | E3: =IF($A$3="TUTTE",SUM($E$6:$E$505),SUMIF($A$6:$A$505,$A$3,$E$6:$E$505)) -> 0 | F3: =IF($A$3="TUTTE",SUM($F$6:$F$505),SUMIF($A$6:$A$505,$A$3,$F$6:$F$505)) -> 0 | G3: =IF($A$3="TUTTE",SUM($G$6:$G$505),SUMIF($A$6:$A$505,$A$3,$G$6:$G$505)) -> 0 | H3: =IF($A$3="TUTTE",SUM($H$6:$H$505),SUMIF($A$6:$A$505,$A$3,$H$6:$H$505)) -> 0 | I3: =IF($A$3="TUTTE",SUM($I$6:$I$505),SUMIF($A$6:$A$505,$A$3,$I$6:$I$505)) -> 0 | J3: =IF($A$3="TUTTE",COUNTIF($A$6:$A$505,"<>"),COUNTIF($A$6:$A$505,$A$3)) -> 0
A5: CODICE COMMESSA | B5: DATA SALDO | C5: SAL MATURATO | D5: FATTURATO LORDO | E5: RITENUTE | F5: SVINCOLI | G5: PERDITE SAL ACCETTATE | H5: ORE | I5: COSTI DIRETTI | J5: CONTROLLO DUPLICATO
B6: =IF($A6="","",DATE(PARAMETRI!$B$11-1,12,31)) | J6: =IF($A6="","",IF(COUNTIF($A$6:$A$505,$A6)>1,"DUPLICATO","OK"))
B7: =IF($A7="","",DATE(PARAMETRI!$B$11-1,12,31)) | J7: =IF($A7="","",IF(COUNTIF($A$6:$A$505,$A7)>1,"DUPLICATO","OK"))
B8: =IF($A8="","",DATE(PARAMETRI!$B$11-1,12,31)) | J8: =IF($A8="","",IF(COUNTIF($A$6:$A$505,$A8)>1,"DUPLICATO","OK"))
B9: =IF($A9="","",DATE(PARAMETRI!$B$11-1,12,31)) | J9: =IF($A9="","",IF(COUNTIF($A$6:$A$505,$A9)>1,"DUPLICATO","OK"))
B10: =IF($A10="","",DATE(PARAMETRI!$B$11-1,12,31)) | J10: =IF($A10="","",IF(COUNTIF($A$6:$A$505,$A10)>1,"DUPLICATO","OK"))
B11: =IF($A11="","",DATE(PARAMETRI!$B$11-1,12,31)) | J11: =IF($A11="","",IF(COUNTIF($A$6:$A$505,$A11)>1,"DUPLICATO","OK"))
B12: =IF($A12="","",DATE(PARAMETRI!$B$11-1,12,31)) | J12: =IF($A12="","",IF(COUNTIF($A$6:$A$505,$A12)>1,"DUPLICATO","OK"))
B13: =IF($A13="","",DATE(PARAMETRI!$B$11-1,12,31)) | J13: =IF($A13="","",IF(COUNTIF($A$6:$A$505,$A13)>1,"DUPLICATO","OK"))
B14: =IF($A14="","",DATE(PARAMETRI!$B$11-1,12,31)) | J14: =IF($A14="","",IF(COUNTIF($A$6:$A$505,$A14)>1,"DUPLICATO","OK"))
B15: =IF($A15="","",DATE(PARAMETRI!$B$11-1,12,31)) | J15: =IF($A15="","",IF(COUNTIF($A$6:$A$505,$A15)>1,"DUPLICATO","OK"))
B16: =IF($A16="","",DATE(PARAMETRI!$B$11-1,12,31)) | J16: =IF($A16="","",IF(COUNTIF($A$6:$A$505,$A16)>1,"DUPLICATO","OK"))
B17: =IF($A17="","",DATE(PARAMETRI!$B$11-1,12,31)) | J17: =IF($A17="","",IF(COUNTIF($A$6:$A$505,$A17)>1,"DUPLICATO","OK"))
... B505: =IF($A505="","",DATE(PARAMETRI!$B$11-1,12,31)) | J505: =IF($A505="","",IF(COUNTIF($A$6:$A$505,$A505)>1,"DUPLICATO","OK"))

Sheet BUDGET COMMESSA
A1: BUDGET COMMESSA — REV.14
A2: Budget tecnico per commessa. Codice, cliente e cantiere provengono esclusivamente dall'ANAGRAFICA.
A3: PERIODO DA | B3: 46023 | C3: PERIODO A | D3: 46387 | E3: COMMESSE APERTE | F3: =IF(OR($B$3="",$D$3="",$B$3>$D$3),"",COUNTIFS(ANAGRAFICA!$J$6:$J$305,">="&$B$3,ANAGRAFICA!$J$6:$J$305,"<="&$D$3,ANAGRAFICA!$K$6:$K$305,"",ANAGRAFICA!$L$6:$L$305,"<>Finito*",ANAGRAFICA!$B$6:$B$305,"<>")) -> 2 | G3: ORE PREVISTE | H3: =IF(OR($B$3="",$D$3="",$B$3>$D$3),"",SUMIFS($D$6:$D$305,ANAGRAFICA!$J$6:$J$305,">="&$B$3,ANAGRAFICA!$J$6:$J$305,"<="&$D$3,ANAGRAFICA!$K$6:$K$305,"",ANAGRAFICA!$L$6:$L$305,"<>Finito*",ANAGRAFICA!$B$6:$B$305,"<>")) -> 2800 | I3: COSTO TOTALE PREVISTO | J3: =IF(OR($B$3="",$D$3="",$B$3>$D$3),"",SUMIFS($H$6:$H$305,ANAGRAFICA!$J$6:$J$305,">="&$B$3,ANAGRAFICA!$J$6:$J$305,"<="&$D$3,ANAGRAFICA!$K$6:$K$305,"",ANAGRAFICA!$L$6:$L$305,"<>Finito*",ANAGRAFICA!$B$6:$B$305,"<>")) -> 179520
A4: La dashboard considera le commesse ancora aperte con DATA DI FINE PREVISTA compresa nel periodo selezionato.
A5: CODICE COMMESSA | B5: CLIENTE | C5: DESCRIZIONE / CANTIERE | D5: ORE PREVISTE | E5: COSTO ORARIO | F5: COSTO ORE | G5: COSTI DIRETTI PREVISTI | H5: COSTO TOTALE PREVISTO | I5: MARGINE TEORICO | J5: NOTE
A6: =IF(ANAGRAFICA!$B6="","",ANAGRAFICA!$B6) -> C042 | B6: =IF($A6="","",ANAGRAFICA!$C6) -> CARRON BAU | C6: =IF($A6="","",ANAGRAFICA!$D6) -> MURATURE IN LATERIZIO C/O COSMO SPA - PESCHIERA DEL GARDA | D6: 1800 | E6: 45.79 | F6: =IF(OR($A6="",$D6="",$E6=""),"",$D6*$E6) -> 82422 | G6: 31308 | H6: =IF($A6="","",SUM($F6,$G6)) -> 113730 | I6: =IFERROR(IF(OR($A6="",ANAGRAFICA!$P6="",ANAGRAFICA!$P6=0),"",(ANAGRAFICA!$P6-$H6)/ANAGRAFICA!$P6),"") -> 0.20502671 | J6: DATI DIMOSTRATIVI — da sostituire con l'Analisi di fattibilità approvata
A7: =IF(ANAGRAFICA!$B7="","",ANAGRAFICA!$B7) -> C011 | B7: =IF($A7="","",ANAGRAFICA!$C7) -> CARRON | C7: =IF($A7="","",ANAGRAFICA!$D7) -> ZABARELLA 2023 - COD. CANTIERE 774 | F7: =IF(OR($A7="",$D7="",$E7=""),"",$D7*$E7) | H7: =IF($A7="","",SUM($F7,$G7)) -> 0 | I7: =IFERROR(IF(OR($A7="",ANAGRAFICA!$P7="",ANAGRAFICA!$P7=0),"",(ANAGRAFICA!$P7-$H7)/ANAGRAFICA!$P7),"") -> 1
A8: =IF(ANAGRAFICA!$B8="","",ANAGRAFICA!$B8) -> TEST10 | B8: =IF($A8="","",ANAGRAFICA!$C8) -> COMMESSA DIMOSTRATIVA | C8: =IF($A8="","",ANAGRAFICA!$D8) -> TEST REV.10 - PERDITE SAL E COSTI MENSILI | D8: 1000 | E8: 45.79 | F8: =IF(OR($A8="",$D8="",$E8=""),"",$D8*$E8) -> 45790 | G8: 20000 | H8: =IF($A8="","",SUM($F8,$G8)) -> 65790 | I8: =IFERROR(IF(OR($A8="",ANAGRAFICA!$P8="",ANAGRAFICA!$P8=0),"",(ANAGRAFICA!$P8-$H8)/ANAGRAFICA!$P8),"") -> 0.3421
A9: =IF(ANAGRAFICA!$B9="","",ANAGRAFICA!$B9) -> C042 | B9: =IF($A9="","",ANAGRAFICA!$C9) -> 0 | C9: =IF($A9="","",ANAGRAFICA!$D9) -> 0 | F9: =IF(OR($A9="",$D9="",$E9=""),"",$D9*$E9) | H9: =IF($A9="","",SUM($F9,$G9)) -> 0 | I9: =IFERROR(IF(OR($A9="",ANAGRAFICA!$P9="",ANAGRAFICA!$P9=0),"",(ANAGRAFICA!$P9-$H9)/ANAGRAFICA!$P9),"")
A10: =IF(ANAGRAFICA!$B10="","",ANAGRAFICA!$B10) | B10: =IF($A10="","",ANAGRAFICA!$C10) | C10: =IF($A10="","",ANAGRAFICA!$D10) | F10: =IF(OR($A10="",$D10="",$E10=""),"",$D10*$E10) | H10: =IF($A10="","",SUM($F10,$G10)) | I10: =IFERROR(IF(OR($A10="",ANAGRAFICA!$P10="",ANAGRAFICA!$P10=0),"",(ANAGRAFICA!$P10-$H10)/ANAGRAFICA!$P10),"")
A11: =IF(ANAGRAFICA!$B11="","",ANAGRAFICA!$B11) | B11: =IF($A11="","",ANAGRAFICA!$C11) | C11: =IF($A11="","",ANAGRAFICA!$D11) | F11: =IF(OR($A11="",$D11="",$E11=""),"",$D11*$E11) | H11: =IF($A11="","",SUM($F11,$G11)) | I11: =IFERROR(IF(OR($A11="",ANAGRAFICA!$P11="",ANAGRAFICA!$P11=0),"",(ANAGRAFICA!$P11-$H11)/ANAGRAFICA!$P11),"")
A12: =IF(ANAGRAFICA!$B12="","",ANAGRAFICA!$B12) | B12: =IF($A12="","",ANAGRAFICA!$C12) | C12: =IF($A12="","",ANAGRAFICA!$D12) | F12: =IF(OR($A12="",$D12="",$E12=""),"",$D12*$E12) | H12: =IF($A12="","",SUM($F12,$G12)) | I12: =IFERROR(IF(OR($A12="",ANAGRAFICA!$P12="",ANAGRAFICA!$P12=0),"",(ANAGRAFICA!$P12-$H12)/ANAGRAFICA!$P12),"")
A13: =IF(ANAGRAFICA!$B13="","",ANAGRAFICA!$B13) | B13: =IF($A13="","",ANAGRAFICA!$C13) | C13: =IF($A13="","",ANAGRAFICA!$D13) | F13: =IF(OR($A13="",$D13="",$E13=""),"",$D13*$E13) | H13: =IF($A13="","",SUM($F13,$G13)) | I13: =IFERROR(IF(OR($A13="",ANAGRAFICA!$P13="",ANAGRAFICA!$P13=0),"",(ANAGRAFICA!$P13-$H13)/ANAGRAFICA!$P13),"")
A14: =IF(ANAGRAFICA!$B14="","",ANAGRAFICA!$B14) | B14: =IF($A14="","",ANAGRAFICA!$C14) | C14: =IF($A14="","",ANAGRAFICA!$D14) | F14: =IF(OR($A14="",$D14="",$E14=""),"",$D14*$E14) | H14: =IF($A14="","",SUM($F14,$G14)) | I14: =IFERROR(IF(OR($A14="",ANAGRAFICA!$P14="",ANAGRAFICA!$P14=0),"",(ANAGRAFICA!$P14-$H14)/ANAGRAFICA!$P14),"")
A15: =IF(ANAGRAFICA!$B15="","",ANAGRAFICA!$B15) | B15: =IF($A15="","",ANAGRAFICA!$C15) | C15: =IF($A15="","",ANAGRAFICA!$D15) | F15: =IF(OR($A15="",$D15="",$E15=""),"",$D15*$E15) | H15: =IF($A15="","",SUM($F15,$G15)) | I15: =IFERROR(IF(OR($A15="",ANAGRAFICA!$P15="",ANAGRAFICA!$P15=0),"",(ANAGRAFICA!$P15-$H15)/ANAGRAFICA!$P15),"")
A16: =IF(ANAGRAFICA!$B16="","",ANAGRAFICA!$B16) | B16: =IF($A16="","",ANAGRAFICA!$C16) | C16: =IF($A16="","",ANAGRAFICA!$D16) | F16: =IF(OR($A16="",$D16="",$E16=""),"",$D16*$E16) | H16: =IF($A16="","",SUM($F16,$G16)) | I16: =IFERROR(IF(OR($A16="",ANAGRAFICA!$P16="",ANAGRAFICA!$P16=0),"",(ANAGRAFICA!$P16-$H16)/ANAGRAFICA!$P16),"")
A17: =IF(ANAGRAFICA!$B17="","",ANAGRAFICA!$B17) | B17: =IF($A17="","",ANAGRAFICA!$C17) | C17: =IF($A17="","",ANAGRAFICA!$D17) | F17: =IF(OR($A17="",$D17="",$E17=""),"",$D17*$E17) | H17: =IF($A17="","",SUM($F17,$G17)) | I17: =IFERROR(IF(OR($A17="",ANAGRAFICA!$P17="",ANAGRAFICA!$P17=0),"",(ANAGRAFICA!$P17-$H17)/ANAGRAFICA!$P17),"")
A18: =IF(ANAGRAFICA!$B18="","",ANAGRAFICA!$B18) | B18: =IF($A18="","",ANAGRAFICA!$C18) | C18: =IF($A18="","",ANAGRAFICA!$D18) | F18: =IF(OR($A18="",$D18="",$E18=""),"",$D18*$E18) | H18: =IF($A18="","",SUM($F18,$G18)) | I18: =IFERROR(IF(OR($A18="",ANAGRAFICA!$P18="",ANAGRAFICA!$P18=0),"",(ANAGRAFICA!$P18-$H18)/ANAGRAFICA!$P18),"")
A19: =IF(ANAGRAFICA!$B19="","",ANAGRAFICA!$B19) | B19: =IF($A19="","",ANAGRAFICA!$C19) | C19: =IF($A19="","",ANAGRAFICA!$D19) | F19: =IF(OR($A19="",$D19="",$E19=""),"",$D19*$E19) | H19: =IF($A19="","",SUM($F19,$G19)) | I19: =IFERROR(IF(OR($A19="",ANAGRAFICA!$P19="",ANAGRAFICA!$P19=0),"",(ANAGRAFICA!$P19-$H19)/ANAGRAFICA!$P19),"")
A20: =IF(ANAGRAFICA!$B20="","",ANAGRAFICA!$B20) | B20: =IF($A20="","",ANAGRAFICA!$C20) | C20: =IF($A20="","",ANAGRAFICA!$D20) | F20: =IF(OR($A20="",$D20="",$E20=""),"",$D20*$E20) | H20: =IF($A20="","",SUM($F20,$G20)) | I20: =IFERROR(IF(OR($A20="",ANAGRAFICA!$P20="",ANAGRAFICA!$P20=0),"",(ANAGRAFICA!$P20-$H20)/ANAGRAFICA!$P20),"")
... A305: =IF(ANAGRAFICA!$B305="","",ANAGRAFICA!$B305) | B305: =IF($A305="","",ANAGRAFICA!$C305) | C305: =IF($A305="","",ANAGRAFICA!$D305) | F305: =IF(OR($A305="",$D305="",$E305=""),"",$D305*$E305) | H305: =IF($A305="","",SUM($F305,$G305)) | I305: =IFERROR(IF(OR($A305="",ANAGRAFICA!$P305="",ANAGRAFICA!$P305=0),"",(ANAGRAFICA!$P305-$H305)/ANAGRAFICA!$P305),"")

Sheet MOVIMENTI 2026
A1: MOVIMENTI 2026 — ARCHIVIO UNICO — REV.14
A2: COMMESSA | C2: MESE INIZIALE | E2: MESE FINALE | G2: SAL MATURATO | H2: FATTURATO LORDO | I2: RITENUTE | J2: SVINCOLI | K2: FATTURATO NETTO | L2: ORE | M2: PERDITE SAL | N2: COSTI DIRETTI | Q2: =DATE(PARAMETRI!$B$11,MATCH($C$3,PARAMETRI!$G$3:$G$14,0),1) -> 46023
A3: TUTTE | C3: Gennaio | E3: Dicembre | G3: =IF($Q$2>=$Q$3,0,IF($A$3="TUTTE",SUMIFS($I$7:$I$4206,$E$7:$E$4206,">="&$Q$2,$E$7:$E$4206,"<"&$Q$3),SUMIFS($I$7:$I$4206,$B$7:$B$4206,$A$3,$E$7:$E$4206,">="&$Q$2,$E$7:$E$4206,"<"&$Q$3))) -> 87770.9 | H3: =IF($Q$2>=$Q$3,0,IF($A$3="TUTTE",SUMIFS($J$7:$J$4206,$E$7:$E$4206,">="&$Q$2,$E$7:$E$4206,"<"&$Q$3),SUMIFS($J$7:$J$4206,$B$7:$B$4206,$A$3,$E$7:$E$4206,">="&$Q$2,$E$7:$E$4206,"<"&$Q$3))) -> 91770.9 | I3: =IF($Q$2>=$Q$3,0,IF($A$3="TUTTE",SUMIFS($K$7:$K$4206,$E$7:$E$4206,">="&$Q$2,$E$7:$E$4206,"<"&$Q$3),SUMIFS($K$7:$K$4206,$B$7:$B$4206,$A$3,$E$7:$E$4206,">="&$Q$2,$E$7:$E$4206,"<"&$Q$3))) -> 2010.23 | J3: =IF($Q$2>=$Q$3,0,IF($A$3="TUTTE",SUMIFS($L$7:$L$4206,$E$7:$E$4206,">="&$Q$2,$E$7:$E$4206,"<"&$Q$3),SUMIFS($L$7:$L$4206,$B$7:$B$4206,$A$3,$E$7:$E$4206,">="&$Q$2,$E$7:$E$4206,"<"&$Q$3))) -> 500 | K3: =IF($Q$2>=$Q$3,0,IF($A$3="TUTTE",SUMIFS($M$7:$M$4206,$E$7:$E$4206,">="&$Q$2,$E$7:$E$4206,"<"&$Q$3),SUMIFS($M$7:$M$4206,$B$7:$B$4206,$A$3,$E$7:$E$4206,">="&$Q$2,$E$7:$E$4206,"<"&$Q$3))) -> 90260.67 | L3: =IF($Q$2>=$Q$3,0,IF($A$3="TUTTE",SUMIFS($N$7:$N$4206,$E$7:$E$4206,">="&$Q$2,$E$7:$E$4206,"<"&$Q$3),SUMIFS($N$7:$N$4206,$B$7:$B$4206,$A$3,$E$7:$E$4206,">="&$Q$2,$E$7:$E$4206,"<"&$Q$3))) -> 980 | M3: =IF($Q$2>=$Q$3,0,IF($A$3="TUTTE",SUMIFS($P$7:$P$4206,$E$7:$E$4206,">="&$Q$2,$E$7:$E$4206,"<"&$Q$3),SUMIFS($P$7:$P$4206,$B$7:$B$4206,$A$3,$E$7:$E$4206,">="&$Q$2,$E$7:$E$4206,"<"&$Q$3))) -> 8000 | N3: =0+IF(MATCH($C$3,PARAMETRI!$G$3:$G$14,0)>MATCH($E$3,PARAMETRI!$G$3:$G$14,0),0,IF($A$3="TUTTE",SUMIFS('COSTI DIRETTI'!$H$6:$H$505,'COSTI DIRETTI'!$A$6:$A$505,">="&DATE(PARAMETRI!$B$11,MATCH($C$3,PARAMETRI!$G$3:$G$14,0),1),'COSTI DIRETTI'!$A$6:$A$505,"<"&DATE(PARAMETRI!$B$11,MATCH($E$3,PARAMETRI!$G$3:$G$14,0)+1,1)),SUMIFS('COSTI DIRETTI'!$H$6:$H$505,'COSTI DIRETTI'!$C$6:$C$505,$A$3,'COSTI DIRETTI'!$A$6:$A$505,">="&DATE(PARAMETRI!$B$11,MATCH($C$3,PARAMETRI!$G$3:$G$14,0),1),'COSTI DIRETTI'!$A$6:$A$505,"<"&DATE(PARAMETRI!$B$11,MATCH($E$3,PARAMETRI!$G$3:$G$14,0)+1,1)))) -> 38308 | Q3: =DATE(PARAMETRI!$B$11,MATCH($E$3,PARAMETRI!$G$3:$G$14,0)+1,1) -> 46388
A4: Dashboard = soli movimenti dell'anno corrente. I saldi al 31/12/2025 restano esclusi. Filtrare la tabella sottostante per analisi di dettaglio.
A6: COMMESSA (CODICE | CLIENTE | CANTIERE) | B6: CODICE COMMESSA | C6: CLIENTE | D6: CANTIERE | E6: DATA MOVIMENTO * | F6: TIPO MOVIMENTO | G6: NUMERO DOCUMENTO | H6: DESCRIZIONE | I6: SAL MATURATO | J6: FATTURATO LORDO | K6: RITENUTA | L6: SVINCOLO RITENUTA | M6: FATTURATO NETTO | N6: ORE EFFETTIVE | O6: NOTE | P6: PERDITA SAL ACCETTATA | Q6: MESE
A7: TEST10 | COMMESSA DIMOSTRATIVA | TEST REV.10 - PERDITE SAL E COSTI MENSILI | B7: =IFERROR(IF($A7="","",LEFT($A7,FIND(" | ",$A7)-1)),"") -> TEST10 | C7: =IFERROR(IF($A7="","",MID($A7,FIND(" | ",$A7)+3,FIND(" | ",$A7,FIND(" | ",$A7)+3)-FIND(" | ",$A7)-3)),"") -> COMMESSA DIMOSTRATIVA | D7: =IFERROR(IF($A7="","",RIGHT($A7,LEN($A7)-FIND(" | ",$A7,FIND(" | ",$A7)+3)-2)),"") -> TEST REV.10 - PERDITE SAL E COSTI MENSILI | E7: 46037 | F7: SAL + FATTURA | G7: T10-01 | H7: SAL/Fattura test gennaio | I7: 10000 | J7: 15000 | K7: 0 | L7: 0 | M7: =IF($B7="","",SUM($J7,-$K7,$L7)) -> 15000 | N7: 100 | O7: TEST REV.10 - MESE 1 | P7: 0
A8: TEST10 | COMMESSA DIMOSTRATIVA | TEST REV.10 - PERDITE SAL E COSTI MENSILI | B8: =IFERROR(IF($A8="","",LEFT($A8,FIND(" | ",$A8)-1)),"") -> TEST10 | C8: =IFERROR(IF($A8="","",MID($A8,FIND(" | ",$A8)+3,FIND(" | ",$A8,FIND(" | ",$A8)+3)-FIND(" | ",$A8)-3)),"") -> COMMESSA DIMOSTRATIVA | D8: =IFERROR(IF($A8="","",RIGHT($A8,LEN($A8)-FIND(" | ",$A8,FIND(" | ",$A8)+3)-2)),"") -> TEST REV.10 - PERDITE SAL E COSTI MENSILI | E8: 46068 | F8: SAL + FATTURA | G8: T10-02 | H8: SAL/Fattura e perdita accettata | I8: 10000 | J8: 15000 | K8: 0 | L8: 0 | M8: =IF($B8="","",SUM($J8,-$K8,$L8)) -> 15000 | N8: 120 | O8: TEST REV.10 - PERDITA DEFINITIVA | P8: 5000
A9: TEST10 | COMMESSA DIMOSTRATIVA | TEST REV.10 - PERDITE SAL E COSTI MENSILI | B9: =IFERROR(IF($A9="","",LEFT($A9,FIND(" | ",$A9)-1)),"") -> TEST10 | C9: =IFERROR(IF($A9="","",MID($A9,FIND(" | ",$A9)+3,FIND(" | ",$A9,FIND(" | ",$A9)+3)-FIND(" | ",$A9)-3)),"") -> COMMESSA DIMOSTRATIVA | D9: =IFERROR(IF($A9="","",RIGHT($A9,LEN($A9)-FIND(" | ",$A9,FIND(" | ",$A9)+3)-2)),"") -> TEST REV.10 - PERDITE SAL E COSTI MENSILI | E9: 46096 | F9: SAL + FATTURA | G9: T10-03 | H9: SAL/Fattura test marzo | I9: 5000 | J9: 10000 | K9: 0 | L9: 0 | M9: =IF($B9="","",SUM($J9,-$K9,$L9)) -> 10000 | N9: 80 | O9: TEST REV.10 - MESE 3 | P9: 0
A10: C042 | CARRON BAU | MURATURE IN LATERIZIO C/O COSMO SPA - PESCHIERA DEL GARDA | B10: =IFERROR(IF($A10="","",LEFT($A10,FIND(" | ",$A10)-1)),"") -> C042 | C10: =IFERROR(IF($A10="","",MID($A10,FIND(" | ",$A10)+3,FIND(" | ",$A10,FIND(" | ",$A10)+3)-FIND(" | ",$A10)-3)),"") -> CARRON BAU | D10: =IFERROR(IF($A10="","",RIGHT($A10,LEN($A10)-FIND(" | ",$A10,FIND(" | ",$A10)+3)-2)),"") -> MURATURE IN LATERIZIO C/O COSMO SPA - PESCHIERA DEL GARDA | E10: 46218 | F10: SAL + FATTURA | G10: 210 | H10: SAL 1 | I10: 20000 | J10: 18000 | K10: 900 | L10: 0 | M10: =IF($B10="","",SUM($J10,-$K10,$L10)) -> 17100 | N10: 300 | O10: PRIMO MOVIMENTO DI PROVA | P10: 2000
A11: C042 | CARRON BAU | MURATURE IN LATERIZIO C/O COSMO SPA - PESCHIERA DEL GARDA | B11: =IFERROR(IF($A11="","",LEFT($A11,FIND(" | ",$A11)-1)),"") -> C042 | C11: =IFERROR(IF($A11="","",MID($A11,FIND(" | ",$A11)+3,FIND(" | ",$A11,FIND(" | ",$A11)+3)-FIND(" | ",$A11)-3)),"") -> CARRON BAU | D11: =IFERROR(IF($A11="","",RIGHT($A11,LEN($A11)-FIND(" | ",$A11,FIND(" | ",$A11)+3)-2)),"") -> MURATURE IN LATERIZIO C/O COSMO SPA - PESCHIERA DEL GARDA | E11: 46234 | F11: SAL + FATTURA | G11: 259 | H11: SAL 2 | I11: 22770.9 | J11: 24770.9 | K11: 1110.23 | L11: 0 | M11: =IF($B11="","",SUM($J11,-$K11,$L11)) -> 23660.67 | N11: 380 | O11: SECONDO MOVIMENTO DELLA STESSA COMMESSA
A12: C011 | CARRON | ZABARELLA 2023 - COD. CANTIERE 774 | B12: =IFERROR(IF($A12="","",LEFT($A12,FIND(" | ",$A12)-1)),"") -> C011 | C12: =IFERROR(IF($A12="","",MID($A12,FIND(" | ",$A12)+3,FIND(" | ",$A12,FIND(" | ",$A12)+3)-FIND(" | ",$A12)-3)),"") -> CARRON | D12: =IFERROR(IF($A12="","",RIGHT($A12,LEN($A12)-FIND(" | ",$A12,FIND(" | ",$A12)+3)-2)),"") -> ZABARELLA 2023 - COD. CANTIERE 774 | E12: 46234 | I12: 10000 | J12: 9000 | M12: =IF($B12="","",SUM($J12,-$K12,$L12)) -> 9000 | P12: 1000
A13: C011 | CARRON | ZABARELLA 2023 - COD. CANTIERE 774 | B13: =IFERROR(IF($A13="","",LEFT($A13,FIND(" | ",$A13)-1)),"") -> C011 | C13: =IFERROR(IF($A13="","",MID($A13,FIND(" | ",$A13)+3,FIND(" | ",$A13,FIND(" | ",$A13)+3)-FIND(" | ",$A13)-3)),"") -> CARRON | D13: =IFERROR(IF($A13="","",RIGHT($A13,LEN($A13)-FIND(" | ",$A13,FIND(" | ",$A13)+3)-2)),"") -> ZABARELLA 2023 - COD. CANTIERE 774 | E13: 46234 | I13: 10000 | M13: =IF($B13="","",SUM($J13,-$K13,$L13)) -> 0
A14: C042 | CARRON BAU | MURATURE IN LATERIZIO C/O COSMO SPA - PESCHIERA DEL GARDA | B14: =IFERROR(IF($A14="","",LEFT($A14,FIND(" | ",$A14)-1)),"") -> C042 | C14: =IFERROR(IF($A14="","",MID($A14,FIND(" | ",$A14)+3,FIND(" | ",$A14,FIND(" | ",$A14)+3)-FIND(" | ",$A14)-3)),"") -> CARRON BAU | D14: =IFERROR(IF($A14="","",RIGHT($A14,LEN($A14)-FIND(" | ",$A14,FIND(" | ",$A14)+3)-2)),"") -> MURATURE IN LATERIZIO C/O COSMO SPA - PESCHIERA DEL GARDA | E14: 46259 | F14: SVINCOLO RITENUTA | G14: SV-01 | H14: SVINCOLO PARZIALE | I14: 0 | J14: 0 | K14: 0 | L14: 500 | M14: =IF($B14="","",SUM($J14,-$K14,$L14)) -> 500 | N14: 0 | O14: SVINCOLO PARZIALE DI PROVA
B15: =IFERROR(IF($A15="","",LEFT($A15,FIND(" | ",$A15)-1)),"") | C15: =IFERROR(IF($A15="","",MID($A15,FIND(" | ",$A15)+3,FIND(" | ",$A15,FIND(" | ",$A15)+3)-FIND(" | ",$A15)-3)),"") | D15: =IFERROR(IF($A15="","",RIGHT($A15,LEN($A15)-FIND(" | ",$A15,FIND(" | ",$A15)+3)-2)),"") | M15: =IF($B15="","",SUM($J15,-$K15,$L15))
B16: =IFERROR(IF($A16="","",LEFT($A16,FIND(" | ",$A16)-1)),"") | C16: =IFERROR(IF($A16="","",MID($A16,FIND(" | ",$A16)+3,FIND(" | ",$A16,FIND(" | ",$A16)+3)-FIND(" | ",$A16)-3)),"") | D16: =IFERROR(IF($A16="","",RIGHT($A16,LEN($A16)-FIND(" | ",$A16,FIND(" | ",$A16)+3)-2)),"") | M16: =IF($B16="","",SUM($J16,-$K16,$L16))
B17: =IFERROR(IF($A17="","",LEFT($A17,FIND(" | ",$A17)-1)),"") | C17: =IFERROR(IF($A17="","",MID($A17,FIND(" | ",$A17)+3,FIND(" | ",$A17,FIND(" | ",$A17)+3)-FIND(" | ",$A17)-3)),"") | D17: =IFERROR(IF($A17="","",RIGHT($A17,LEN($A17)-FIND(" | ",$A17,FIND(" | ",$A17)+3)-2)),"") | M17: =IF($B17="","",SUM($J17,-$K17,$L17))
B18: =IFERROR(IF($A18="","",LEFT($A18,FIND(" | ",$A18)-1)),"") | C18: =IFERROR(IF($A18="","",MID($A18,FIND(" | ",$A18)+3,FIND(" | ",$A18,FIND(" | ",$A18)+3)-FIND(" | ",$A18)-3)),"") | D18: =IFERROR(IF($A18="","",RIGHT($A18,LEN($A18)-FIND(" | ",$A18,FIND(" | ",$A18)+3)-2)),"") | M18: =IF($B18="","",SUM($J18,-$K18,$L18))
B19: =IFERROR(IF($A19="","",LEFT($A19,FIND(" | ",$A19)-1)),"") | C19: =IFERROR(IF($A19="","",MID($A19,FIND(" | ",$A19)+3,FIND(" | ",$A19,FIND(" | ",$A19)+3)-FIND(" | ",$A19)-3)),"") | D19: =IFERROR(IF($A19="","",RIGHT($A19,LEN($A19)-FIND(" | ",$A19,FIND(" | ",$A19)+3)-2)),"") | M19: =IF($B19="","",SUM($J19,-$K19,$L19))
B20: =IFERROR(IF($A20="","",LEFT($A20,FIND(" | ",$A20)-1)),"") | C20: =IFERROR(IF($A20="","",MID($A20,FIND(" | ",$A20)+3,FIND(" | ",$A20,FIND(" | ",$A20)+3)-FIND(" | ",$A20)-3)),"") | D20: =IFERROR(IF($A20="","",RIGHT($A20,LEN($A20)-FIND(" | ",$A20,FIND(" | ",$A20)+3)-2)),"") | M20: =IF($B20="","",SUM($J20,-$K20,$L20))
B21: =IFERROR(IF($A21="","",LEFT($A21,FIND(" | ",$A21)-1)),"") | C21: =IFERROR(IF($A21="","",MID($A21,FIND(" | ",$A21)+3,FIND(" | ",$A21,FIND(" | ",$A21)+3)-FIND(" | ",$A21)-3)),"") | D21: =IFERROR(IF($A21="","",RIGHT($A21,LEN($A21)-FIND(" | ",$A21,FIND(" | ",$A21)+3)-2)),"") | M21: =IF($B21="","",SUM($J21,-$K21,$L21))
B22: =IFERROR(IF($A22="","",LEFT($A22,FIND(" | ",$A22)-1)),"") | C22: =IFERROR(IF($A22="","",MID($A22,FIND(" | ",$A22)+3,FIND(" | ",$A22,FIND(" | ",$A22)+3)-FIND(" | ",$A22)-3)),"") | D22: =IFERROR(IF($A22="","",RIGHT($A22,LEN($A22)-FIND(" | ",$A22,FIND(" | ",$A22)+3)-2)),"") | M22: =IF($B22="","",SUM($J22,-$K22,$L22))
B23: =IFERROR(IF($A23="","",LEFT($A23,FIND(" | ",$A23)-1)),"") | C23: =IFERROR(IF($A23="","",MID($A23,FIND(" | ",$A23)+3,FIND(" | ",$A23,FIND(" | ",$A23)+3)-FIND(" | ",$A23)-3)),"") | D23: =IFERROR(IF($A23="","",RIGHT($A23,LEN($A23)-FIND(" | ",$A23,FIND(" | ",$A23)+3)-2)),"") | M23: =IF($B23="","",SUM($J23,-$K23,$L23))
B24: =IFERROR(IF($A24="","",LEFT($A24,FIND(" | ",$A24)-1)),"") | C24: =IFERROR(IF($A24="","",MID($A24,FIND(" | ",$A24)+3,FIND(" | ",$A24,FIND(" | ",$A24)+3)-FIND(" | ",$A24)-3)),"") | D24: =IFERROR(IF($A24="","",RIGHT($A24,LEN($A24)-FIND(" | ",$A24,FIND(" | ",$A24)+3)-2)),"") | M24: =IF($B24="","",SUM($J24,-$K24,$L24))
B25: =IFERROR(IF($A25="","",LEFT($A25,FIND(" | ",$A25)-1)),"") | C25: =IFERROR(IF($A25="","",MID($A25,FIND(" | ",$A25)+3,FIND(" | ",$A25,FIND(" | ",$A25)+3)-FIND(" | ",$A25)-3)),"") | D25: =IFERROR(IF($A25="","",RIGHT($A25,LEN($A25)-FIND(" | ",$A25,FIND(" | ",$A25)+3)-2)),"") | M25: =IF($B25="","",SUM($J25,-$K25,$L25))
B26: =IFERROR(IF($A26="","",LEFT($A26,FIND(" | ",$A26)-1)),"") | C26: =IFERROR(IF($A26="","",MID($A26,FIND(" | ",$A26)+3,FIND(" | ",$A26,FIND(" | ",$A26)+3)-FIND(" | ",$A26)-3)),"") | D26: =IFERROR(IF($A26="","",RIGHT($A26,LEN($A26)-FIND(" | ",$A26,FIND(" | ",$A26)+3)-2)),"") | M26: =IF($B26="","",SUM($J26,-$K26,$L26))
... B4206: =IFERROR(IF($A4206="","",LEFT($A4206,FIND(" | ",$A4206)-1)),"") | C4206: =IFERROR(IF($A4206="","",MID($A4206,FIND(" | ",$A4206)+3,FIND(" | ",$A4206,FIND(" | ",$A4206)+3)-FIND(" | ",$A4206)-3)),"") | D4206: =IFERROR(IF($A4206="","",RIGHT($A4206,LEN($A4206)-FIND(" | ",$A4206,FIND(" | ",$A4206)+3)-2)),"") | M4206: =IF($B4206="","",SUM($J4206,-$K4206,$L4206))

Sheet COSTI DIRETTI
A1: COSTI DIRETTI 2026 — REV.14
A2: Registrare esclusivamente i costi specifici della commessa non già assorbiti dal costo orario aziendale.
G3: TOTALE COSTI | H3: =SUM($H$6:$H$505) -> 38308 | I3: ULTIMA DATA | J3: =IF(COUNT($A$6:$A$505)=0,"",MAX($A$6:$A$505)) -> 46254
A5: DATA COSTO | B5: COMMESSA (CODICE | CLIENTE | CANTIERE) | C5: CODICE COMMESSA | D5: CLIENTE | E5: CANTIERE | F5: MACRO-CATEGORIA DA ANALISI | G5: DESCRIZIONE | H5: IMPORTO | I5: FORNITORE / DOCUMENTO | J5: NOTE
A6: 46215 | B6: C042 | CARRON BAU | MURATURE IN LATERIZIO C/O COSMO SPA - PESCHIERA DEL GARDA | C6: =IFERROR(IF($B6="","",LEFT($B6,FIND(" | ",$B6)-1)),"") -> C042 | D6: =IFERROR(IF($B6="","",MID($B6,FIND(" | ",$B6)+3,FIND(" | ",$B6,FIND(" | ",$B6)+3)-FIND(" | ",$B6)-3)),"") -> CARRON BAU | E6: =IFERROR(IF($B6="","",RIGHT($B6,LEN($B6)-FIND(" | ",$B6,FIND(" | ",$B6)+3)-2)),"") -> MURATURE IN LATERIZIO C/O COSMO SPA - PESCHIERA DEL GARDA | F6: Materiali e attrezzature | G6: Laterizi e malte | H6: 5000 | I6: Fornitore di prova | J6: VALORE DIMOSTRATIVO
A7: 46227 | B7: C042 | CARRON BAU | MURATURE IN LATERIZIO C/O COSMO SPA - PESCHIERA DEL GARDA | C7: =IFERROR(IF($B7="","",LEFT($B7,FIND(" | ",$B7)-1)),"") -> C042 | D7: =IFERROR(IF($B7="","",MID($B7,FIND(" | ",$B7)+3,FIND(" | ",$B7,FIND(" | ",$B7)+3)-FIND(" | ",$B7)-3)),"") -> CARRON BAU | E7: =IFERROR(IF($B7="","",RIGHT($B7,LEN($B7)-FIND(" | ",$B7,FIND(" | ",$B7)+3)-2)),"") -> MURATURE IN LATERIZIO C/O COSMO SPA - PESCHIERA DEL GARDA | F7: Materiali e attrezzature | G7: Piattaforma dedicata | H7: 2000 | I7: Noleggio di prova | J7: VALORE DIMOSTRATIVO
A8: 46239 | B8: C042 | CARRON BAU | MURATURE IN LATERIZIO C/O COSMO SPA - PESCHIERA DEL GARDA | C8: =IFERROR(IF($B8="","",LEFT($B8,FIND(" | ",$B8)-1)),"") -> C042 | D8: =IFERROR(IF($B8="","",MID($B8,FIND(" | ",$B8)+3,FIND(" | ",$B8,FIND(" | ",$B8)+3)-FIND(" | ",$B8)-3)),"") -> CARRON BAU | E8: =IFERROR(IF($B8="","",RIGHT($B8,LEN($B8)-FIND(" | ",$B8,FIND(" | ",$B8)+3)-2)),"") -> MURATURE IN LATERIZIO C/O COSMO SPA - PESCHIERA DEL GARDA | F8: Materiali e attrezzature | G8: Trasporto straordinario | H8: 1000 | I8: Documento di prova | J8: VALORE DIMOSTRATIVO
A9: 46254 | B9: C042 | CARRON BAU | MURATURE IN LATERIZIO C/O COSMO SPA - PESCHIERA DEL GARDA | C9: =IFERROR(IF($B9="","",LEFT($B9,FIND(" | ",$B9)-1)),"") -> C042 | D9: =IFERROR(IF($B9="","",MID($B9,FIND(" | ",$B9)+3,FIND(" | ",$B9,FIND(" | ",$B9)+3)-FIND(" | ",$B9)-3)),"") -> CARRON BAU | E9: =IFERROR(IF($B9="","",RIGHT($B9,LEN($B9)-FIND(" | ",$B9,FIND(" | ",$B9)+3)-2)),"") -> MURATURE IN LATERIZIO C/O COSMO SPA - PESCHIERA DEL GARDA | F9: Materiali e attrezzature | G9: Fornitura aggiuntiva di prova | H9: 24308 | I9: Fornitore di prova | J9: VALORE DIMOSTRATIVO PER TEST SFORAMENTO
A10: 46042 | B10: TEST10 | COMMESSA DIMOSTRATIVA | TEST REV.10 - PERDITE SAL E COSTI MENSILI | C10: =IFERROR(IF($B10="","",LEFT($B10,FIND(" | ",$B10)-1)),"") -> TEST10 | D10: =IFERROR(IF($B10="","",MID($B10,FIND(" | ",$B10)+3,FIND(" | ",$B10,FIND(" | ",$B10)+3)-FIND(" | ",$B10)-3)),"") -> COMMESSA DIMOSTRATIVA | E10: =IFERROR(IF($B10="","",RIGHT($B10,LEN($B10)-FIND(" | ",$B10,FIND(" | ",$B10)+3)-2)),"") -> TEST REV.10 - PERDITE SAL E COSTI MENSILI | F10: Materiali e attrezzature | G10: Costo diretto test gennaio | H10: 1000
A11: 46073 | B11: TEST10 | COMMESSA DIMOSTRATIVA | TEST REV.10 - PERDITE SAL E COSTI MENSILI | C11: =IFERROR(IF($B11="","",LEFT($B11,FIND(" | ",$B11)-1)),"") -> TEST10 | D11: =IFERROR(IF($B11="","",MID($B11,FIND(" | ",$B11)+3,FIND(" | ",$B11,FIND(" | ",$B11)+3)-FIND(" | ",$B11)-3)),"") -> COMMESSA DIMOSTRATIVA | E11: =IFERROR(IF($B11="","",RIGHT($B11,LEN($B11)-FIND(" | ",$B11,FIND(" | ",$B11)+3)-2)),"") -> TEST REV.10 - PERDITE SAL E COSTI MENSILI | F11: Materiali e attrezzature | G11: Costo diretto test febbraio | H11: 2000
A12: 46132 | B12: TEST10 | COMMESSA DIMOSTRATIVA | TEST REV.10 - PERDITE SAL E COSTI MENSILI | C12: =IFERROR(IF($B12="","",LEFT($B12,FIND(" | ",$B12)-1)),"") -> TEST10 | D12: =IFERROR(IF($B12="","",MID($B12,FIND(" | ",$B12)+3,FIND(" | ",$B12,FIND(" | ",$B12)+3)-FIND(" | ",$B12)-3)),"") -> COMMESSA DIMOSTRATIVA | E12: =IFERROR(IF($B12="","",RIGHT($B12,LEN($B12)-FIND(" | ",$B12,FIND(" | ",$B12)+3)-2)),"") -> TEST REV.10 - PERDITE SAL E COSTI MENSILI | F12: Materiali e attrezzature | G12: Costo diretto test aprile senza ore | H12: 3000
C13: =IFERROR(IF($B13="","",LEFT($B13,FIND(" | ",$B13)-1)),"") | D13: =IFERROR(IF($B13="","",MID($B13,FIND(" | ",$B13)+3,FIND(" | ",$B13,FIND(" | ",$B13)+3)-FIND(" | ",$B13)-3)),"") | E13: =IFERROR(IF($B13="","",RIGHT($B13,LEN($B13)-FIND(" | ",$B13,FIND(" | ",$B13)+3)-2)),"")
C14: =IFERROR(IF($B14="","",LEFT($B14,FIND(" | ",$B14)-1)),"") | D14: =IFERROR(IF($B14="","",MID($B14,FIND(" | ",$B14)+3,FIND(" | ",$B14,FIND(" | ",$B14)+3)-FIND(" | ",$B14)-3)),"") | E14: =IFERROR(IF($B14="","",RIGHT($B14,LEN($B14)-FIND(" | ",$B14,FIND(" | ",$B14)+3)-2)),"")
C15: =IFERROR(IF($B15="","",LEFT($B15,FIND(" | ",$B15)-1)),"") | D15: =IFERROR(IF($B15="","",MID($B15,FIND(" | ",$B15)+3,FIND(" | ",$B15,FIND(" | ",$B15)+3)-FIND(" | ",$B15)-3)),"") | E15: =IFERROR(IF($B15="","",RIGHT($B15,LEN($B15)-FIND(" | ",$B15,FIND(" | ",$B15)+3)-2)),"")
C16: =IFERROR(IF($B16="","",LEFT($B16,FIND(" | ",$B16)-1)),"") | D16: =IFERROR(IF($B16="","",MID($B16,FIND(" | ",$B16)+3,FIND(" | ",$B16,FIND(" | ",$B16)+3)-FIND(" | ",$B16)-3)),"") | E16: =IFERROR(IF($B16="","",RIGHT($B16,LEN($B16)-FIND(" | ",$B16,FIND(" | ",$B16)+3)-2)),"")
C17: =IFERROR(IF($B17="","",LEFT($B17,FIND(" | ",$B17)-1)),"") | D17: =IFERROR(IF($B17="","",MID($B17,FIND(" | ",$B17)+3,FIND(" | ",$B17,FIND(" | ",$B17)+3)-FIND(" | ",$B17)-3)),"") | E17: =IFERROR(IF($B17="","",RIGHT($B17,LEN($B17)-FIND(" | ",$B17,FIND(" | ",$B17)+3)-2)),"")
C18: =IFERROR(IF($B18="","",LEFT($B18,FIND(" | ",$B18)-1)),"") | D18: =IFERROR(IF($B18="","",MID($B18,FIND(" | ",$B18)+3,FIND(" | ",$B18,FIND(" | ",$B18)+3)-FIND(" | ",$B18)-3)),"") | E18: =IFERROR(IF($B18="","",RIGHT($B18,LEN($B18)-FIND(" | ",$B18,FIND(" | ",$B18)+3)-2)),"")
C19: =IFERROR(IF($B19="","",LEFT($B19,FIND(" | ",$B19)-1)),"") | D19: =IFERROR(IF($B19="","",MID($B19,FIND(" | ",$B19)+3,FIND(" | ",$B19,FIND(" | ",$B19)+3)-FIND(" | ",$B19)-3)),"") | E19: =IFERROR(IF($B19="","",RIGHT($B19,LEN($B19)-FIND(" | ",$B19,FIND(" | ",$B19)+3)-2)),"")
C20: =IFERROR(IF($B20="","",LEFT($B20,FIND(" | ",$B20)-1)),"") | D20: =IFERROR(IF($B20="","",MID($B20,FIND(" | ",$B20)+3,FIND(" | ",$B20,FIND(" | ",$B20)+3)-FIND(" | ",$B20)-3)),"") | E20: =IFERROR(IF($B20="","",RIGHT($B20,LEN($B20)-FIND(" | ",$B20,FIND(" | ",$B20)+3)-2)),"")
C21: =IFERROR(IF($B21="","",LEFT($B21,FIND(" | ",$B21)-1)),"") | D21: =IFERROR(IF($B21="","",MID($B21,FIND(" | ",$B21)+3,FIND(" | ",$B21,FIND(" | ",$B21)+3)-FIND(" | ",$B21)-3)),"") | E21: =IFERROR(IF($B21="","",RIGHT($B21,LEN($B21)-FIND(" | ",$B21,FIND(" | ",$B21)+3)-2)),"")
C22: =IFERROR(IF($B22="","",LEFT($B22,FIND(" | ",$B22)-1)),"") | D22: =IFERROR(IF($B22="","",MID($B22,FIND(" | ",$B22)+3,FIND(" | ",$B22,FIND(" | ",$B22)+3)-FIND(" | ",$B22)-3)),"") | E22: =IFERROR(IF($B22="","",RIGHT($B22,LEN($B22)-FIND(" | ",$B22,FIND(" | ",$B22)+3)-2)),"")
C23: =IFERROR(IF($B23="","",LEFT($B23,FIND(" | ",$B23)-1)),"") | D23: =IFERROR(IF($B23="","",MID($B23,FIND(" | ",$B23)+3,FIND(" | ",$B23,FIND(" | ",$B23)+3)-FIND(" | ",$B23)-3)),"") | E23: =IFERROR(IF($B23="","",RIGHT($B23,LEN($B23)-FIND(" | ",$B23,FIND(" | ",$B23)+3)-2)),"")
C24: =IFERROR(IF($B24="","",LEFT($B24,FIND(" | ",$B24)-1)),"") | D24: =IFERROR(IF($B24="","",MID($B24,FIND(" | ",$B24)+3,FIND(" | ",$B24,FIND(" | ",$B24)+3)-FIND(" | ",$B24)-3)),"") | E24: =IFERROR(IF($B24="","",RIGHT($B24,LEN($B24)-FIND(" | ",$B24,FIND(" | ",$B24)+3)-2)),"")
... C505: =IFERROR(IF($B505="","",LEFT($B505,FIND(" | ",$B505)-1)),"") | D505: =IFERROR(IF($B505="","",MID($B505,FIND(" | ",$B505)+3,FIND(" | ",$B505,FIND(" | ",$B505)+3)-FIND(" | ",$B505)-3)),"") | E505: =IFERROR(IF($B505="","",RIGHT($B505,LEN($B505)-FIND(" | ",$B505,FIND(" | ",$B505)+3)-2)),"")

Sheet CANTIERI
A1: CONTROLLO ECONOMICO E PRODUTTIVO CANTIERI 2026 — REV.14
A2: SELEZIONA COMMESSA | D2: CONTRATTO AGGIORNATO | G2: PERDITE SAL ACCETTATE | J2: VALORE RECUPERABILE | M2: SAL MATURATO | P2: FATTURATO LORDO | S2: SAL NON FATTURATO | V2: RESIDUO LAVORI EFFETTIVO | AA2: MESE | AB2: COSTO MESE | AC2: COSTO CUMULATO
A3: TUTTE | D3: =IF($A$3="TUTTE",SUBTOTAL(109,$J$9:$J$308),IFERROR(INDEX($J$9:$J$308,MATCH($A$3,$C$9:$C$308,0)),0)) -> 425819.41 | G3: =IF($A$3="TUTTE",SUBTOTAL(109,$V$9:$V$308),IFERROR(INDEX($V$9:$V$308,MATCH($A$3,$C$9:$C$308,0)),0)) -> 10000 | J3: =IF($A$3="TUTTE",SUBTOTAL(109,$W$9:$W$308),IFERROR(INDEX($W$9:$W$308,MATCH($A$3,$C$9:$C$308,0)),0)) -> 417819.41 | M3: =IF($A$3="TUTTE",SUBTOTAL(109,$K$9:$K$308),IFERROR(INDEX($K$9:$K$308,MATCH($A$3,$C$9:$C$308,0)),0)) -> 130541.8 | P3: =IF($A$3="TUTTE",SUBTOTAL(109,$L$9:$L$308),IFERROR(INDEX($L$9:$L$308,MATCH($A$3,$C$9:$C$308,0)),0)) -> 134541.8 | S3: =IF($A$3="TUTTE",SUBTOTAL(109,$M$9:$M$308),IFERROR(INDEX($M$9:$M$308,MATCH($A$3,$C$9:$C$308,0)),0)) -> 11000 | V3: =IF($A$3="TUTTE",SUBTOTAL(109,$N$9:$N$308),IFERROR(INDEX($N$9:$N$308,MATCH($A$3,$C$9:$C$308,0)),0)) -> 330048.51 | AA3: Gennaio | AB3: =IF($A$3="","",IF($A$3="TUTTE",SUMIFS('MOVIMENTI 2026'!$N$7:$N$4206,'MOVIMENTI 2026'!$E$7:$E$4206,">="&DATE(PARAMETRI!$B$11,1,1),'MOVIMENTI 2026'!$E$7:$E$4206,"<"&DATE(PARAMETRI!$B$11,2,1))*PARAMETRI!$B$4+SUMIFS('COSTI DIRETTI'!$H$6:$H$505,'COSTI DIRETTI'!$A$6:$A$505,">="&DATE(PARAMETRI!$B$11,1,1),'COSTI DIRETTI'!$A$6:$A$505,"<"&DATE(PARAMETRI!$B$11,2,1)),SUMIFS('MOVIMENTI 2026'!$N$7:$N$4206,'MOVIMENTI 2026'!$B$7:$B$4206,$A$3,'MOVIMENTI 2026'!$E$7:$E$4206,">="&DATE(PARAMETRI!$B$11,1,1),'MOVIMENTI 2026'!$E$7:$E$4206,"<"&DATE(PARAMETRI!$B$11,2,1))*PARAMETRI!$B$4+SUMIFS('COSTI DIRETTI'!$H$6:$H$505,'COSTI DIRETTI'!$C$6:$C$505,$A$3,'COSTI DIRETTI'!$A$6:$A$505,">="&DATE(PARAMETRI!$B$11,1,1),'COSTI DIRETTI'!$A$6:$A$505,"<"&DATE(PARAMETRI!$B$11,2,1)))) -> 5579 | AC3: =IF($A$3="","",$AB3) -> 5579
A4: RESIDUO DA FATTURARE | D4: FATTURATO OLTRE RECUPERABILE | G4: RITENUTE DA SBLOCCARE | J4: COSTO EFFETTIVO CUMULATO | M4: STATO / ALLERTA | P4: AGGIORNATO AL | S4: CANTIERI CRITICI | V4: CANTIERI IN ATTENZIONE | AA4: Febbraio | AB4: =IF($A$3="","",IF($A$3="TUTTE",SUMIFS('MOVIMENTI 2026'!$N$7:$N$4206,'MOVIMENTI 2026'!$E$7:$E$4206,">="&DATE(PARAMETRI!$B$11,2,1),'MOVIMENTI 2026'!$E$7:$E$4206,"<"&DATE(PARAMETRI!$B$11,3,1))*PARAMETRI!$B$4+SUMIFS('COSTI DIRETTI'!$H$6:$H$505,'COSTI DIRETTI'!$A$6:$A$505,">="&DATE(PARAMETRI!$B$11,2,1),'COSTI DIRETTI'!$A$6:$A$505,"<"&DATE(PARAMETRI!$B$11,3,1)),SUMIFS('MOVIMENTI 2026'!$N$7:$N$4206,'MOVIMENTI 2026'!$B$7:$B$4206,$A$3,'MOVIMENTI 2026'!$E$7:$E$4206,">="&DATE(PARAMETRI!$B$11,2,1),'MOVIMENTI 2026'!$E$7:$E$4206,"<"&DATE(PARAMETRI!$B$11,3,1))*PARAMETRI!$B$4+SUMIFS('COSTI DIRETTI'!$H$6:$H$505,'COSTI DIRETTI'!$C$6:$C$505,$A$3,'COSTI DIRETTI'!$A$6:$A$505,">="&DATE(PARAMETRI!$B$11,2,1),'COSTI DIRETTI'!$A$6:$A$505,"<"&DATE(PARAMETRI!$B$11,3,1)))) -> 7494.8 | AC4: =IF($A$3="","",$AC3+$AB4) -> 13073.8
A5: =IF($A$3="TUTTE",SUBTOTAL(109,$BE$9:$BE$308),IFERROR(INDEX($BE$9:$BE$308,MATCH($A$3,$C$9:$C$308,0)),0)) -> 326048.51 | D5: =IF($A$3="TUTTE",SUBTOTAL(109,$BF$9:$BF$308),IFERROR(INDEX($BF$9:$BF$308,MATCH($A$3,$C$9:$C$308,0)),0)) -> 0 | G5: =IF($A$3="TUTTE",SUBTOTAL(109,$O$9:$O$308),IFERROR(INDEX($O$9:$O$308,MATCH($A$3,$C$9:$C$308,0)),0)) -> 3020.46 | J5: =IF($A$3="TUTTE",SUBTOTAL(109,$U$9:$U$308),IFERROR(INDEX($U$9:$U$308,MATCH($A$3,$C$9:$C$308,0)),0)) -> 146627.4 | M5: =IF($A$3="TUTTE","PORTAFOGLIO COMPLESSIVO",IFERROR(INDEX($I$9:$I$308,MATCH($A$3,$C$9:$C$308,0))&" — "&INDEX($A$9:$A$308,MATCH($A$3,$C$9:$C$308,0)),"CODICE NON TROVATO")) -> PORTAFOGLIO COMPLESSIVO | P5: =IF($A$3="TUTTE",IF(COUNT($Y$9:$Y$308)=0,"",MAX($Y$9:$Y$308)),IFERROR(IF(INDEX($Y$9:$Y$308,MATCH($A$3,$C$9:$C$308,0))=0,"",INDEX($Y$9:$Y$308,MATCH($A$3,$C$9:$C$308,0))),"")) -> 46259 | S5: =IF($A$3="TUTTE",SUBTOTAL(109,$BT$9:$BT$308),IF(IFERROR(INDEX($A$9:$A$308,MATCH($A$3,$C$9:$C$308,0)),"")="CRITICO",1,0)) -> 1 | V5: =IF($A$3="TUTTE",SUBTOTAL(109,$BU$9:$BU$308),IF(IFERROR(INDEX($A$9:$A$308,MATCH($A$3,$C$9:$C$308,0)),"")="ATTENZIONE",1,0)) -> 3 | AA5: Marzo | AB5: =IF($A$3="","",IF($A$3="TUTTE",SUMIFS('MOVIMENTI 2026'!$N$7:$N$4206,'MOVIMENTI 2026'!$E$7:$E$4206,">="&DATE(PARAMETRI!$B$11,3,1),'MOVIMENTI 2026'!$E$7:$E$4206,"<"&DATE(PARAMETRI!$B$11,4,1))*PARAMETRI!$B$4+SUMIFS('COSTI DIRETTI'!$H$6:$H$505,'COSTI DIRETTI'!$A$6:$A$505,">="&DATE(PARAMETRI!$B$11,3,1),'COSTI DIRETTI'!$A$6:$A$505,"<"&DATE(PARAMETRI!$B$11,4,1)),SUMIFS('MOVIMENTI 2026'!$N$7:$N$4206,'MOVIMENTI 2026'!$B$7:$B$4206,$A$3,'MOVIMENTI 2026'!$E$7:$E$4206,">="&DATE(PARAMETRI!$B$11,3,1),'MOVIMENTI 2026'!$E$7:$E$4206,"<"&DATE(PARAMETRI!$B$11,4,1))*PARAMETRI!$B$4+SUMIFS('COSTI DIRETTI'!$H$6:$H$505,'COSTI DIRETTI'!$C$6:$C$505,$A$3,'COSTI DIRETTI'!$A$6:$A$505,">="&DATE(PARAMETRI!$B$11,3,1),'COSTI DIRETTI'!$A$6:$A$505,"<"&DATE(PARAMETRI!$B$11,4,1)))) -> 3663.2 | AC5: =IF($A$3="","",$AC4+$AB5) -> 16737
A6: Giallo = selezione/input • Azzurro = calcolo automatico • CANTIERI mostra saldi al 31/12/2025 + movimenti 2026 • AGGIORNATO AL è una data manuale per singola commessa. | AA6: Aprile | AB6: =IF($A$3="","",IF($A$3="TUTTE",SUMIFS('MOVIMENTI 2026'!$N$7:$N$4206,'MOVIMENTI 2026'!$E$7:$E$4206,">="&DATE(PARAMETRI!$B$11,4,1),'MOVIMENTI 2026'!$E$7:$E$4206,"<"&DATE(PARAMETRI!$B$11,5,1))*PARAMETRI!$B$4+SUMIFS('COSTI DIRETTI'!$H$6:$H$505,'COSTI DIRETTI'!$A$6:$A$505,">="&DATE(PARAMETRI!$B$11,4,1),'COSTI DIRETTI'!$A$6:$A$505,"<"&DATE(PARAMETRI!$B$11,5,1)),SUMIFS('MOVIMENTI 2026'!$N$7:$N$4206,'MOVIMENTI 2026'!$B$7:$B$4206,$A$3,'MOVIMENTI 2026'!$E$7:$E$4206,">="&DATE(PARAMETRI!$B$11,4,1),'MOVIMENTI 2026'!$E$7:$E$4206,"<"&DATE(PARAMETRI!$B$11,5,1))*PARAMETRI!$B$4+SUMIFS('COSTI DIRETTI'!$H$6:$H$505,'COSTI DIRETTI'!$C$6:$C$505,$A$3,'COSTI DIRETTI'!$A$6:$A$505,">="&DATE(PARAMETRI!$B$11,4,1),'COSTI DIRETTI'!$A$6:$A$505,"<"&DATE(PARAMETRI!$B$11,5,1)))) -> 3000 | AC6: =IF($A$3="","",$AC5+$AB6) -> 19737
A7: ALLERTE | C7: IDENTIFICAZIONE | J7: CONTRATTO / SAL | P7: TEMPO | R7: ORE / PRODUTTIVITÀ | T7: COSTI DIRETTI / CONSUNTIVO | V7: PERDITE / RECUPERABILE | X7: AZIONI | Y7: CONTROLLO | AA7: Maggio | AB7: =IF($A$3="","",IF($A$3="TUTTE",SUMIFS('MOVIMENTI 2026'!$N$7:$N$4206,'MOVIMENTI 2026'!$E$7:$E$4206,">="&DATE(PARAMETRI!$B$11,5,1),'MOVIMENTI 2026'!$E$7:$E$4206,"<"&DATE(PARAMETRI!$B$11,6,1))*PARAMETRI!$B$4+SUMIFS('COSTI DIRETTI'!$H$6:$H$505,'COSTI DIRETTI'!$A$6:$A$505,">="&DATE(PARAMETRI!$B$11,5,1),'COSTI DIRETTI'!$A$6:$A$505,"<"&DATE(PARAMETRI!$B$11,6,1)),SUMIFS('MOVIMENTI 2026'!$N$7:$N$4206,'MOVIMENTI 2026'!$B$7:$B$4206,$A$3,'MOVIMENTI 2026'!$E$7:$E$4206,">="&DATE(PARAMETRI!$B$11,5,1),'MOVIMENTI 2026'!$E$7:$E$4206,"<"&DATE(PARAMETRI!$B$11,6,1))*PARAMETRI!$B$4+SUMIFS('COSTI DIRETTI'!$H$6:$H$505,'COSTI DIRETTI'!$C$6:$C$505,$A$3,'COSTI DIRETTI'!$A$6:$A$505,">="&DATE(PARAMETRI!$B$11,5,1),'COSTI DIRETTI'!$A$6:$A$505,"<"&DATE(PARAMETRI!$B$11,6,1)))) -> 0 | AC7: =IF($A$3="","",$AC6+$AB7) -> 19737
A8: ALLERTA | B8: MOTIVO DELL'ALLERTA | C8: CODICE COMMESSA | D8: CLIENTE | E8: DESCRIZIONE | F8: RAMO DI ATTIVITÀ | G8: TECNICO | H8: PREPOSTO | I8: STATO CANTIERE | J8: CONTRATTO AGGIORNATO | K8: SAL MATURATO | L8: FATTURATO LORDO | M8: SAL NON FATTURATO | N8: RESIDUO LAVORI | O8: RITENUTE DA SBLOCCARE | P8: SAL % / TEMPO % / SCOSTAMENTO - RISCHIO RITARDO DELLA COMMESSA | Q8: GIORNI DI RITARDO PRODUTTIVO | R8: ORE PREVISTE / USATE / RESIDUE | S8: % ORE / % SAL / SCOSTAMENTO - RISCHIO CONSUMO ECCESSIVO DI ORE | T8: COSTI DIRETTI: BUDGET / SOSTENUTI / RESIDUO-SFORAMENTO | U8: COSTO EFFETTIVO CUMULATO | V8: PERDITE SAL ACCETTATE | W8: VALORE RECUPERABILE | X8: NOTE / AZIONE | Y8: AGGIORNATO AL | AA8: Giugno | AB8: =IF($A$3="","",IF($A$3="TUTTE",SUMIFS('MOVIMENTI 2026'!$N$7:$N$4206,'MOVIMENTI 2026'!$E$7:$E$4206,">="&DATE(PARAMETRI!$B$11,6,1),'MOVIMENTI 2026'!$E$7:$E$4206,"<"&DATE(PARAMETRI!$B$11,7,1))*PARAMETRI!$B$4+SUMIFS('COSTI DIRETTI'!$H$6:$H$505,'COSTI DIRETTI'!$A$6:$A$505,">="&DATE(PARAMETRI!$B$11,6,1),'COSTI DIRETTI'!$A$6:$A$505,"<"&DATE(PARAMETRI!$B$11,7,1)),SUMIFS('MOVIMENTI 2026'!$N$7:$N$4206,'MOVIMENTI 2026'!$B$7:$B$4206,$A$3,'MOVIMENTI 2026'!$E$7:$E$4206,">="&DATE(PARAMETRI!$B$11,6,1),'MOVIMENTI 2026'!$E$7:$E$4206,"<"&DATE(PARAMETRI!$B$11,7,1))*PARAMETRI!$B$4+SUMIFS('COSTI DIRETTI'!$H$6:$H$505,'COSTI DIRETTI'!$C$6:$C$505,$A$3,'COSTI DIRETTI'!$A$6:$A$505,">="&DATE(PARAMETRI!$B$11,6,1),'COSTI DIRETTI'!$A$6:$A$505,"<"&DATE(PARAMETRI!$B$11,7,1)))) -> 0 | AC8: =IF($A$3="","",$AC7+$AB8) -> 19737
A9: =IFERROR(IF($C9="","",IF(OR($BF9>0,$V9>$J9,AND(ISNUMBER($Q9),$Q9>0),AND($BI9<>"",$BI9<-PARAMETRI!$B$6),AND($BM9<>"",$BM9>=1),AND($BN9<>"",$BN9>PARAMETRI!$B$8),AND(ISNUMBER($BR9),$BR9>0)),"CRITICO",IF(OR($AZ9="",LEFT($C9,5)="TEMP",$BJ9="",$BO9="",ANAGRAFICA!$I6="",ANAGRAFICA!$J6="",$Y9="",AND(OR($I9="Finito ritenute non previste",$I9="Finito con sblocco ritenute",$I9="Finito senza sblocco ritenute"),ANAGRAFICA!$K6=""),OR(AND(ANAGRAFICA!$T6<>"",ANAGRAFICA!$J6<>ANAGRAFICA!$T6,OR(ANAGRAFICA!$R6="",ANAGRAFICA!$R6="Nessuna variazione")),AND(ANAGRAFICA!$J6="",ANAGRAFICA!$R6<>"",ANAGRAFICA!$R6<>"Nessuna variazione")),AND($BI9<>"",$BI9<-PARAMETRI!$B$5),AND($BN9<>"",$BN9>PARAMETRI!$B$7),AND($W9>0,$M9>$W9*PARAMETRI!$B$9),AND($O9>0,OR($I9="Finito ritenute non previste",$I9="Finito con sblocco ritenute",$I9="Finito senza sblocco ritenute")),AND($BA9>0,$BO9>0,$BP9=0),AND(OR($I9="Finito ritenute non previste",$I9="Finito con sblocco ritenute",$I9="Finito senza sblocco ritenute"),$W9>0,$N9>$W9*PARAMETRI!$B$9),$V9>0),"ATTENZIONE","REGOLARE"))),"ATTENZIONE") -> CRITICO | B9: =IFERROR(IF($C9="","",IF($BF9>0,"FATTURATO OLTRE VALORE RECUPERABILE; ","")&IF($V9>$J9,"PERDITE ACCETTATE OLTRE CONTRATTO; ","")&IF($V9>0,"PERDITA SAL ACCETTATA (€ "&TEXT($V9,"#,##0.00")&"); ","")&IF(AND(ISNUMBER($Q9),$Q9>0),"RITARDO PRODUTTIVO ("&TEXT($Q9,"0")&" GG); ","")&IF(AND($BI9<>"",$BI9<-PARAMETRI!$B$5),"AVANZAMENTO PIÙ LENTO DEL TEMPO; ","")&IF(AND($BM9<>"",$BM9>1),"ORE OLTRE BUDGET; ","")&IF(AND($BM9<>"",$BM9=1),"ORE PREVENTIVATE ESAURITE; ","")&IF(AND($BN9<>"",$BN9>PARAMETRI!$B$7),"CONSUMO ORE SUPERIORE ALL'AVANZAMENTO; ","")&IF(AND(ISNUMBER($BR9),$BR9>0),"COSTI DIRETTI OLTRE BUDGET; ","")&IF(AND($W9>0,$M9>$W9*PARAMETRI!$B$9),"SAL MATURATO NON FATTURATO; ","")&IF(AND($O9>0,OR($I9="Finito ritenute non previste",$I9="Finito con sblocco ritenute",$I9="Finito senza sblocco ritenute")),"RITENUTE DA SBLOCCARE; ","")&IF(AND($BA9>0,$BO9>0,$BP9=0),"COSTI DIRETTI NON REGISTRATI; ","")&IF(AND(OR($I9="Finito ritenute non previste",$I9="Finito con sblocco ritenute",$I9="Finito senza sblocco ritenute"),$W9>0,$N9>$W9*PARAMETRI!$B$9),"CANTIERE FINITO CON RESIDUO LAVORI; ","")&IF(AND(OR($I9="Finito ritenute non previste",$I9="Finito con sblocco ritenute",$I9="Finito senza sblocco ritenute"),ANAGRAFICA!$K6=""),"DATA FINE EFFETTIVA MANCANTE; ","")&IF(OR(AND(ANAGRAFICA!$T6<>"",ANAGRAFICA!$J6<>ANAGRAFICA!$T6,OR(ANAGRAFICA!$R6="",ANAGRAFICA!$R6="Nessuna variazione")),AND(ANAGRAFICA!$J6="",ANAGRAFICA!$R6<>"",ANAGRAFICA!$R6<>"Nessuna variazione")),"GESTIONE DATA FINE INCOMPLETA; ","")&IF($Y9="","AGGIORNATO AL MANCANTE; ","")&IF(OR($AZ9="",$BJ9="",$BO9="",ANAGRAFICA!$I6="",ANAGRAFICA!$J6=""),"DATI PREVISIONALI INCOMPLETI; ","")&IF(LEFT($C9,5)="TEMP","CODICE COMMESSA TEMPORANEO; ","")),"DATI INCOMPLETI; ") -> PERDITA SAL ACCETTATA (€ 2000,000); AVANZAMENTO PIÙ LENTO DEL TEMPO; CONSUMO ORE SUPERIORE ALL'AVANZAMENTO; COSTI DIRETTI OLTRE BUDGET; | C9: =IF(ANAGRAFICA!$B6="","",ANAGRAFICA!$B6) -> C042 | D9: =IF($C9="","",ANAGRAFICA!$C6) -> CARRON BAU | E9: =IF($C9="","",ANAGRAFICA!$D6) -> MURATURE IN LATERIZIO C/O COSMO SPA - PESCHIERA DEL GARDA | F9: =IF($C9="","",ANAGRAFICA!$E6) -> MURATURA | G9: =IF($C9="","",ANAGRAFICA!$F6) -> DAVIDE | H9: =IF($C9="","",ANAGRAFICA!$G6) -> AHMET MOUSTAFA | I9: =IF($C9="","",ANAGRAFICA!$L6) -> In corso | J9: =IF($C9="","",$AZ9) -> 143061.41 | K9: =IF($C9="","",$BA9) -> 42770.9 | L9: =IF($C9="","",$BB9) -> 42770.9 | M9: =IF($C9="","",MAX($BA9-$BB9,0)) -> 0 | N9: =IF(OR($C9="",$W9=""),"",MAX($W9-$BA9,0)) -> 98290.51 | O9: =IF($C9="","",MAX($BC9-$BD9,0)) -> 1510.23 | P9: =IF(OR($C9="",$BG9="",$BH9="",$BI9=""),"",TEXT($BG9,"0.0%")&" / "&TEXT($BH9,"0.0%")&" / "&TEXT($BI9,"0.0%")) -> 30% / 100% / -70% | Q9: =IF(OR($C9="",'BUDGET COMMESSA'!$D6="",'BUDGET COMMESSA'!$D6<=0,ANAGRAFICA!$J6=""),"",IF(OR($I9="Finito ritenute non previste",$I9="Finito con sblocco ritenute",$I9="Finito senza sblocco ritenute"),0,IF(AND($BK9>=$BJ9,ANAGRAFICA!$R6="Ritardo produttivo FIDA"),IF(ANAGRAFICA!$T6<>"",MAX(0,ANAGRAFICA!$J6-ANAGRAFICA!$T6),MAX(0,$Y9-ANAGRAFICA!$J6)),0))) -> 0 | R9: =IF(OR($C9="",$BJ9=""),"",TEXT($BJ9,"#,##0.00")&" / "&TEXT($BK9,"#,##0.00")&" / "&TEXT($BL9,"#,##0.00")) -> 1800,000 / 680,000 / 1120,000 | S9: =IF(OR($C9="",$BM9="",$BG9="",$BN9=""),"",TEXT($BM9,"0.0%")&" / "&TEXT($BG9,"0.0%")&" / "&TEXT($BN9,"0.0%")) -> 38% / 30% / 07% | T9: =IF(OR($C9="",$BO9=""),"",IF($BR9>0,"BUDGET € "&TEXT($BO9,"#,##0.00")&" | SOSTENUTI € "&TEXT($BP9,"#,##0.00")&" | SFORAMENTO € "&TEXT($BR9,"#,##0.00"),"BUDGET € "&TEXT($BO9,"#,##0.00")&" | SOSTENUTI € "&TEXT($BP9,"#,##0.00")&" | RESIDUO € "&TEXT($BQ9,"#,##0.00"))) -> BUDGET € 31308,000 | SOSTENUTI € 32308,000 | SFORAMENTO € 1000,000 | U9: =IF($C9="","",$BS9) -> 63445.2 | V9: =IF($C9="","",$BV9) -> 2000 | W9: =IF(OR($C9="",$AZ9=""),"",MAX($AZ9-$BV9,0)) -> 141061.41 | Y9: 46259 | AA9: Luglio | AB9: =IF($A$3="","",IF($A$3="TUTTE",SUMIFS('MOVIMENTI 2026'!$N$7:$N$4206,'MOVIMENTI 2026'!$E$7:$E$4206,">="&DATE(PARAMETRI!$B$11,7,1),'MOVIMENTI 2026'!$E$7:$E$4206,"<"&DATE(PARAMETRI!$B$11,8,1))*PARAMETRI!$B$4+SUMIFS('COSTI DIRETTI'!$H$6:$H$505,'COSTI DIRETTI'!$A$6:$A$505,">="&DATE(PARAMETRI!$B$11,7,1),'COSTI DIRETTI'!$A$6:$A$505,"<"&DATE(PARAMETRI!$B$11,8,1)),SUMIFS('MOVIMENTI 2026'!$N$7:$N$4206,'MOVIMENTI 2026'!$B$7:$B$4206,$A$3,'MOVIMENTI 2026'!$E$7:$E$4206,">="&DATE(PARAMETRI!$B$11,7,1),'MOVIMENTI 2026'!$E$7:$E$4206,"<"&DATE(PARAMETRI!$B$11,8,1))*PARAMETRI!$B$4+SUMIFS('COSTI DIRETTI'!$H$6:$H$505,'COSTI DIRETTI'!$C$6:$C$505,$A$3,'COSTI DIRETTI'!$A$6:$A$505,">="&DATE(PARAMETRI!$B$11,7,1),'COSTI DIRETTI'!$A$6:$A$505,"<"&DATE(PARAMETRI!$B$11,8,1)))) -> 38137.2 | AC9: =IF($A$3="","",$AC8+$AB9) -> 57874.2 | AZ9: =IF($C9="","",ANAGRAFICA!$P6) -> 143061.41 | BA9: =IF($C9="","",SUMIF('MOVIMENTI 2026'!$B$7:$B$4206,$C9,'MOVIMENTI 2026'!$I$7:$I$4206)+SUMIF('SALDI AL 31.12.2025'!$A$6:$A$505,$C9,'SALDI AL 31.12.2025'!$C$6:$C$505)) -> 42770.9 | BB9: =IF($C9="","",SUMIF('MOVIMENTI 2026'!$B$7:$B$4206,$C9,'MOVIMENTI 2026'!$J$7:$J$4206)+SUMIF('SALDI AL 31.12.2025'!$A$6:$A$505,$C9,'SALDI AL 31.12.2025'!$D$6:$D$505)) -> 42770.9 | BC9: =IF($C9="","",SUMIF('MOVIMENTI 2026'!$B$7:$B$4206,$C9,'MOVIMENTI 2026'!$K$7:$K$4206)+SUMIF('SALDI AL 31.12.2025'!$A$6:$A$505,$C9,'SALDI AL 31.12.2025'!$E$6:$E$505)) -> 2010.23 | BD9: =IF($C9="","",SUMIF('MOVIMENTI 2026'!$B$7:$B$4206,$C9,'MOVIMENTI 2026'!$L$7:$L$4206)+SUMIF('SALDI AL 31.12.2025'!$A$6:$A$505,$C9,'SALDI AL 31.12.2025'!$F$6:$F$505)) -> 500 | BE9: =IF(OR($C9="",$W9=""),"",MAX($W9-$BB9,0)) -> 98290.51 | BF9: =IF(OR($C9="",$W9=""),"",MAX($BB9-$W9,0)) -> 0 | BG9: =IF(OR($C9="",$W9<=0),"",$BA9/$W9) -> 0.30320766 | BH9: =IFERROR(IF(OR($C9="",ANAGRAFICA!$I6="",ANAGRAFICA!$J6="",ANAGRAFICA!$J6<=ANAGRAFICA!$I6,$Y9=""),"",IF(OR($I9="Finito ritenute non previste",$I9="Finito con sblocco ritenute",$I9="Finito senza sblocco ritenute"),1,MAX(0,MIN(1,($Y9-ANAGRAFICA!$I6)/(ANAGRAFICA!$J6-ANAGRAFICA!$I6))))),"") -> 1 | BI9: =IF(OR($C9="",$BG9="",$BH9=""),"",$BG9-$BH9) -> -0.69679234 | BJ9: =IFERROR(IF($C9="","",'BUDGET COMMESSA'!$D6),"") -> 1800 | BK9: =IF($C9="","",SUMIF('MOVIMENTI 2026'!$B$7:$B$4206,$C9,'MOVIMENTI 2026'!$N$7:$N$4206)+SUMIF('SALDI AL 31.12.2025'!$A$6:$A$505,$C9,'SALDI AL 31.12.2025'!$H$6:$H$505)) -> 680 | BL9: =IF(OR($C9="",$BJ9=""),"",MAX($BJ9-$BK9,0)) -> 1120 | BM9: =IF(OR($C9="",$BJ9<=0),"",$BK9/$BJ9) -> 0.37777778 | BN9: =IF(OR($C9="",$BM9="",$BG9=""),"",$BM9-$BG9) -> 0.074570118 | BO9: =IFERROR(IF($C9="","",'BUDGET COMMESSA'!$G6),"") -> 31308 | BP9: =IF($C9="","",SUMIF('COSTI DIRETTI'!$C$6:$C$505,$C9,'COSTI DIRETTI'!$H$6:$H$505)+SUMIF('SALDI AL 31.12.2025'!$A$6:$A$505,$C9,'SALDI AL 31.12.2025'!$I$6:$I$505)) -> 32308 | BQ9: =IF(OR($C9="",$BO9=""),"",MAX($BO9-$BP9,0)) -> 0 | BR9: =IF(OR($C9="",$BO9=""),"",MAX($BP9-$BO9,0)) -> 1000 | BS9: =IF($C9="","",$BK9*PARAMETRI!$B$4+$BP9) -> 63445.2 | BT9: =IF($A9="CRITICO",1,0) -> 1 | BU9: =IF($A9="ATTENZIONE",1,0) -> 0 | BV9: =IF($C9="","",SUMIF('MOVIMENTI 2026'!$B$7:$B$4206,$C9,'MOVIMENTI 2026'!$P$7:$P$4206)+SUMIF('SALDI AL 31.12.2025'!$A$6:$A$505,$C9,'SALDI AL 31.12.2025'!$G$6:$G$505)) -> 2000
A10: =IFERROR(IF($C10="","",IF(OR($BF10>0,$V10>$J10,AND(ISNUMBER($Q10),$Q10>0),AND($BI10<>"",$BI10<-PARAMETRI!$B$6),AND($BM10<>"",$BM10>=1),AND($BN10<>"",$BN10>PARAMETRI!$B$8),AND(ISNUMBER($BR10),$BR10>0)),"CRITICO",IF(OR($AZ10="",LEFT($C10,5)="TEMP",$BJ10="",$BO10="",ANAGRAFICA!$I7="",ANAGRAFICA!$J7="",$Y10="",AND(OR($I10="Finito ritenute non previste",$I10="Finito con sblocco ritenute",$I10="Finito senza sblocco ritenute"),ANAGRAFICA!$K7=""),OR(AND(ANAGRAFICA!$T7<>"",ANAGRAFICA!$J7<>ANAGRAFICA!$T7,OR(ANAGRAFICA!$R7="",ANAGRAFICA!$R7="Nessuna variazione")),AND(ANAGRAFICA!$J7="",ANAGRAFICA!$R7<>"",ANAGRAFICA!$R7<>"Nessuna variazione")),AND($BI10<>"",$BI10<-PARAMETRI!$B$5),AND($BN10<>"",$BN10>PARAMETRI!$B$7),AND($W10>0,$M10>$W10*PARAMETRI!$B$9),AND($O10>0,OR($I10="Finito ritenute non previste",$I10="Finito con sblocco ritenute",$I10="Finito senza sblocco ritenute")),AND($BA10>0,$BO10>0,$BP10=0),AND(OR($I10="Finito ritenute non previste",$I10="Finito con sblocco ritenute",$I10="Finito senza sblocco ritenute"),$W10>0,$N10>$W10*PARAMETRI!$B$9),$V10>0),"ATTENZIONE","REGOLARE"))),"ATTENZIONE") -> ATTENZIONE | B10: =IFERROR(IF($C10="","",IF($BF10>0,"FATTURATO OLTRE VALORE RECUPERABILE; ","")&IF($V10>$J10,"PERDITE ACCETTATE OLTRE CONTRATTO; ","")&IF($V10>0,"PERDITA SAL ACCETTATA (€ "&TEXT($V10,"#,##0.00")&"); ","")&IF(AND(ISNUMBER($Q10),$Q10>0),"RITARDO PRODUTTIVO ("&TEXT($Q10,"0")&" GG); ","")&IF(AND($BI10<>"",$BI10<-PARAMETRI!$B$5),"AVANZAMENTO PIÙ LENTO DEL TEMPO; ","")&IF(AND($BM10<>"",$BM10>1),"ORE OLTRE BUDGET; ","")&IF(AND($BM10<>"",$BM10=1),"ORE PREVENTIVATE ESAURITE; ","")&IF(AND($BN10<>"",$BN10>PARAMETRI!$B$7),"CONSUMO ORE SUPERIORE ALL'AVANZAMENTO; ","")&IF(AND(ISNUMBER($BR10),$BR10>0),"COSTI DIRETTI OLTRE BUDGET; ","")&IF(AND($W10>0,$M10>$W10*PARAMETRI!$B$9),"SAL MATURATO NON FATTURATO; ","")&IF(AND($O10>0,OR($I10="Finito ritenute non previste",$I10="Finito con sblocco ritenute",$I10="Finito senza sblocco ritenute")),"RITENUTE DA SBLOCCARE; ","")&IF(AND($BA10>0,$BO10>0,$BP10=0),"COSTI DIRETTI NON REGISTRATI; ","")&IF(AND(OR($I10="Finito ritenute non previste",$I10="Finito con sblocco ritenute",$I10="Finito senza sblocco ritenute"),$W10>0,$N10>$W10*PARAMETRI!$B$9),"CANTIERE FINITO CON RESIDUO LAVORI; ","")&IF(AND(OR($I10="Finito ritenute non previste",$I10="Finito con sblocco ritenute",$I10="Finito senza sblocco ritenute"),ANAGRAFICA!$K7=""),"DATA FINE EFFETTIVA MANCANTE; ","")&IF(OR(AND(ANAGRAFICA!$T7<>"",ANAGRAFICA!$J7<>ANAGRAFICA!$T7,OR(ANAGRAFICA!$R7="",ANAGRAFICA!$R7="Nessuna variazione")),AND(ANAGRAFICA!$J7="",ANAGRAFICA!$R7<>"",ANAGRAFICA!$R7<>"Nessuna variazione")),"GESTIONE DATA FINE INCOMPLETA; ","")&IF($Y10="","AGGIORNATO AL MANCANTE; ","")&IF(OR($AZ10="",$BJ10="",$BO10="",ANAGRAFICA!$I7="",ANAGRAFICA!$J7=""),"DATI PREVISIONALI INCOMPLETI; ","")&IF(LEFT($C10,5)="TEMP","CODICE COMMESSA TEMPORANEO; ","")),"DATI INCOMPLETI; ") -> PERDITA SAL ACCETTATA (€ 1000,000); SAL MATURATO NON FATTURATO; CANTIERE FINITO CON RESIDUO LAVORI; DATA FINE EFFETTIVA MANCANTE; AGGIORNATO AL MANCANTE; | C10: =IF(ANAGRAFICA!$B7="","",ANAGRAFICA!$B7) -> C011 | D10: =IF($C10="","",ANAGRAFICA!$C7) -> CARRON | E10: =IF($C10="","",ANAGRAFICA!$D7) -> ZABARELLA 2023 - COD. CANTIERE 774 | F10: =IF($C10="","",ANAGRAFICA!$E7) -> MURATURA+ECONOMIE | G10: =IF($C10="","",ANAGRAFICA!$F7) -> ALBAN | H10: =IF($C10="","",ANAGRAFICA!$G7) -> NA | I10: =IF($C10="","",ANAGRAFICA!$L7) -> Finito ritenute non previste | J10: =IF($C10="","",$AZ10) -> 182758 | K10: =IF($C10="","",$BA10) -> 20000 | L10: =IF($C10="","",$BB10) -> 9000 | M10: =IF($C10="","",MAX($BA10-$BB10,0)) -> 11000 | N10: =IF(OR($C10="",$W10=""),"",MAX($W10-$BA10,0)) -> 161758 | O10: =IF($C10="","",MAX($BC10-$BD10,0)) -> 0 | P10: =IF(OR($C10="",$BG10="",$BH10="",$BI10=""),"",TEXT($BG10,"0.0%")&" / "&TEXT($BH10,"0.0%")&" / "&TEXT($BI10,"0.0%")) | Q10: =IF(OR($C10="",'BUDGET COMMESSA'!$D7="",'BUDGET COMMESSA'!$D7<=0,ANAGRAFICA!$J7=""),"",IF(OR($I10="Finito ritenute non previste",$I10="Finito con sblocco ritenute",$I10="Finito senza sblocco ritenute"),0,IF(AND($BK10>=$BJ10,ANAGRAFICA!$R7="Ritardo produttivo FIDA"),IF(ANAGRAFICA!$T7<>"",MAX(0,ANAGRAFICA!$J7-ANAGRAFICA!$T7),MAX(0,$Y10-ANAGRAFICA!$J7)),0))) | R10: =IF(OR($C10="",$BJ10=""),"",TEXT($BJ10,"#,##0.00")&" / "&TEXT($BK10,"#,##0.00")&" / "&TEXT($BL10,"#,##0.00")) -> ,000 / ,000 / ,000 | S10: =IF(OR($C10="",$BM10="",$BG10="",$BN10=""),"",TEXT($BM10,"0.0%")&" / "&TEXT($BG10,"0.0%")&" / "&TEXT($BN10,"0.0%")) | T10: =IF(OR($C10="",$BO10=""),"",IF($BR10>0,"BUDGET € "&TEXT($BO10,"#,##0.00")&" | SOSTENUTI € "&TEXT($BP10,"#,##0.00")&" | SFORAMENTO € "&TEXT($BR10,"#,##0.00"),"BUDGET € "&TEXT($BO10,"#,##0.00")&" | SOSTENUTI € "&TEXT($BP10,"#,##0.00")&" | RESIDUO € "&TEXT($BQ10,"#,##0.00"))) -> BUDGET € ,000 | SOSTENUTI € ,000 | RESIDUO € ,000 | U10: =IF($C10="","",$BS10) -> 0 | V10: =IF($C10="","",$BV10) -> 1000 | W10: =IF(OR($C10="",$AZ10=""),"",MAX($AZ10-$BV10,0)) -> 181758 | AA10: Agosto | AB10: =IF($A$3="","",IF($A$3="TUTTE",SUMIFS('MOVIMENTI 2026'!$N$7:$N$4206,'MOVIMENTI 2026'!$E$7:$E$4206,">="&DATE(PARAMETRI!$B$11,8,1),'MOVIMENTI 2026'!$E$7:$E$4206,"<"&DATE(PARAMETRI!$B$11,9,1))*PARAMETRI!$B$4+SUMIFS('COSTI DIRETTI'!$H$6:$H$505,'COSTI DIRETTI'!$A$6:$A$505,">="&DATE(PARAMETRI!$B$11,8,1),'COSTI DIRETTI'!$A$6:$A$505,"<"&DATE(PARAMETRI!$B$11,9,1)),SUMIFS('MOVIMENTI 2026'!$N$7:$N$4206,'MOVIMENTI 2026'!$B$7:$B$4206,$A$3,'MOVIMENTI 2026'!$E$7:$E$4206,">="&DATE(PARAMETRI!$B$11,8,1),'MOVIMENTI 2026'!$E$7:$E$4206,"<"&DATE(PARAMETRI!$B$11,9,1))*PARAMETRI!$B$4+SUMIFS('COSTI DIRETTI'!$H$6:$H$505,'COSTI DIRETTI'!$C$6:$C$505,$A$3,'COSTI DIRETTI'!$A$6:$A$505,">="&DATE(PARAMETRI!$B$11,8,1),'COSTI DIRETTI'!$A$6:$A$505,"<"&DATE(PARAMETRI!$B$11,9,1)))) -> 25308 | AC10: =IF($A$3="","",$AC9+$AB10) -> 83182.2 | AZ10: =IF($C10="","",ANAGRAFICA!$P7) -> 182758 | BA10: =IF($C10="","",SUMIF('MOVIMENTI 2026'!$B$7:$B$4206,$C10,'MOVIMENTI 2026'!$I$7:$I$4206)+SUMIF('SALDI AL 31.12.2025'!$A$6:$A$505,$C10,'SALDI AL 31.12.2025'!$C$6:$C$505)) -> 20000 | BB10: =IF($C10="","",SUMIF('MOVIMENTI 2026'!$B$7:$B$4206,$C10,'MOVIMENTI 2026'!$J$7:$J$4206)+SUMIF('SALDI AL 31.12.2025'!$A$6:$A$505,$C10,'SALDI AL 31.12.2025'!$D$6:$D$505)) -> 9000 | BC10: =IF($C10="","",SUMIF('MOVIMENTI 2026'!$B$7:$B$4206,$C10,'MOVIMENTI 2026'!$K$7:$K$4206)+SUMIF('SALDI AL 31.12.2025'!$A$6:$A$505,$C10,'SALDI AL 31.12.2025'!$E$6:$E$505)) -> 0 | BD10: =IF($C10="","",SUMIF('MOVIMENTI 2026'!$B$7:$B$4206,$C10,'MOVIMENTI 2026'!$L$7:$L$4206)+SUMIF('SALDI AL 31.12.2025'!$A$6:$A$505,$C10,'SALDI AL 31.12.2025'!$F$6:$F$505)) -> 0 | BE10: =IF(OR($C10="",$W10=""),"",MAX($W10-$BB10,0)) -> 172758 | BF10: =IF(OR($C10="",$W10=""),"",MAX($BB10-$W10,0)) -> 0 | BG10: =IF(OR($C10="",$W10<=0),"",$BA10/$W10) -> 0.11003642 | BH10: =IFERROR(IF(OR($C10="",ANAGRAFICA!$I7="",ANAGRAFICA!$J7="",ANAGRAFICA!$J7<=ANAGRAFICA!$I7,$Y10=""),"",IF(OR($I10="Finito ritenute non previste",$I10="Finito con sblocco ritenute",$I10="Finito senza sblocco ritenute"),1,MAX(0,MIN(1,($Y10-ANAGRAFICA!$I7)/(ANAGRAFICA!$J7-ANAGRAFICA!$I7))))),"") | BI10: =IF(OR($C10="",$BG10="",$BH10=""),"",$BG10-$BH10) | BJ10: =IFERROR(IF($C10="","",'BUDGET COMMESSA'!$D7),"") -> 0 | BK10: =IF($C10="","",SUMIF('MOVIMENTI 2026'!$B$7:$B$4206,$C10,'MOVIMENTI 2026'!$N$7:$N$4206)+SUMIF('SALDI AL 31.12.2025'!$A$6:$A$505,$C10,'SALDI AL 31.12.2025'!$H$6:$H$505)) -> 0 | BL10: =IF(OR($C10="",$BJ10=""),"",MAX($BJ10-$BK10,0)) -> 0 | BM10: =IF(OR($C10="",$BJ10<=0),"",$BK10/$BJ10) | BN10: =IF(OR($C10="",$BM10="",$BG10=""),"",$BM10-$BG10) | BO10: =IFERROR(IF($C10="","",'BUDGET COMMESSA'!$G7),"") -> 0 | BP10: =IF($C10="","",SUMIF('COSTI DIRETTI'!$C$6:$C$505,$C10,'COSTI DIRETTI'!$H$6:$H$505)+SUMIF('SALDI AL 31.12.2025'!$A$6:$A$505,$C10,'SALDI AL 31.12.2025'!$I$6:$I$505)) -> 0 | BQ10: =IF(OR($C10="",$BO10=""),"",MAX($BO10-$BP10,0)) -> 0 | BR10: =IF(OR($C10="",$BO10=""),"",MAX($BP10-$BO10,0)) -> 0 | BS10: =IF($C10="","",$BK10*PARAMETRI!$B$4+$BP10) -> 0 | BT10: =IF($A10="CRITICO",1,0) -> 0 | BU10: =IF($A10="ATTENZIONE",1,0) -> 1 | BV10: =IF($C10="","",SUMIF('MOVIMENTI 2026'!$B$7:$B$4206,$C10,'MOVIMENTI 2026'!$P$7:$P$4206)+SUMIF('SALDI AL 31.12.2025'!$A$6:$A$505,$C10,'SALDI AL 31.12.2025'!$G$6:$G$505)) -> 1000
A11: =IFERROR(IF($C11="","",IF(OR($BF11>0,$V11>$J11,AND(ISNUMBER($Q11),$Q11>0),AND($BI11<>"",$BI11<-PARAMETRI!$B$6),AND($BM11<>"",$BM11>=1),AND($BN11<>"",$BN11>PARAMETRI!$B$8),AND(ISNUMBER($BR11),$BR11>0)),"CRITICO",IF(OR($AZ11="",LEFT($C11,5)="TEMP",$BJ11="",$BO11="",ANAGRAFICA!$I8="",ANAGRAFICA!$J8="",$Y11="",AND(OR($I11="Finito ritenute non previste",$I11="Finito con sblocco ritenute",$I11="Finito senza sblocco ritenute"),ANAGRAFICA!$K8=""),OR(AND(ANAGRAFICA!$T8<>"",ANAGRAFICA!$J8<>ANAGRAFICA!$T8,OR(ANAGRAFICA!$R8="",ANAGRAFICA!$R8="Nessuna variazione")),AND(ANAGRAFICA!$J8="",ANAGRAFICA!$R8<>"",ANAGRAFICA!$R8<>"Nessuna variazione")),AND($BI11<>"",$BI11<-PARAMETRI!$B$5),AND($BN11<>"",$BN11>PARAMETRI!$B$7),AND($W11>0,$M11>$W11*PARAMETRI!$B$9),AND($O11>0,OR($I11="Finito ritenute non previste",$I11="Finito con sblocco ritenute",$I11="Finito senza sblocco ritenute")),AND($BA11>0,$BO11>0,$BP11=0),AND(OR($I11="Finito ritenute non previste",$I11="Finito con sblocco ritenute",$I11="Finito senza sblocco ritenute"),$W11>0,$N11>$W11*PARAMETRI!$B$9),$V11>0),"ATTENZIONE","REGOLARE"))),"ATTENZIONE") -> ATTENZIONE | B11: =IFERROR(IF($C11="","",IF($BF11>0,"FATTURATO OLTRE VALORE RECUPERABILE; ","")&IF($V11>$J11,"PERDITE ACCETTATE OLTRE CONTRATTO; ","")&IF($V11>0,"PERDITA SAL ACCETTATA (€ "&TEXT($V11,"#,##0.00")&"); ","")&IF(AND(ISNUMBER($Q11),$Q11>0),"RITARDO PRODUTTIVO ("&TEXT($Q11,"0")&" GG); ","")&IF(AND($BI11<>"",$BI11<-PARAMETRI!$B$5),"AVANZAMENTO PIÙ LENTO DEL TEMPO; ","")&IF(AND($BM11<>"",$BM11>1),"ORE OLTRE BUDGET; ","")&IF(AND($BM11<>"",$BM11=1),"ORE PREVENTIVATE ESAURITE; ","")&IF(AND($BN11<>"",$BN11>PARAMETRI!$B$7),"CONSUMO ORE SUPERIORE ALL'AVANZAMENTO; ","")&IF(AND(ISNUMBER($BR11),$BR11>0),"COSTI DIRETTI OLTRE BUDGET; ","")&IF(AND($W11>0,$M11>$W11*PARAMETRI!$B$9),"SAL MATURATO NON FATTURATO; ","")&IF(AND($O11>0,OR($I11="Finito ritenute non previste",$I11="Finito con sblocco ritenute",$I11="Finito senza sblocco ritenute")),"RITENUTE DA SBLOCCARE; ","")&IF(AND($BA11>0,$BO11>0,$BP11=0),"COSTI DIRETTI NON REGISTRATI; ","")&IF(AND(OR($I11="Finito ritenute non previste",$I11="Finito con sblocco ritenute",$I11="Finito senza sblocco ritenute"),$W11>0,$N11>$W11*PARAMETRI!$B$9),"CANTIERE FINITO CON RESIDUO LAVORI; ","")&IF(AND(OR($I11="Finito ritenute non previste",$I11="Finito con sblocco ritenute",$I11="Finito senza sblocco ritenute"),ANAGRAFICA!$K8=""),"DATA FINE EFFETTIVA MANCANTE; ","")&IF(OR(AND(ANAGRAFICA!$T8<>"",ANAGRAFICA!$J8<>ANAGRAFICA!$T8,OR(ANAGRAFICA!$R8="",ANAGRAFICA!$R8="Nessuna variazione")),AND(ANAGRAFICA!$J8="",ANAGRAFICA!$R8<>"",ANAGRAFICA!$R8<>"Nessuna variazione")),"GESTIONE DATA FINE INCOMPLETA; ","")&IF($Y11="","AGGIORNATO AL MANCANTE; ","")&IF(OR($AZ11="",$BJ11="",$BO11="",ANAGRAFICA!$I8="",ANAGRAFICA!$J8=""),"DATI PREVISIONALI INCOMPLETI; ","")&IF(LEFT($C11,5)="TEMP","CODICE COMMESSA TEMPORANEO; ","")),"DATI INCOMPLETI; ") -> PERDITA SAL ACCETTATA (€ 5000,000); | C11: =IF(ANAGRAFICA!$B8="","",ANAGRAFICA!$B8) -> TEST10 | D11: =IF($C11="","",ANAGRAFICA!$C8) -> COMMESSA DIMOSTRATIVA | E11: =IF($C11="","",ANAGRAFICA!$D8) -> TEST REV.10 - PERDITE SAL E COSTI MENSILI | F11: =IF($C11="","",ANAGRAFICA!$E8) -> TEST | G11: =IF($C11="","",ANAGRAFICA!$F8) -> DIREZIONE | H11: =IF($C11="","",ANAGRAFICA!$G8) -> PREPOSTO TEST | I11: =IF($C11="","",ANAGRAFICA!$L8) -> In corso | J11: =IF($C11="","",$AZ11) -> 100000 | K11: =IF($C11="","",$BA11) -> 25000 | L11: =IF($C11="","",$BB11) -> 40000 | M11: =IF($C11="","",MAX($BA11-$BB11,0)) -> 0 | N11: =IF(OR($C11="",$W11=""),"",MAX($W11-$BA11,0)) -> 70000 | O11: =IF($C11="","",MAX($BC11-$BD11,0)) -> 0 | P11: =IF(OR($C11="",$BG11="",$BH11="",$BI11=""),"",TEXT($BG11,"0.0%")&" / "&TEXT($BH11,"0.0%")&" / "&TEXT($BI11,"0.0%")) -> 26% / 30% / -04% | Q11: =IF(OR($C11="",'BUDGET COMMESSA'!$D8="",'BUDGET COMMESSA'!$D8<=0,ANAGRAFICA!$J8=""),"",IF(OR($I11="Finito ritenute non previste",$I11="Finito con sblocco ritenute",$I11="Finito senza sblocco ritenute"),0,IF(AND($BK11>=$BJ11,ANAGRAFICA!$R8="Ritardo produttivo FIDA"),IF(ANAGRAFICA!$T8<>"",MAX(0,ANAGRAFICA!$J8-ANAGRAFICA!$T8),MAX(0,$Y11-ANAGRAFICA!$J8)),0))) -> 0 | R11: =IF(OR($C11="",$BJ11=""),"",TEXT($BJ11,"#,##0.00")&" / "&TEXT($BK11,"#,##0.00")&" / "&TEXT($BL11,"#,##0.00")) -> 1000,000 / 300,000 / 700,000 | S11: =IF(OR($C11="",$BM11="",$BG11="",$BN11=""),"",TEXT($BM11,"0.0%")&" / "&TEXT($BG11,"0.0%")&" / "&TEXT($BN11,"0.0%")) -> 30% / 26% / 04% | T11: =IF(OR($C11="",$BO11=""),"",IF($BR11>0,"BUDGET € "&TEXT($BO11,"#,##0.00")&" | SOSTENUTI € "&TEXT($BP11,"#,##0.00")&" | SFORAMENTO € "&TEXT($BR11,"#,##0.00"),"BUDGET € "&TEXT($BO11,"#,##0.00")&" | SOSTENUTI € "&TEXT($BP11,"#,##0.00")&" | RESIDUO € "&TEXT($BQ11,"#,##0.00"))) -> BUDGET € 20000,000 | SOSTENUTI € 6000,000 | RESIDUO € 14000,000 | U11: =IF($C11="","",$BS11) -> 19737 | V11: =IF($C11="","",$BV11) -> 5000 | W11: =IF(OR($C11="",$AZ11=""),"",MAX($AZ11-$BV11,0)) -> 95000 | Y11: 46132 | AA11: Settembre | AB11: =IF($A$3="","",IF($A$3="TUTTE",SUMIFS('MOVIMENTI 2026'!$N$7:$N$4206,'MOVIMENTI 2026'!$E$7:$E$4206,">="&DATE(PARAMETRI!$B$11,9,1),'MOVIMENTI 2026'!$E$7:$E$4206,"<"&DATE(PARAMETRI!$B$11,10,1))*PARAMETRI!$B$4+SUMIFS('COSTI DIRETTI'!$H$6:$H$505,'COSTI DIRETTI'!$A$6:$A$505,">="&DATE(PARAMETRI!$B$11,9,1),'COSTI DIRETTI'!$A$6:$A$505,"<"&DATE(PARAMETRI!$B$11,10,1)),SUMIFS('MOVIMENTI 2026'!$N$7:$N$4206,'MOVIMENTI 2026'!$B$7:$B$4206,$A$3,'MOVIMENTI 2026'!$E$7:$E$4206,">="&DATE(PARAMETRI!$B$11,9,1),'MOVIMENTI 2026'!$E$7:$E$4206,"<"&DATE(PARAMETRI!$B$11,10,1))*PARAMETRI!$B$4+SUMIFS('COSTI DIRETTI'!$H$6:$H$505,'COSTI DIRETTI'!$C$6:$C$505,$A$3,'COSTI DIRETTI'!$A$6:$A$505,">="&DATE(PARAMETRI!$B$11,9,1),'COSTI DIRETTI'!$A$6:$A$505,"<"&DATE(PARAMETRI!$B$11,10,1)))) -> 0 | AC11: =IF($A$3="","",$AC10+$AB11) -> 83182.2 | AZ11: =IF($C11="","",ANAGRAFICA!$P8) -> 100000 | BA11: =IF($C11="","",SUMIF('MOVIMENTI 2026'!$B$7:$B$4206,$C11,'MOVIMENTI 2026'!$I$7:$I$4206)+SUMIF('SALDI AL 31.12.2025'!$A$6:$A$505,$C11,'SALDI AL 31.12.2025'!$C$6:$C$505)) -> 25000 | BB11: =IF($C11="","",SUMIF('MOVIMENTI 2026'!$B$7:$B$4206,$C11,'MOVIMENTI 2026'!$J$7:$J$4206)+SUMIF('SALDI AL 31.12.2025'!$A$6:$A$505,$C11,'SALDI AL 31.12.2025'!$D$6:$D$505)) -> 40000 | BC11: =IF($C11="","",SUMIF('MOVIMENTI 2026'!$B$7:$B$4206,$C11,'MOVIMENTI 2026'!$K$7:$K$4206)+SUMIF('SALDI AL 31.12.2025'!$A$6:$A$505,$C11,'SALDI AL 31.12.2025'!$E$6:$E$505)) -> 0 | BD11: =IF($C11="","",SUMIF('MOVIMENTI 2026'!$B$7:$B$4206,$C11,'MOVIMENTI 2026'!$L$7:$L$4206)+SUMIF('SALDI AL 31.12.2025'!$A$6:$A$505,$C11,'SALDI AL 31.12.2025'!$F$6:$F$505)) -> 0 | BE11: =IF(OR($C11="",$W11=""),"",MAX($W11-$BB11,0)) -> 55000 | BF11: =IF(OR($C11="",$W11=""),"",MAX($BB11-$W11,0)) -> 0 | BG11: =IF(OR($C11="",$W11<=0),"",$BA11/$W11) -> 0.26315789 | BH11: =IFERROR(IF(OR($C11="",ANAGRAFICA!$I8="",ANAGRAFICA!$J8="",ANAGRAFICA!$J8<=ANAGRAFICA!$I8,$Y11=""),"",IF(OR($I11="Finito ritenute non previste",$I11="Finito con sblocco ritenute",$I11="Finito senza sblocco ritenute"),1,MAX(0,MIN(1,($Y11-ANAGRAFICA!$I8)/(ANAGRAFICA!$J8-ANAGRAFICA!$I8))))),"") -> 0.29945055 | BI11: =IF(OR($C11="",$BG11="",$BH11=""),"",$BG11-$BH11) -> -0.036292655 | BJ11: =IFERROR(IF($C11="","",'BUDGET COMMESSA'!$D8),"") -> 1000 | BK11: =IF($C11="","",SUMIF('MOVIMENTI 2026'!$B$7:$B$4206,$C11,'MOVIMENTI 2026'!$N$7:$N$4206)+SUMIF('SALDI AL 31.12.2025'!$A$6:$A$505,$C11,'SALDI AL 31.12.2025'!$H$6:$H$505)) -> 300 | BL11: =IF(OR($C11="",$BJ11=""),"",MAX($BJ11-$BK11,0)) -> 700 | BM11: =IF(OR($C11="",$BJ11<=0),"",$BK11/$BJ11) -> 0.3 | BN11: =IF(OR($C11="",$BM11="",$BG11=""),"",$BM11-$BG11) -> 0.036842105 | BO11: =IFERROR(IF($C11="","",'BUDGET COMMESSA'!$G8),"") -> 20000 | BP11: =IF($C11="","",SUMIF('COSTI DIRETTI'!$C$6:$C$505,$C11,'COSTI DIRETTI'!$H$6:$H$505)+SUMIF('SALDI AL 31.12.2025'!$A$6:$A$505,$C11,'SALDI AL 31.12.2025'!$I$6:$I$505)) -> 6000 | BQ11: =IF(OR($C11="",$BO11=""),"",MAX($BO11-$BP11,0)) -> 14000 | BR11: =IF(OR($C11="",$BO11=""),"",MAX($BP11-$BO11,0)) -> 0 | BS11: =IF($C11="","",$BK11*PARAMETRI!$B$4+$BP11) -> 19737 | BT11: =IF($A11="CRITICO",1,0) -> 0 | BU11: =IF($A11="ATTENZIONE",1,0) -> 1 | BV11: =IF($C11="","",SUMIF('MOVIMENTI 2026'!$B$7:$B$4206,$C11,'MOVIMENTI 2026'!$P$7:$P$4206)+SUMIF('SALDI AL 31.12.2025'!$A$6:$A$505,$C11,'SALDI AL 31.12.2025'!$G$6:$G$505)) -> 5000
A12: =IFERROR(IF($C12="","",IF(OR($BF12>0,$V12>$J12,AND(ISNUMBER($Q12),$Q12>0),AND($BI12<>"",$BI12<-PARAMETRI!$B$6),AND($BM12<>"",$BM12>=1),AND($BN12<>"",$BN12>PARAMETRI!$B$8),AND(ISNUMBER($BR12),$BR12>0)),"CRITICO",IF(OR($AZ12="",LEFT($C12,5)="TEMP",$BJ12="",$BO12="",ANAGRAFICA!$I9="",ANAGRAFICA!$J9="",$Y12="",AND(OR($I12="Finito ritenute non previste",$I12="Finito con sblocco ritenute",$I12="Finito senza sblocco ritenute"),ANAGRAFICA!$K9=""),OR(AND(ANAGRAFICA!$T9<>"",ANAGRAFICA!$J9<>ANAGRAFICA!$T9,OR(ANAGRAFICA!$R9="",ANAGRAFICA!$R9="Nessuna variazione")),AND(ANAGRAFICA!$J9="",ANAGRAFICA!$R9<>"",ANAGRAFICA!$R9<>"Nessuna variazione")),AND($BI12<>"",$BI12<-PARAMETRI!$B$5),AND($BN12<>"",$BN12>PARAMETRI!$B$7),AND($W12>0,$M12>$W12*PARAMETRI!$B$9),AND($O12>0,OR($I12="Finito ritenute non previste",$I12="Finito con sblocco ritenute",$I12="Finito senza sblocco ritenute")),AND($BA12>0,$BO12>0,$BP12=0),AND(OR($I12="Finito ritenute non previste",$I12="Finito con sblocco ritenute",$I12="Finito senza sblocco ritenute"),$W12>0,$N12>$W12*PARAMETRI!$B$9),$V12>0),"ATTENZIONE","REGOLARE"))),"ATTENZIONE") -> ATTENZIONE | B12: =IFERROR(IF($C12="","",IF($BF12>0,"FATTURATO OLTRE VALORE RECUPERABILE; ","")&IF($V12>$J12,"PERDITE ACCETTATE OLTRE CONTRATTO; ","")&IF($V12>0,"PERDITA SAL ACCETTATA (€ "&TEXT($V12,"#,##0.00")&"); ","")&IF(AND(ISNUMBER($Q12),$Q12>0),"RITARDO PRODUTTIVO ("&TEXT($Q12,"0")&" GG); ","")&IF(AND($BI12<>"",$BI12<-PARAMETRI!$B$5),"AVANZAMENTO PIÙ LENTO DEL TEMPO; ","")&IF(AND($BM12<>"",$BM12>1),"ORE OLTRE BUDGET; ","")&IF(AND($BM12<>"",$BM12=1),"ORE PREVENTIVATE ESAURITE; ","")&IF(AND($BN12<>"",$BN12>PARAMETRI!$B$7),"CONSUMO ORE SUPERIORE ALL'AVANZAMENTO; ","")&IF(AND(ISNUMBER($BR12),$BR12>0),"COSTI DIRETTI OLTRE BUDGET; ","")&IF(AND($W12>0,$M12>$W12*PARAMETRI!$B$9),"SAL MATURATO NON FATTURATO; ","")&IF(AND($O12>0,OR($I12="Finito ritenute non previste",$I12="Finito con sblocco ritenute",$I12="Finito senza sblocco ritenute")),"RITENUTE DA SBLOCCARE; ","")&IF(AND($BA12>0,$BO12>0,$BP12=0),"COSTI DIRETTI NON REGISTRATI; ","")&IF(AND(OR($I12="Finito ritenute non previste",$I12="Finito con sblocco ritenute",$I12="Finito senza sblocco ritenute"),$W12>0,$N12>$W12*PARAMETRI!$B$9),"CANTIERE FINITO CON RESIDUO LAVORI; ","")&IF(AND(OR($I12="Finito ritenute non previste",$I12="Finito con sblocco ritenute",$I12="Finito senza sblocco ritenute"),ANAGRAFICA!$K9=""),"DATA FINE EFFETTIVA MANCANTE; ","")&IF(OR(AND(ANAGRAFICA!$T9<>"",ANAGRAFICA!$J9<>ANAGRAFICA!$T9,OR(ANAGRAFICA!$R9="",ANAGRAFICA!$R9="Nessuna variazione")),AND(ANAGRAFICA!$J9="",ANAGRAFICA!$R9<>"",ANAGRAFICA!$R9<>"Nessuna variazione")),"GESTIONE DATA FINE INCOMPLETA; ","")&IF($Y12="","AGGIORNATO AL MANCANTE; ","")&IF(OR($AZ12="",$BJ12="",$BO12="",ANAGRAFICA!$I9="",ANAGRAFICA!$J9=""),"DATI PREVISIONALI INCOMPLETI; ","")&IF(LEFT($C12,5)="TEMP","CODICE COMMESSA TEMPORANEO; ","")),"DATI INCOMPLETI; ") -> DATI INCOMPLETI; | C12: =IF(ANAGRAFICA!$B9="","",ANAGRAFICA!$B9) -> C042 | D12: =IF($C12="","",ANAGRAFICA!$C9) -> 0 | E12: =IF($C12="","",ANAGRAFICA!$D9) -> 0 | F12: =IF($C12="","",ANAGRAFICA!$E9) -> 0 | G12: =IF($C12="","",ANAGRAFICA!$F9) -> 0 | H12: =IF($C12="","",ANAGRAFICA!$G9) -> 0 | I12: =IF($C12="","",ANAGRAFICA!$L9) -> 0 | J12: =IF($C12="","",$AZ12) | K12: =IF($C12="","",$BA12) -> 42770.9 | L12: =IF($C12="","",$BB12) -> 42770.9 | M12: =IF($C12="","",MAX($BA12-$BB12,0)) -> 0 | N12: =IF(OR($C12="",$W12=""),"",MAX($W12-$BA12,0)) | O12: =IF($C12="","",MAX($BC12-$BD12,0)) -> 1510.23 | P12: =IF(OR($C12="",$BG12="",$BH12="",$BI12=""),"",TEXT($BG12,"0.0%")&" / "&TEXT($BH12,"0.0%")&" / "&TEXT($BI12,"0.0%")) -> #VALUE! | Q12: =IF(OR($C12="",'BUDGET COMMESSA'!$D9="",'BUDGET COMMESSA'!$D9<=0,ANAGRAFICA!$J9=""),"",IF(OR($I12="Finito ritenute non previste",$I12="Finito con sblocco ritenute",$I12="Finito senza sblocco ritenute"),0,IF(AND($BK12>=$BJ12,ANAGRAFICA!$R9="Ritardo produttivo FIDA"),IF(ANAGRAFICA!$T9<>"",MAX(0,ANAGRAFICA!$J9-ANAGRAFICA!$T9),MAX(0,$Y12-ANAGRAFICA!$J9)),0))) | R12: =IF(OR($C12="",$BJ12=""),"",TEXT($BJ12,"#,##0.00")&" / "&TEXT($BK12,"#,##0.00")&" / "&TEXT($BL12,"#,##0.00")) -> ,000 / 680,000 / ,000 | S12: =IF(OR($C12="",$BM12="",$BG12="",$BN12=""),"",TEXT($BM12,"0.0%")&" / "&TEXT($BG12,"0.0%")&" / "&TEXT($BN12,"0.0%")) -> #VALUE! | T12: =IF(OR($C12="",$BO12=""),"",IF($BR12>0,"BUDGET € "&TEXT($BO12,"#,##0.00")&" | SOSTENUTI € "&TEXT($BP12,"#,##0.00")&" | SFORAMENTO € "&TEXT($BR12,"#,##0.00"),"BUDGET € "&TEXT($BO12,"#,##0.00")&" | SOSTENUTI € "&TEXT($BP12,"#,##0.00")&" | RESIDUO € "&TEXT($BQ12,"#,##0.00"))) -> BUDGET € ,000 | SOSTENUTI € 32308,000 | SFORAMENTO € 32308,000 | U12: =IF($C12="","",$BS12) -> 63445.2 | V12: =IF($C12="","",$BV12) -> 2000 | W12: =IF(OR($C12="",$AZ12=""),"",MAX($AZ12-$BV12,0)) | AA12: Ottobre | AB12: =IF($A$3="","",IF($A$3="TUTTE",SUMIFS('MOVIMENTI 2026'!$N$7:$N$4206,'MOVIMENTI 2026'!$E$7:$E$4206,">="&DATE(PARAMETRI!$B$11,10,1),'MOVIMENTI 2026'!$E$7:$E$4206,"<"&DATE(PARAMETRI!$B$11,11,1))*PARAMETRI!$B$4+SUMIFS('COSTI DIRETTI'!$H$6:$H$505,'COSTI DIRETTI'!$A$6:$A$505,">="&DATE(PARAMETRI!$B$11,10,1),'COSTI DIRETTI'!$A$6:$A$505,"<"&DATE(PARAMETRI!$B$11,11,1)),SUMIFS('MOVIMENTI 2026'!$N$7:$N$4206,'MOVIMENTI 2026'!$B$7:$B$4206,$A$3,'MOVIMENTI 2026'!$E$7:$E$4206,">="&DATE(PARAMETRI!$B$11,10,1),'MOVIMENTI 2026'!$E$7:$E$4206,"<"&DATE(PARAMETRI!$B$11,11,1))*PARAMETRI!$B$4+SUMIFS('COSTI DIRETTI'!$H$6:$H$505,'COSTI DIRETTI'!$C$6:$C$505,$A$3,'COSTI DIRETTI'!$A$6:$A$505,">="&DATE(PARAMETRI!$B$11,10,1),'COSTI DIRETTI'!$A$6:$A$505,"<"&DATE(PARAMETRI!$B$11,11,1)))) -> 0 | AC12: =IF($A$3="","",$AC11+$AB12) -> 83182.2 | AZ12: =IF($C12="","",ANAGRAFICA!$P9) | BA12: =IF($C12="","",SUMIF('MOVIMENTI 2026'!$B$7:$B$4206,$C12,'MOVIMENTI 2026'!$I$7:$I$4206)+SUMIF('SALDI AL 31.12.2025'!$A$6:$A$505,$C12,'SALDI AL 31.12.2025'!$C$6:$C$505)) -> 42770.9 | BB12: =IF($C12="","",SUMIF('MOVIMENTI 2026'!$B$7:$B$4206,$C12,'MOVIMENTI 2026'!$J$7:$J$4206)+SUMIF('SALDI AL 31.12.2025'!$A$6:$A$505,$C12,'SALDI AL 31.12.2025'!$D$6:$D$505)) -> 42770.9 | BC12: =IF($C12="","",SUMIF('MOVIMENTI 2026'!$B$7:$B$4206,$C12,'MOVIMENTI 2026'!$K$7:$K$4206)+SUMIF('SALDI AL 31.12.2025'!$A$6:$A$505,$C12,'SALDI AL 31.12.2025'!$E$6:$E$505)) -> 2010.23 | BD12: =IF($C12="","",SUMIF('MOVIMENTI 2026'!$B$7:$B$4206,$C12,'MOVIMENTI 2026'!$L$7:$L$4206)+SUMIF('SALDI AL 31.12.2025'!$A$6:$A$505,$C12,'SALDI AL 31.12.2025'!$F$6:$F$505)) -> 500 | BE12: =IF(OR($C12="",$W12=""),"",MAX($W12-$BB12,0)) | BF12: =IF(OR($C12="",$W12=""),"",MAX($BB12-$W12,0)) | BG12: =IF(OR($C12="",$W12<=0),"",$BA12/$W12) -> #VALUE! | BH12: =IFERROR(IF(OR($C12="",ANAGRAFICA!$I9="",ANAGRAFICA!$J9="",ANAGRAFICA!$J9<=ANAGRAFICA!$I9,$Y12=""),"",IF(OR($I12="Finito ritenute non previste",$I12="Finito con sblocco ritenute",$I12="Finito senza sblocco ritenute"),1,MAX(0,MIN(1,($Y12-ANAGRAFICA!$I9)/(ANAGRAFICA!$J9-ANAGRAFICA!$I9))))),"") | BI12: =IF(OR($C12="",$BG12="",$BH12=""),"",$BG12-$BH12) -> #VALUE! | BJ12: =IFERROR(IF($C12="","",'BUDGET COMMESSA'!$D9),"") -> 0 | BK12: =IF($C12="","",SUMIF('MOVIMENTI 2026'!$B$7:$B$4206,$C12,'MOVIMENTI 2026'!$N$7:$N$4206)+SUMIF('SALDI AL 31.12.2025'!$A$6:$A$505,$C12,'SALDI AL 31.12.2025'!$H$6:$H$505)) -> 680 | BL12: =IF(OR($C12="",$BJ12=""),"",MAX($BJ12-$BK12,0)) -> 0 | BM12: =IF(OR($C12="",$BJ12<=0),"",$BK12/$BJ12) | BN12: =IF(OR($C12="",$BM12="",$BG12=""),"",$BM12-$BG12) -> #VALUE! | BO12: =IFERROR(IF($C12="","",'BUDGET COMMESSA'!$G9),"") -> 0 | BP12: =IF($C12="","",SUMIF('COSTI DIRETTI'!$C$6:$C$505,$C12,'COSTI DIRETTI'!$H$6:$H$505)+SUMIF('SALDI AL 31.12.2025'!$A$6:$A$505,$C12,'SALDI AL 31.12.2025'!$I$6:$I$505)) -> 32308 | BQ12: =IF(OR($C12="",$BO12=""),"",MAX($BO12-$BP12,0)) -> 0 | BR12: =IF(OR($C12="",$BO12=""),"",MAX($BP12-$BO12,0)) -> 32308 | BS12: =IF($C12="","",$BK12*PARAMETRI!$B$4+$BP12) -> 63445.2 | BT12: =IF($A12="CRITICO",1,0) -> 0 | BU12: =IF($A12="ATTENZIONE",1,0) -> 1 | BV12: =IF($C12="","",SUMIF('MOVIMENTI 2026'!$B$7:$B$4206,$C12,'MOVIMENTI 2026'!$P$7:$P$4206)+SUMIF('SALDI AL 31.12.2025'!$A$6:$A$505,$C12,'SALDI AL 31.12.2025'!$G$6:$G$505)) -> 2000
A13: =IFERROR(IF($C13="","",IF(OR($BF13>0,$V13>$J13,AND(ISNUMBER($Q13),$Q13>0),AND($BI13<>"",$BI13<-PARAMETRI!$B$6),AND($BM13<>"",$BM13>=1),AND($BN13<>"",$BN13>PARAMETRI!$B$8),AND(ISNUMBER($BR13),$BR13>0)),"CRITICO",IF(OR($AZ13="",LEFT($C13,5)="TEMP",$BJ13="",$BO13="",ANAGRAFICA!$I10="",ANAGRAFICA!$J10="",$Y13="",AND(OR($I13="Finito ritenute non previste",$I13="Finito con sblocco ritenute",$I13="Finito senza sblocco ritenute"),ANAGRAFICA!$K10=""),OR(AND(ANAGRAFICA!$T10<>"",ANAGRAFICA!$J10<>ANAGRAFICA!$T10,OR(ANAGRAFICA!$R10="",ANAGRAFICA!$R10="Nessuna variazione")),AND(ANAGRAFICA!$J10="",ANAGRAFICA!$R10<>"",ANAGRAFICA!$R10<>"Nessuna variazione")),AND($BI13<>"",$BI13<-PARAMETRI!$B$5),AND($BN13<>"",$BN13>PARAMETRI!$B$7),AND($W13>0,$M13>$W13*PARAMETRI!$B$9),AND($O13>0,OR($I13="Finito ritenute non previste",$I13="Finito con sblocco ritenute",$I13="Finito senza sblocco ritenute")),AND($BA13>0,$BO13>0,$BP13=0),AND(OR($I13="Finito ritenute non previste",$I13="Finito con sblocco ritenute",$I13="Finito senza sblocco ritenute"),$W13>0,$N13>$W13*PARAMETRI!$B$9),$V13>0),"ATTENZIONE","REGOLARE"))),"ATTENZIONE") | B13: =IFERROR(IF($C13="","",IF($BF13>0,"FATTURATO OLTRE VALORE RECUPERABILE; ","")&IF($V13>$J13,"PERDITE ACCETTATE OLTRE CONTRATTO; ","")&IF($V13>0,"PERDITA SAL ACCETTATA (€ "&TEXT($V13,"#,##0.00")&"); ","")&IF(AND(ISNUMBER($Q13),$Q13>0),"RITARDO PRODUTTIVO ("&TEXT($Q13,"0")&" GG); ","")&IF(AND($BI13<>"",$BI13<-PARAMETRI!$B$5),"AVANZAMENTO PIÙ LENTO DEL TEMPO; ","")&IF(AND($BM13<>"",$BM13>1),"ORE OLTRE BUDGET; ","")&IF(AND($BM13<>"",$BM13=1),"ORE PREVENTIVATE ESAURITE; ","")&IF(AND($BN13<>"",$BN13>PARAMETRI!$B$7),"CONSUMO ORE SUPERIORE ALL'AVANZAMENTO; ","")&IF(AND(ISNUMBER($BR13),$BR13>0),"COSTI DIRETTI OLTRE BUDGET; ","")&IF(AND($W13>0,$M13>$W13*PARAMETRI!$B$9),"SAL MATURATO NON FATTURATO; ","")&IF(AND($O13>0,OR($I13="Finito ritenute non previste",$I13="Finito con sblocco ritenute",$I13="Finito senza sblocco ritenute")),"RITENUTE DA SBLOCCARE; ","")&IF(AND($BA13>0,$BO13>0,$BP13=0),"COSTI DIRETTI NON REGISTRATI; ","")&IF(AND(OR($I13="Finito ritenute non previste",$I13="Finito con sblocco ritenute",$I13="Finito senza sblocco ritenute"),$W13>0,$N13>$W13*PARAMETRI!$B$9),"CANTIERE FINITO CON RESIDUO LAVORI; ","")&IF(AND(OR($I13="Finito ritenute non previste",$I13="Finito con sblocco ritenute",$I13="Finito senza sblocco ritenute"),ANAGRAFICA!$K10=""),"DATA FINE EFFETTIVA MANCANTE; ","")&IF(OR(AND(ANAGRAFICA!$T10<>"",ANAGRAFICA!$J10<>ANAGRAFICA!$T10,OR(ANAGRAFICA!$R10="",ANAGRAFICA!$R10="Nessuna variazione")),AND(ANAGRAFICA!$J10="",ANAGRAFICA!$R10<>"",ANAGRAFICA!$R10<>"Nessuna variazione")),"GESTIONE DATA FINE INCOMPLETA; ","")&IF($Y13="","AGGIORNATO AL MANCANTE; ","")&IF(OR($AZ13="",$BJ13="",$BO13="",ANAGRAFICA!$I10="",ANAGRAFICA!$J10=""),"DATI PREVISIONALI INCOMPLETI; ","")&IF(LEFT($C13,5)="TEMP","CODICE COMMESSA TEMPORANEO; ","")),"DATI INCOMPLETI; ") | C13: =IF(ANAGRAFICA!$B10="","",ANAGRAFICA!$B10) | D13: =IF($C13="","",ANAGRAFICA!$C10) | E13: =IF($C13="","",ANAGRAFICA!$D10) | F13: =IF($C13="","",ANAGRAFICA!$E10) | G13: =IF($C13="","",ANAGRAFICA!$F10) | H13: =IF($C13="","",ANAGRAFICA!$G10) | I13: =IF($C13="","",ANAGRAFICA!$L10) | J13: =IF($C13="","",$AZ13) | K13: =IF($C13="","",$BA13) | L13: =IF($C13="","",$BB13) | M13: =IF($C13="","",MAX($BA13-$BB13,0)) | N13: =IF(OR($C13="",$W13=""),"",MAX($W13-$BA13,0)) | O13: =IF($C13="","",MAX($BC13-$BD13,0)) | P13: =IF(OR($C13="",$BG13="",$BH13="",$BI13=""),"",TEXT($BG13,"0.0%")&" / "&TEXT($BH13,"0.0%")&" / "&TEXT($BI13,"0.0%")) | Q13: =IF(OR($C13="",'BUDGET COMMESSA'!$D10="",'BUDGET COMMESSA'!$D10<=0,ANAGRAFICA!$J10=""),"",IF(OR($I13="Finito ritenute non previste",$I13="Finito con sblocco ritenute",$I13="Finito senza sblocco ritenute"),0,IF(AND($BK13>=$BJ13,ANAGRAFICA!$R10="Ritardo produttivo FIDA"),IF(ANAGRAFICA!$T10<>"",MAX(0,ANAGRAFICA!$J10-ANAGRAFICA!$T10),MAX(0,$Y13-ANAGRAFICA!$J10)),0))) | R13: =IF(OR($C13="",$BJ13=""),"",TEXT($BJ13,"#,##0.00")&" / "&TEXT($BK13,"#,##0.00")&" / "&TEXT($BL13,"#,##0.00")) | S13: =IF(OR($C13="",$BM13="",$BG13="",$BN13=""),"",TEXT($BM13,"0.0%")&" / "&TEXT($BG13,"0.0%")&" / "&TEXT($BN13,"0.0%")) | T13: =IF(OR($C13="",$BO13=""),"",IF($BR13>0,"BUDGET € "&TEXT($BO13,"#,##0.00")&" | SOSTENUTI € "&TEXT($BP13,"#,##0.00")&" | SFORAMENTO € "&TEXT($BR13,"#,##0.00"),"BUDGET € "&TEXT($BO13,"#,##0.00")&" | SOSTENUTI € "&TEXT($BP13,"#,##0.00")&" | RESIDUO € "&TEXT($BQ13,"#,##0.00"))) | U13: =IF($C13="","",$BS13) | V13: =IF($C13="","",$BV13) | W13: =IF(OR($C13="",$AZ13=""),"",MAX($AZ13-$BV13,0)) | AA13: Novembre | AB13: =IF($A$3="","",IF($A$3="TUTTE",SUMIFS('MOVIMENTI 2026'!$N$7:$N$4206,'MOVIMENTI 2026'!$E$7:$E$4206,">="&DATE(PARAMETRI!$B$11,11,1),'MOVIMENTI 2026'!$E$7:$E$4206,"<"&DATE(PARAMETRI!$B$11,12,1))*PARAMETRI!$B$4+SUMIFS('COSTI DIRETTI'!$H$6:$H$505,'COSTI DIRETTI'!$A$6:$A$505,">="&DATE(PARAMETRI!$B$11,11,1),'COSTI DIRETTI'!$A$6:$A$505,"<"&DATE(PARAMETRI!$B$11,12,1)),SUMIFS('MOVIMENTI 2026'!$N$7:$N$4206,'MOVIMENTI 2026'!$B$7:$B$4206,$A$3,'MOVIMENTI 2026'!$E$7:$E$4206,">="&DATE(PARAMETRI!$B$11,11,1),'MOVIMENTI 2026'!$E$7:$E$4206,"<"&DATE(PARAMETRI!$B$11,12,1))*PARAMETRI!$B$4+SUMIFS('COSTI DIRETTI'!$H$6:$H$505,'COSTI DIRETTI'!$C$6:$C$505,$A$3,'COSTI DIRETTI'!$A$6:$A$505,">="&DATE(PARAMETRI!$B$11,11,1),'COSTI DIRETTI'!$A$6:$A$505,"<"&DATE(PARAMETRI!$B$11,12,1)))) -> 0 | AC13: =IF($A$3="","",$AC12+$AB13) -> 83182.2 | AZ13: =IF($C13="","",ANAGRAFICA!$P10) | BA13: =IF($C13="","",SUMIF('MOVIMENTI 2026'!$B$7:$B$4206,$C13,'MOVIMENTI 2026'!$I$7:$I$4206)+SUMIF('SALDI AL 31.12.2025'!$A$6:$A$505,$C13,'SALDI AL 31.12.2025'!$C$6:$C$505)) | BB13: =IF($C13="","",SUMIF('MOVIMENTI 2026'!$B$7:$B$4206,$C13,'MOVIMENTI 2026'!$J$7:$J$4206)+SUMIF('SALDI AL 31.12.2025'!$A$6:$A$505,$C13,'SALDI AL 31.12.2025'!$D$6:$D$505)) | BC13: =IF($C13="","",SUMIF('MOVIMENTI 2026'!$B$7:$B$4206,$C13,'MOVIMENTI 2026'!$K$7:$K$4206)+SUMIF('SALDI AL 31.12.2025'!$A$6:$A$505,$C13,'SALDI AL 31.12.2025'!$E$6:$E$505)) | BD13: =IF($C13="","",SUMIF('MOVIMENTI 2026'!$B$7:$B$4206,$C13,'MOVIMENTI 2026'!$L$7:$L$4206)+SUMIF('SALDI AL 31.12.2025'!$A$6:$A$505,$C13,'SALDI AL 31.12.2025'!$F$6:$F$505)) | BE13: =IF(OR($C13="",$W13=""),"",MAX($W13-$BB13,0)) | BF13: =IF(OR($C13="",$W13=""),"",MAX($BB13-$W13,0)) | BG13: =IF(OR($C13="",$W13<=0),"",$BA13/$W13) | BH13: =IFERROR(IF(OR($C13="",ANAGRAFICA!$I10="",ANAGRAFICA!$J10="",ANAGRAFICA!$J10<=ANAGRAFICA!$I10,$Y13=""),"",IF(OR($I13="Finito ritenute non previste",$I13="Finito con sblocco ritenute",$I13="Finito senza sblocco ritenute"),1,MAX(0,MIN(1,($Y13-ANAGRAFICA!$I10)/(ANAGRAFICA!$J10-ANAGRAFICA!$I10))))),"") | BI13: =IF(OR($C13="",$BG13="",$BH13=""),"",$BG13-$BH13) | BJ13: =IFERROR(IF($C13="","",'BUDGET COMMESSA'!$D10),"") | BK13: =IF($C13="","",SUMIF('MOVIMENTI 2026'!$B$7:$B$4206,$C13,'MOVIMENTI 2026'!$N$7:$N$4206)+SUMIF('SALDI AL 31.12.2025'!$A$6:$A$505,$C13,'SALDI AL 31.12.2025'!$H$6:$H$505)) | BL13: =IF(OR($C13="",$BJ13=""),"",MAX($BJ13-$BK13,0)) | BM13: =IF(OR($C13="",$BJ13<=0),"",$BK13/$BJ13) | BN13: =IF(OR($C13="",$BM13="",$BG13=""),"",$BM13-$BG13) | BO13: =IFERROR(IF($C13="","",'BUDGET COMMESSA'!$G10),"") | BP13: =IF($C13="","",SUMIF('COSTI DIRETTI'!$C$6:$C$505,$C13,'COSTI DIRETTI'!$H$6:$H$505)+SUMIF('SALDI AL 31.12.2025'!$A$6:$A$505,$C13,'SALDI AL 31.12.2025'!$I$6:$I$505)) | BQ13: =IF(OR($C13="",$BO13=""),"",MAX($BO13-$BP13,0)) | BR13: =IF(OR($C13="",$BO13=""),"",MAX($BP13-$BO13,0)) | BS13: =IF($C13="","",$BK13*PARAMETRI!$B$4+$BP13) | BT13: =IF($A13="CRITICO",1,0) -> 0 | BU13: =IF($A13="ATTENZIONE",1,0) -> 0 | BV13: =IF($C13="","",SUMIF('MOVIMENTI 2026'!$B$7:$B$4206,$C13,'MOVIMENTI 2026'!$P$7:$P$4206)+SUMIF('SALDI AL 31.12.2025'!$A$6:$A$505,$C13,'SALDI AL 31.12.2025'!$G$6:$G$505))
A14: =IFERROR(IF($C14="","",IF(OR($BF14>0,$V14>$J14,AND(ISNUMBER($Q14),$Q14>0),AND($BI14<>"",$BI14<-PARAMETRI!$B$6),AND($BM14<>"",$BM14>=1),AND($BN14<>"",$BN14>PARAMETRI!$B$8),AND(ISNUMBER($BR14),$BR14>0)),"CRITICO",IF(OR($AZ14="",LEFT($C14,5)="TEMP",$BJ14="",$BO14="",ANAGRAFICA!$I11="",ANAGRAFICA!$J11="",$Y14="",AND(OR($I14="Finito ritenute non previste",$I14="Finito con sblocco ritenute",$I14="Finito senza sblocco ritenute"),ANAGRAFICA!$K11=""),OR(AND(ANAGRAFICA!$T11<>"",ANAGRAFICA!$J11<>ANAGRAFICA!$T11,OR(ANAGRAFICA!$R11="",ANAGRAFICA!$R11="Nessuna variazione")),AND(ANAGRAFICA!$J11="",ANAGRAFICA!$R11<>"",ANAGRAFICA!$R11<>"Nessuna variazione")),AND($BI14<>"",$BI14<-PARAMETRI!$B$5),AND($BN14<>"",$BN14>PARAMETRI!$B$7),AND($W14>0,$M14>$W14*PARAMETRI!$B$9),AND($O14>0,OR($I14="Finito ritenute non previste",$I14="Finito con sblocco ritenute",$I14="Finito senza sblocco ritenute")),AND($BA14>0,$BO14>0,$BP14=0),AND(OR($I14="Finito ritenute non previste",$I14="Finito con sblocco ritenute",$I14="Finito senza sblocco ritenute"),$W14>0,$N14>$W14*PARAMETRI!$B$9),$V14>0),"ATTENZIONE","REGOLARE"))),"ATTENZIONE") | B14: =IFERROR(IF($C14="","",IF($BF14>0,"FATTURATO OLTRE VALORE RECUPERABILE; ","")&IF($V14>$J14,"PERDITE ACCETTATE OLTRE CONTRATTO; ","")&IF($V14>0,"PERDITA SAL ACCETTATA (€ "&TEXT($V14,"#,##0.00")&"); ","")&IF(AND(ISNUMBER($Q14),$Q14>0),"RITARDO PRODUTTIVO ("&TEXT($Q14,"0")&" GG); ","")&IF(AND($BI14<>"",$BI14<-PARAMETRI!$B$5),"AVANZAMENTO PIÙ LENTO DEL TEMPO; ","")&IF(AND($BM14<>"",$BM14>1),"ORE OLTRE BUDGET; ","")&IF(AND($BM14<>"",$BM14=1),"ORE PREVENTIVATE ESAURITE; ","")&IF(AND($BN14<>"",$BN14>PARAMETRI!$B$7),"CONSUMO ORE SUPERIORE ALL'AVANZAMENTO; ","")&IF(AND(ISNUMBER($BR14),$BR14>0),"COSTI DIRETTI OLTRE BUDGET; ","")&IF(AND($W14>0,$M14>$W14*PARAMETRI!$B$9),"SAL MATURATO NON FATTURATO; ","")&IF(AND($O14>0,OR($I14="Finito ritenute non previste",$I14="Finito con sblocco ritenute",$I14="Finito senza sblocco ritenute")),"RITENUTE DA SBLOCCARE; ","")&IF(AND($BA14>0,$BO14>0,$BP14=0),"COSTI DIRETTI NON REGISTRATI; ","")&IF(AND(OR($I14="Finito ritenute non previste",$I14="Finito con sblocco ritenute",$I14="Finito senza sblocco ritenute"),$W14>0,$N14>$W14*PARAMETRI!$B$9),"CANTIERE FINITO CON RESIDUO LAVORI; ","")&IF(AND(OR($I14="Finito ritenute non previste",$I14="Finito con sblocco ritenute",$I14="Finito senza sblocco ritenute"),ANAGRAFICA!$K11=""),"DATA FINE EFFETTIVA MANCANTE; ","")&IF(OR(AND(ANAGRAFICA!$T11<>"",ANAGRAFICA!$J11<>ANAGRAFICA!$T11,OR(ANAGRAFICA!$R11="",ANAGRAFICA!$R11="Nessuna variazione")),AND(ANAGRAFICA!$J11="",ANAGRAFICA!$R11<>"",ANAGRAFICA!$R11<>"Nessuna variazione")),"GESTIONE DATA FINE INCOMPLETA; ","")&IF($Y14="","AGGIORNATO AL MANCANTE; ","")&IF(OR($AZ14="",$BJ14="",$BO14="",ANAGRAFICA!$I11="",ANAGRAFICA!$J11=""),"DATI PREVISIONALI INCOMPLETI; ","")&IF(LEFT($C14,5)="TEMP","CODICE COMMESSA TEMPORANEO; ","")),"DATI INCOMPLETI; ") | C14: =IF(ANAGRAFICA!$B11="","",ANAGRAFICA!$B11) | D14: =IF($C14="","",ANAGRAFICA!$C11) | E14: =IF($C14="","",ANAGRAFICA!$D11) | F14: =IF($C14="","",ANAGRAFICA!$E11) | G14: =IF($C14="","",ANAGRAFICA!$F11) | H14: =IF($C14="","",ANAGRAFICA!$G11) | I14: =IF($C14="","",ANAGRAFICA!$L11) | J14: =IF($C14="","",$AZ14) | K14: =IF($C14="","",$BA14) | L14: =IF($C14="","",$BB14) | M14: =IF($C14="","",MAX($BA14-$BB14,0)) | N14: =IF(OR($C14="",$W14=""),"",MAX($W14-$BA14,0)) | O14: =IF($C14="","",MAX($BC14-$BD14,0)) | P14: =IF(OR($C14="",$BG14="",$BH14="",$BI14=""),"",TEXT($BG14,"0.0%")&" / "&TEXT($BH14,"0.0%")&" / "&TEXT($BI14,"0.0%")) | Q14: =IF(OR($C14="",'BUDGET COMMESSA'!$D11="",'BUDGET COMMESSA'!$D11<=0,ANAGRAFICA!$J11=""),"",IF(OR($I14="Finito ritenute non previste",$I14="Finito con sblocco ritenute",$I14="Finito senza sblocco ritenute"),0,IF(AND($BK14>=$BJ14,ANAGRAFICA!$R11="Ritardo produttivo FIDA"),IF(ANAGRAFICA!$T11<>"",MAX(0,ANAGRAFICA!$J11-ANAGRAFICA!$T11),MAX(0,$Y14-ANAGRAFICA!$J11)),0))) | R14: =IF(OR($C14="",$BJ14=""),"",TEXT($BJ14,"#,##0.00")&" / "&TEXT($BK14,"#,##0.00")&" / "&TEXT($BL14,"#,##0.00")) | S14: =IF(OR($C14="",$BM14="",$BG14="",$BN14=""),"",TEXT($BM14,"0.0%")&" / "&TEXT($BG14,"0.0%")&" / "&TEXT($BN14,"0.0%")) | T14: =IF(OR($C14="",$BO14=""),"",IF($BR14>0,"BUDGET € "&TEXT($BO14,"#,##0.00")&" | SOSTENUTI € "&TEXT($BP14,"#,##0.00")&" | SFORAMENTO € "&TEXT($BR14,"#,##0.00"),"BUDGET € "&TEXT($BO14,"#,##0.00")&" | SOSTENUTI € "&TEXT($BP14,"#,##0.00")&" | RESIDUO € "&TEXT($BQ14,"#,##0.00"))) | U14: =IF($C14="","",$BS14) | V14: =IF($C14="","",$BV14) | W14: =IF(OR($C14="",$AZ14=""),"",MAX($AZ14-$BV14,0)) | AA14: Dicembre | AB14: =IF($A$3="","",IF($A$3="TUTTE",SUMIFS('MOVIMENTI 2026'!$N$7:$N$4206,'MOVIMENTI 2026'!$E$7:$E$4206,">="&DATE(PARAMETRI!$B$11,12,1),'MOVIMENTI 2026'!$E$7:$E$4206,"<"&DATE(PARAMETRI!$B$11,13,1))*PARAMETRI!$B$4+SUMIFS('COSTI DIRETTI'!$H$6:$H$505,'COSTI DIRETTI'!$A$6:$A$505,">="&DATE(PARAMETRI!$B$11,12,1),'COSTI DIRETTI'!$A$6:$A$505,"<"&DATE(PARAMETRI!$B$11,13,1)),SUMIFS('MOVIMENTI 2026'!$N$7:$N$4206,'MOVIMENTI 2026'!$B$7:$B$4206,$A$3,'MOVIMENTI 2026'!$E$7:$E$4206,">="&DATE(PARAMETRI!$B$11,12,1),'MOVIMENTI 2026'!$E$7:$E$4206,"<"&DATE(PARAMETRI!$B$11,13,1))*PARAMETRI!$B$4+SUMIFS('COSTI DIRETTI'!$H$6:$H$505,'COSTI DIRETTI'!$C$6:$C$505,$A$3,'COSTI DIRETTI'!$A$6:$A$505,">="&DATE(PARAMETRI!$B$11,12,1),'COSTI DIRETTI'!$A$6:$A$505,"<"&DATE(PARAMETRI!$B$11,13,1)))) -> 0 | AC14: =IF($A$3="","",$AC13+$AB14) -> 83182.2 | AZ14: =IF($C14="","",ANAGRAFICA!$P11) | BA14: =IF($C14="","",SUMIF('MOVIMENTI 2026'!$B$7:$B$4206,$C14,'MOVIMENTI 2026'!$I$7:$I$4206)+SUMIF('SALDI AL 31.12.2025'!$A$6:$A$505,$C14,'SALDI AL 31.12.2025'!$C$6:$C$505)) | BB14: =IF($C14="","",SUMIF('MOVIMENTI 2026'!$B$7:$B$4206,$C14,'MOVIMENTI 2026'!$J$7:$J$4206)+SUMIF('SALDI AL 31.12.2025'!$A$6:$A$505,$C14,'SALDI AL 31.12.2025'!$D$6:$D$505)) | BC14: =IF($C14="","",SUMIF('MOVIMENTI 2026'!$B$7:$B$4206,$C14,'MOVIMENTI 2026'!$K$7:$K$4206)+SUMIF('SALDI AL 31.12.2025'!$A$6:$A$505,$C14,'SALDI AL 31.12.2025'!$E$6:$E$505)) | BD14: =IF($C14="","",SUMIF('MOVIMENTI 2026'!$B$7:$B$4206,$C14,'MOVIMENTI 2026'!$L$7:$L$4206)+SUMIF('SALDI AL 31.12.2025'!$A$6:$A$505,$C14,'SALDI AL 31.12.2025'!$F$6:$F$505)) | BE14: =IF(OR($C14="",$W14=""),"",MAX($W14-$BB14,0)) | BF14: =IF(OR($C14="",$W14=""),"",MAX($BB14-$W14,0)) | BG14: =IF(OR($C14="",$W14<=0),"",$BA14/$W14) | BH14: =IFERROR(IF(OR($C14="",ANAGRAFICA!$I11="",ANAGRAFICA!$J11="",ANAGRAFICA!$J11<=ANAGRAFICA!$I11,$Y14=""),"",IF(OR($I14="Finito ritenute non previste",$I14="Finito con sblocco ritenute",$I14="Finito senza sblocco ritenute"),1,MAX(0,MIN(1,($Y14-ANAGRAFICA!$I11)/(ANAGRAFICA!$J11-ANAGRAFICA!$I11))))),"") | BI14: =IF(OR($C14="",$BG14="",$BH14=""),"",$BG14-$BH14) | BJ14: =IFERROR(IF($C14="","",'BUDGET COMMESSA'!$D11),"") | BK14: =IF($C14="","",SUMIF('MOVIMENTI 2026'!$B$7:$B$4206,$C14,'MOVIMENTI 2026'!$N$7:$N$4206)+SUMIF('SALDI AL 31.12.2025'!$A$6:$A$505,$C14,'SALDI AL 31.12.2025'!$H$6:$H$505)) | BL14: =IF(OR($C14="",$BJ14=""),"",MAX($BJ14-$BK14,0)) | BM14: =IF(OR($C14="",$BJ14<=0),"",$BK14/$BJ14) | BN14: =IF(OR($C14="",$BM14="",$BG14=""),"",$BM14-$BG14) | BO14: =IFERROR(IF($C14="","",'BUDGET COMMESSA'!$G11),"") | BP14: =IF($C14="","",SUMIF('COSTI DIRETTI'!$C$6:$C$505,$C14,'COSTI DIRETTI'!$H$6:$H$505)+SUMIF('SALDI AL 31.12.2025'!$A$6:$A$505,$C14,'SALDI AL 31.12.2025'!$I$6:$I$505)) | BQ14: =IF(OR($C14="",$BO14=""),"",MAX($BO14-$BP14,0)) | BR14: =IF(OR($C14="",$BO14=""),"",MAX($BP14-$BO14,0)) | BS14: =IF($C14="","",$BK14*PARAMETRI!$B$4+$BP14) | BT14: =IF($A14="CRITICO",1,0) -> 0 | BU14: =IF($A14="ATTENZIONE",1,0) -> 0 | BV14: =IF($C14="","",SUMIF('MOVIMENTI 2026'!$B$7:$B$4206,$C14,'MOVIMENTI 2026'!$P$7:$P$4206)+SUMIF('SALDI AL 31.12.2025'!$A$6:$A$505,$C14,'SALDI AL 31.12.2025'!$G$6:$G$505))
A15: =IFERROR(IF($C15="","",IF(OR($BF15>0,$V15>$J15,AND(ISNUMBER($Q15),$Q15>0),AND($BI15<>"",$BI15<-PARAMETRI!$B$6),AND($BM15<>"",$BM15>=1),AND($BN15<>"",$BN15>PARAMETRI!$B$8),AND(ISNUMBER($BR15),$BR15>0)),"CRITICO",IF(OR($AZ15="",LEFT($C15,5)="TEMP",$BJ15="",$BO15="",ANAGRAFICA!$I12="",ANAGRAFICA!$J12="",$Y15="",AND(OR($I15="Finito ritenute non previste",$I15="Finito con sblocco ritenute",$I15="Finito senza sblocco ritenute"),ANAGRAFICA!$K12=""),OR(AND(ANAGRAFICA!$T12<>"",ANAGRAFICA!$J12<>ANAGRAFICA!$T12,OR(ANAGRAFICA!$R12="",ANAGRAFICA!$R12="Nessuna variazione")),AND(ANAGRAFICA!$J12="",ANAGRAFICA!$R12<>"",ANAGRAFICA!$R12<>"Nessuna variazione")),AND($BI15<>"",$BI15<-PARAMETRI!$B$5),AND($BN15<>"",$BN15>PARAMETRI!$B$7),AND($W15>0,$M15>$W15*PARAMETRI!$B$9),AND($O15>0,OR($I15="Finito ritenute non previste",$I15="Finito con sblocco ritenute",$I15="Finito senza sblocco ritenute")),AND($BA15>0,$BO15>0,$BP15=0),AND(OR($I15="Finito ritenute non previste",$I15="Finito con sblocco ritenute",$I15="Finito senza sblocco ritenute"),$W15>0,$N15>$W15*PARAMETRI!$B$9),$V15>0),"ATTENZIONE","REGOLARE"))),"ATTENZIONE") | B15: =IFERROR(IF($C15="","",IF($BF15>0,"FATTURATO OLTRE VALORE RECUPERABILE; ","")&IF($V15>$J15,"PERDITE ACCETTATE OLTRE CONTRATTO; ","")&IF($V15>0,"PERDITA SAL ACCETTATA (€ "&TEXT($V15,"#,##0.00")&"); ","")&IF(AND(ISNUMBER($Q15),$Q15>0),"RITARDO PRODUTTIVO ("&TEXT($Q15,"0")&" GG); ","")&IF(AND($BI15<>"",$BI15<-PARAMETRI!$B$5),"AVANZAMENTO PIÙ LENTO DEL TEMPO; ","")&IF(AND($BM15<>"",$BM15>1),"ORE OLTRE BUDGET; ","")&IF(AND($BM15<>"",$BM15=1),"ORE PREVENTIVATE ESAURITE; ","")&IF(AND($BN15<>"",$BN15>PARAMETRI!$B$7),"CONSUMO ORE SUPERIORE ALL'AVANZAMENTO; ","")&IF(AND(ISNUMBER($BR15),$BR15>0),"COSTI DIRETTI OLTRE BUDGET; ","")&IF(AND($W15>0,$M15>$W15*PARAMETRI!$B$9),"SAL MATURATO NON FATTURATO; ","")&IF(AND($O15>0,OR($I15="Finito ritenute non previste",$I15="Finito con sblocco ritenute",$I15="Finito senza sblocco ritenute")),"RITENUTE DA SBLOCCARE; ","")&IF(AND($BA15>0,$BO15>0,$BP15=0),"COSTI DIRETTI NON REGISTRATI; ","")&IF(AND(OR($I15="Finito ritenute non previste",$I15="Finito con sblocco ritenute",$I15="Finito senza sblocco ritenute"),$W15>0,$N15>$W15*PARAMETRI!$B$9),"CANTIERE FINITO CON RESIDUO LAVORI; ","")&IF(AND(OR($I15="Finito ritenute non previste",$I15="Finito con sblocco ritenute",$I15="Finito senza sblocco ritenute"),ANAGRAFICA!$K12=""),"DATA FINE EFFETTIVA MANCANTE; ","")&IF(OR(AND(ANAGRAFICA!$T12<>"",ANAGRAFICA!$J12<>ANAGRAFICA!$T12,OR(ANAGRAFICA!$R12="",ANAGRAFICA!$R12="Nessuna variazione")),AND(ANAGRAFICA!$J12="",ANAGRAFICA!$R12<>"",ANAGRAFICA!$R12<>"Nessuna variazione")),"GESTIONE DATA FINE INCOMPLETA; ","")&IF($Y15="","AGGIORNATO AL MANCANTE; ","")&IF(OR($AZ15="",$BJ15="",$BO15="",ANAGRAFICA!$I12="",ANAGRAFICA!$J12=""),"DATI PREVISIONALI INCOMPLETI; ","")&IF(LEFT($C15,5)="TEMP","CODICE COMMESSA TEMPORANEO; ","")),"DATI INCOMPLETI; ") | C15: =IF(ANAGRAFICA!$B12="","",ANAGRAFICA!$B12) | D15: =IF($C15="","",ANAGRAFICA!$C12) | E15: =IF($C15="","",ANAGRAFICA!$D12) | F15: =IF($C15="","",ANAGRAFICA!$E12) | G15: =IF($C15="","",ANAGRAFICA!$F12) | H15: =IF($C15="","",ANAGRAFICA!$G12) | I15: =IF($C15="","",ANAGRAFICA!$L12) | J15: =IF($C15="","",$AZ15) | K15: =IF($C15="","",$BA15) | L15: =IF($C15="","",$BB15) | M15: =IF($C15="","",MAX($BA15-$BB15,0)) | N15: =IF(OR($C15="",$W15=""),"",MAX($W15-$BA15,0)) | O15: =IF($C15="","",MAX($BC15-$BD15,0)) | P15: =IF(OR($C15="",$BG15="",$BH15="",$BI15=""),"",TEXT($BG15,"0.0%")&" / "&TEXT($BH15,"0.0%")&" / "&TEXT($BI15,"0.0%")) | Q15: =IF(OR($C15="",'BUDGET COMMESSA'!$D12="",'BUDGET COMMESSA'!$D12<=0,ANAGRAFICA!$J12=""),"",IF(OR($I15="Finito ritenute non previste",$I15="Finito con sblocco ritenute",$I15="Finito senza sblocco ritenute"),0,IF(AND($BK15>=$BJ15,ANAGRAFICA!$R12="Ritardo produttivo FIDA"),IF(ANAGRAFICA!$T12<>"",MAX(0,ANAGRAFICA!$J12-ANAGRAFICA!$T12),MAX(0,$Y15-ANAGRAFICA!$J12)),0))) | R15: =IF(OR($C15="",$BJ15=""),"",TEXT($BJ15,"#,##0.00")&" / "&TEXT($BK15,"#,##0.00")&" / "&TEXT($BL15,"#,##0.00")) | S15: =IF(OR($C15="",$BM15="",$BG15="",$BN15=""),"",TEXT($BM15,"0.0%")&" / "&TEXT($BG15,"0.0%")&" / "&TEXT($BN15,"0.0%")) | T15: =IF(OR($C15="",$BO15=""),"",IF($BR15>0,"BUDGET € "&TEXT($BO15,"#,##0.00")&" | SOSTENUTI € "&TEXT($BP15,"#,##0.00")&" | SFORAMENTO € "&TEXT($BR15,"#,##0.00"),"BUDGET € "&TEXT($BO15,"#,##0.00")&" | SOSTENUTI € "&TEXT($BP15,"#,##0.00")&" | RESIDUO € "&TEXT($BQ15,"#,##0.00"))) | U15: =IF($C15="","",$BS15) | V15: =IF($C15="","",$BV15) | W15: =IF(OR($C15="",$AZ15=""),"",MAX($AZ15-$BV15,0)) | AZ15: =IF($C15="","",ANAGRAFICA!$P12) | BA15: =IF($C15="","",SUMIF('MOVIMENTI 2026'!$B$7:$B$4206,$C15,'MOVIMENTI 2026'!$I$7:$I$4206)+SUMIF('SALDI AL 31.12.2025'!$A$6:$A$505,$C15,'SALDI AL 31.12.2025'!$C$6:$C$505)) | BB15: =IF($C15="","",SUMIF('MOVIMENTI 2026'!$B$7:$B$4206,$C15,'MOVIMENTI 2026'!$J$7:$J$4206)+SUMIF('SALDI AL 31.12.2025'!$A$6:$A$505,$C15,'SALDI AL 31.12.2025'!$D$6:$D$505)) | BC15: =IF($C15="","",SUMIF('MOVIMENTI 2026'!$B$7:$B$4206,$C15,'MOVIMENTI 2026'!$K$7:$K$4206)+SUMIF('SALDI AL 31.12.2025'!$A$6:$A$505,$C15,'SALDI AL 31.12.2025'!$E$6:$E$505)) | BD15: =IF($C15="","",SUMIF('MOVIMENTI 2026'!$B$7:$B$4206,$C15,'MOVIMENTI 2026'!$L$7:$L$4206)+SUMIF('SALDI AL 31.12.2025'!$A$6:$A$505,$C15,'SALDI AL 31.12.2025'!$F$6:$F$505)) | BE15: =IF(OR($C15="",$W15=""),"",MAX($W15-$BB15,0)) | BF15: =IF(OR($C15="",$W15=""),"",MAX($BB15-$W15,0)) | BG15: =IF(OR($C15="",$W15<=0),"",$BA15/$W15) | BH15: =IFERROR(IF(OR($C15="",ANAGRAFICA!$I12="",ANAGRAFICA!$J12="",ANAGRAFICA!$J12<=ANAGRAFICA!$I12,$Y15=""),"",IF(OR($I15="Finito ritenute non previste",$I15="Finito con sblocco ritenute",$I15="Finito senza sblocco ritenute"),1,MAX(0,MIN(1,($Y15-ANAGRAFICA!$I12)/(ANAGRAFICA!$J12-ANAGRAFICA!$I12))))),"") | BI15: =IF(OR($C15="",$BG15="",$BH15=""),"",$BG15-$BH15) | BJ15: =IFERROR(IF($C15="","",'BUDGET COMMESSA'!$D12),"") | BK15: =IF($C15="","",SUMIF('MOVIMENTI 2026'!$B$7:$B$4206,$C15,'MOVIMENTI 2026'!$N$7:$N$4206)+SUMIF('SALDI AL 31.12.2025'!$A$6:$A$505,$C15,'SALDI AL 31.12.2025'!$H$6:$H$505)) | BL15: =IF(OR($C15="",$BJ15=""),"",MAX($BJ15-$BK15,0)) | BM15: =IF(OR($C15="",$BJ15<=0),"",$BK15/$BJ15) | BN15: =IF(OR($C15="",$BM15="",$BG15=""),"",$BM15-$BG15) | BO15: =IFERROR(IF($C15="","",'BUDGET COMMESSA'!$G12),"") | BP15: =IF($C15="","",SUMIF('COSTI DIRETTI'!$C$6:$C$505,$C15,'COSTI DIRETTI'!$H$6:$H$505)+SUMIF('SALDI AL 31.12.2025'!$A$6:$A$505,$C15,'SALDI AL 31.12.2025'!$I$6:$I$505)) | BQ15: =IF(OR($C15="",$BO15=""),"",MAX($BO15-$BP15,0)) | BR15: =IF(OR($C15="",$BO15=""),"",MAX($BP15-$BO15,0)) | BS15: =IF($C15="","",$BK15*PARAMETRI!$B$4+$BP15) | BT15: =IF($A15="CRITICO",1,0) -> 0 | BU15: =IF($A15="ATTENZIONE",1,0) -> 0 | BV15: =IF($C15="","",SUMIF('MOVIMENTI 2026'!$B$7:$B$4206,$C15,'MOVIMENTI 2026'!$P$7:$P$4206)+SUMIF('SALDI AL 31.12.2025'!$A$6:$A$505,$C15,'SALDI AL 31.12.2025'!$G$6:$G$505))
A16: =IFERROR(IF($C16="","",IF(OR($BF16>0,$V16>$J16,AND(ISNUMBER($Q16),$Q16>0),AND($BI16<>"",$BI16<-PARAMETRI!$B$6),AND($BM16<>"",$BM16>=1),AND($BN16<>"",$BN16>PARAMETRI!$B$8),AND(ISNUMBER($BR16),$BR16>0)),"CRITICO",IF(OR($AZ16="",LEFT($C16,5)="TEMP",$BJ16="",$BO16="",ANAGRAFICA!$I13="",ANAGRAFICA!$J13="",$Y16="",AND(OR($I16="Finito ritenute non previste",$I16="Finito con sblocco ritenute",$I16="Finito senza sblocco ritenute"),ANAGRAFICA!$K13=""),OR(AND(ANAGRAFICA!$T13<>"",ANAGRAFICA!$J13<>ANAGRAFICA!$T13,OR(ANAGRAFICA!$R13="",ANAGRAFICA!$R13="Nessuna variazione")),AND(ANAGRAFICA!$J13="",ANAGRAFICA!$R13<>"",ANAGRAFICA!$R13<>"Nessuna variazione")),AND($BI16<>"",$BI16<-PARAMETRI!$B$5),AND($BN16<>"",$BN16>PARAMETRI!$B$7),AND($W16>0,$M16>$W16*PARAMETRI!$B$9),AND($O16>0,OR($I16="Finito ritenute non previste",$I16="Finito con sblocco ritenute",$I16="Finito senza sblocco ritenute")),AND($BA16>0,$BO16>0,$BP16=0),AND(OR($I16="Finito ritenute non previste",$I16="Finito con sblocco ritenute",$I16="Finito senza sblocco ritenute"),$W16>0,$N16>$W16*PARAMETRI!$B$9),$V16>0),"ATTENZIONE","REGOLARE"))),"ATTENZIONE") | B16: =IFERROR(IF($C16="","",IF($BF16>0,"FATTURATO OLTRE VALORE RECUPERABILE; ","")&IF($V16>$J16,"PERDITE ACCETTATE OLTRE CONTRATTO; ","")&IF($V16>0,"PERDITA SAL ACCETTATA (€ "&TEXT($V16,"#,##0.00")&"); ","")&IF(AND(ISNUMBER($Q16),$Q16>0),"RITARDO PRODUTTIVO ("&TEXT($Q16,"0")&" GG); ","")&IF(AND($BI16<>"",$BI16<-PARAMETRI!$B$5),"AVANZAMENTO PIÙ LENTO DEL TEMPO; ","")&IF(AND($BM16<>"",$BM16>1),"ORE OLTRE BUDGET; ","")&IF(AND($BM16<>"",$BM16=1),"ORE PREVENTIVATE ESAURITE; ","")&IF(AND($BN16<>"",$BN16>PARAMETRI!$B$7),"CONSUMO ORE SUPERIORE ALL'AVANZAMENTO; ","")&IF(AND(ISNUMBER($BR16),$BR16>0),"COSTI DIRETTI OLTRE BUDGET; ","")&IF(AND($W16>0,$M16>$W16*PARAMETRI!$B$9),"SAL MATURATO NON FATTURATO; ","")&IF(AND($O16>0,OR($I16="Finito ritenute non previste",$I16="Finito con sblocco ritenute",$I16="Finito senza sblocco ritenute")),"RITENUTE DA SBLOCCARE; ","")&IF(AND($BA16>0,$BO16>0,$BP16=0),"COSTI DIRETTI NON REGISTRATI; ","")&IF(AND(OR($I16="Finito ritenute non previste",$I16="Finito con sblocco ritenute",$I16="Finito senza sblocco ritenute"),$W16>0,$N16>$W16*PARAMETRI!$B$9),"CANTIERE FINITO CON RESIDUO LAVORI; ","")&IF(AND(OR($I16="Finito ritenute non previste",$I16="Finito con sblocco ritenute",$I16="Finito senza sblocco ritenute"),ANAGRAFICA!$K13=""),"DATA FINE EFFETTIVA MANCANTE; ","")&IF(OR(AND(ANAGRAFICA!$T13<>"",ANAGRAFICA!$J13<>ANAGRAFICA!$T13,OR(ANAGRAFICA!$R13="",ANAGRAFICA!$R13="Nessuna variazione")),AND(ANAGRAFICA!$J13="",ANAGRAFICA!$R13<>"",ANAGRAFICA!$R13<>"Nessuna variazione")),"GESTIONE DATA FINE INCOMPLETA; ","")&IF($Y16="","AGGIORNATO AL MANCANTE; ","")&IF(OR($AZ16="",$BJ16="",$BO16="",ANAGRAFICA!$I13="",ANAGRAFICA!$J13=""),"DATI PREVISIONALI INCOMPLETI; ","")&IF(LEFT($C16,5)="TEMP","CODICE COMMESSA TEMPORANEO; ","")),"DATI INCOMPLETI; ") | C16: =IF(ANAGRAFICA!$B13="","",ANAGRAFICA!$B13) | D16: =IF($C16="","",ANAGRAFICA!$C13) | E16: =IF($C16="","",ANAGRAFICA!$D13) | F16: =IF($C16="","",ANAGRAFICA!$E13) | G16: =IF($C16="","",ANAGRAFICA!$F13) | H16: =IF($C16="","",ANAGRAFICA!$G13) | I16: =IF($C16="","",ANAGRAFICA!$L13) | J16: =IF($C16="","",$AZ16) | K16: =IF($C16="","",$BA16) | L16: =IF($C16="","",$BB16) | M16: =IF($C16="","",MAX($BA16-$BB16,0)) | N16: =IF(OR($C16="",$W16=""),"",MAX($W16-$BA16,0)) | O16: =IF($C16="","",MAX($BC16-$BD16,0)) | P16: =IF(OR($C16="",$BG16="",$BH16="",$BI16=""),"",TEXT($BG16,"0.0%")&" / "&TEXT($BH16,"0.0%")&" / "&TEXT($BI16,"0.0%")) | Q16: =IF(OR($C16="",'BUDGET COMMESSA'!$D13="",'BUDGET COMMESSA'!$D13<=0,ANAGRAFICA!$J13=""),"",IF(OR($I16="Finito ritenute non previste",$I16="Finito con sblocco ritenute",$I16="Finito senza sblocco ritenute"),0,IF(AND($BK16>=$BJ16,ANAGRAFICA!$R13="Ritardo produttivo FIDA"),IF(ANAGRAFICA!$T13<>"",MAX(0,ANAGRAFICA!$J13-ANAGRAFICA!$T13),MAX(0,$Y16-ANAGRAFICA!$J13)),0))) | R16: =IF(OR($C16="",$BJ16=""),"",TEXT($BJ16,"#,##0.00")&" / "&TEXT($BK16,"#,##0.00")&" / "&TEXT($BL16,"#,##0.00")) | S16: =IF(OR($C16="",$BM16="",$BG16="",$BN16=""),"",TEXT($BM16,"0.0%")&" / "&TEXT($BG16,"0.0%")&" / "&TEXT($BN16,"0.0%")) | T16: =IF(OR($C16="",$BO16=""),"",IF($BR16>0,"BUDGET € "&TEXT($BO16,"#,##0.00")&" | SOSTENUTI € "&TEXT($BP16,"#,##0.00")&" | SFORAMENTO € "&TEXT($BR16,"#,##0.00"),"BUDGET € "&TEXT($BO16,"#,##0.00")&" | SOSTENUTI € "&TEXT($BP16,"#,##0.00")&" | RESIDUO € "&TEXT($BQ16,"#,##0.00"))) | U16: =IF($C16="","",$BS16) | V16: =IF($C16="","",$BV16) | W16: =IF(OR($C16="",$AZ16=""),"",MAX($AZ16-$BV16,0)) | AZ16: =IF($C16="","",ANAGRAFICA!$P13) | BA16: =IF($C16="","",SUMIF('MOVIMENTI 2026'!$B$7:$B$4206,$C16,'MOVIMENTI 2026'!$I$7:$I$4206)+SUMIF('SALDI AL 31.12.2025'!$A$6:$A$505,$C16,'SALDI AL 31.12.2025'!$C$6:$C$505)) | BB16: =IF($C16="","",SUMIF('MOVIMENTI 2026'!$B$7:$B$4206,$C16,'MOVIMENTI 2026'!$J$7:$J$4206)+SUMIF('SALDI AL 31.12.2025'!$A$6:$A$505,$C16,'SALDI AL 31.12.2025'!$D$6:$D$505)) | BC16: =IF($C16="","",SUMIF('MOVIMENTI 2026'!$B$7:$B$4206,$C16,'MOVIMENTI 2026'!$K$7:$K$4206)+SUMIF('SALDI AL 31.12.2025'!$A$6:$A$505,$C16,'SALDI AL 31.12.2025'!$E$6:$E$505)) | BD16: =IF($C16="","",SUMIF('MOVIMENTI 2026'!$B$7:$B$4206,$C16,'MOVIMENTI 2026'!$L$7:$L$4206)+SUMIF('SALDI AL 31.12.2025'!$A$6:$A$505,$C16,'SALDI AL 31.12.2025'!$F$6:$F$505)) | BE16: =IF(OR($C16="",$W16=""),"",MAX($W16-$BB16,0)) | BF16: =IF(OR($C16="",$W16=""),"",MAX($BB16-$W16,0)) | BG16: =IF(OR($C16="",$W16<=0),"",$BA16/$W16) | BH16: =IFERROR(IF(OR($C16="",ANAGRAFICA!$I13="",ANAGRAFICA!$J13="",ANAGRAFICA!$J13<=ANAGRAFICA!$I13,$Y16=""),"",IF(OR($I16="Finito ritenute non previste",$I16="Finito con sblocco ritenute",$I16="Finito senza sblocco ritenute"),1,MAX(0,MIN(1,($Y16-ANAGRAFICA!$I13)/(ANAGRAFICA!$J13-ANAGRAFICA!$I13))))),"") | BI16: =IF(OR($C16="",$BG16="",$BH16=""),"",$BG16-$BH16) | BJ16: =IFERROR(IF($C16="","",'BUDGET COMMESSA'!$D13),"") | BK16: =IF($C16="","",SUMIF('MOVIMENTI 2026'!$B$7:$B$4206,$C16,'MOVIMENTI 2026'!$N$7:$N$4206)+SUMIF('SALDI AL 31.12.2025'!$A$6:$A$505,$C16,'SALDI AL 31.12.2025'!$H$6:$H$505)) | BL16: =IF(OR($C16="",$BJ16=""),"",MAX($BJ16-$BK16,0)) | BM16: =IF(OR($C16="",$BJ16<=0),"",$BK16/$BJ16) | BN16: =IF(OR($C16="",$BM16="",$BG16=""),"",$BM16-$BG16) | BO16: =IFERROR(IF($C16="","",'BUDGET COMMESSA'!$G13),"") | BP16: =IF($C16="","",SUMIF('COSTI DIRETTI'!$C$6:$C$505,$C16,'COSTI DIRETTI'!$H$6:$H$505)+SUMIF('SALDI AL 31.12.2025'!$A$6:$A$505,$C16,'SALDI AL 31.12.2025'!$I$6:$I$505)) | BQ16: =IF(OR($C16="",$BO16=""),"",MAX($BO16-$BP16,0)) | BR16: =IF(OR($C16="",$BO16=""),"",MAX($BP16-$BO16,0)) | BS16: =IF($C16="","",$BK16*PARAMETRI!$B$4+$BP16) | BT16: =IF($A16="CRITICO",1,0) -> 0 | BU16: =IF($A16="ATTENZIONE",1,0) -> 0 | BV16: =IF($C16="","",SUMIF('MOVIMENTI 2026'!$B$7:$B$4206,$C16,'MOVIMENTI 2026'!$P$7:$P$4206)+SUMIF('SALDI AL 31.12.2025'!$A$6:$A$505,$C16,'SALDI AL 31.12.2025'!$G$6:$G$505))
A17: =IFERROR(IF($C17="","",IF(OR($BF17>0,$V17>$J17,AND(ISNUMBER($Q17),$Q17>0),AND($BI17<>"",$BI17<-PARAMETRI!$B$6),AND($BM17<>"",$BM17>=1),AND($BN17<>"",$BN17>PARAMETRI!$B$8),AND(ISNUMBER($BR17),$BR17>0)),"CRITICO",IF(OR($AZ17="",LEFT($C17,5)="TEMP",$BJ17="",$BO17="",ANAGRAFICA!$I14="",ANAGRAFICA!$J14="",$Y17="",AND(OR($I17="Finito ritenute non previste",$I17="Finito con sblocco ritenute",$I17="Finito senza sblocco ritenute"),ANAGRAFICA!$K14=""),OR(AND(ANAGRAFICA!$T14<>"",ANAGRAFICA!$J14<>ANAGRAFICA!$T14,OR(ANAGRAFICA!$R14="",ANAGRAFICA!$R14="Nessuna variazione")),AND(ANAGRAFICA!$J14="",ANAGRAFICA!$R14<>"",ANAGRAFICA!$R14<>"Nessuna variazione")),AND($BI17<>"",$BI17<-PARAMETRI!$B$5),AND($BN17<>"",$BN17>PARAMETRI!$B$7),AND($W17>0,$M17>$W17*PARAMETRI!$B$9),AND($O17>0,OR($I17="Finito ritenute non previste",$I17="Finito con sblocco ritenute",$I17="Finito senza sblocco ritenute")),AND($BA17>0,$BO17>0,$BP17=0),AND(OR($I17="Finito ritenute non previste",$I17="Finito con sblocco ritenute",$I17="Finito senza sblocco ritenute"),$W17>0,$N17>$W17*PARAMETRI!$B$9),$V17>0),"ATTENZIONE","REGOLARE"))),"ATTENZIONE") | B17: =IFERROR(IF($C17="","",IF($BF17>0,"FATTURATO OLTRE VALORE RECUPERABILE; ","")&IF($V17>$J17,"PERDITE ACCETTATE OLTRE CONTRATTO; ","")&IF($V17>0,"PERDITA SAL ACCETTATA (€ "&TEXT($V17,"#,##0.00")&"); ","")&IF(AND(ISNUMBER($Q17),$Q17>0),"RITARDO PRODUTTIVO ("&TEXT($Q17,"0")&" GG); ","")&IF(AND($BI17<>"",$BI17<-PARAMETRI!$B$5),"AVANZAMENTO PIÙ LENTO DEL TEMPO; ","")&IF(AND($BM17<>"",$BM17>1),"ORE OLTRE BUDGET; ","")&IF(AND($BM17<>"",$BM17=1),"ORE PREVENTIVATE ESAURITE; ","")&IF(AND($BN17<>"",$BN17>PARAMETRI!$B$7),"CONSUMO ORE SUPERIORE ALL'AVANZAMENTO; ","")&IF(AND(ISNUMBER($BR17),$BR17>0),"COSTI DIRETTI OLTRE BUDGET; ","")&IF(AND($W17>0,$M17>$W17*PARAMETRI!$B$9),"SAL MATURATO NON FATTURATO; ","")&IF(AND($O17>0,OR($I17="Finito ritenute non previste",$I17="Finito con sblocco ritenute",$I17="Finito senza sblocco ritenute")),"RITENUTE DA SBLOCCARE; ","")&IF(AND($BA17>0,$BO17>0,$BP17=0),"COSTI DIRETTI NON REGISTRATI; ","")&IF(AND(OR($I17="Finito ritenute non previste",$I17="Finito con sblocco ritenute",$I17="Finito senza sblocco ritenute"),$W17>0,$N17>$W17*PARAMETRI!$B$9),"CANTIERE FINITO CON RESIDUO LAVORI; ","")&IF(AND(OR($I17="Finito ritenute non previste",$I17="Finito con sblocco ritenute",$I17="Finito senza sblocco ritenute"),ANAGRAFICA!$K14=""),"DATA FINE EFFETTIVA MANCANTE; ","")&IF(OR(AND(ANAGRAFICA!$T14<>"",ANAGRAFICA!$J14<>ANAGRAFICA!$T14,OR(ANAGRAFICA!$R14="",ANAGRAFICA!$R14="Nessuna variazione")),AND(ANAGRAFICA!$J14="",ANAGRAFICA!$R14<>"",ANAGRAFICA!$R14<>"Nessuna variazione")),"GESTIONE DATA FINE INCOMPLETA; ","")&IF($Y17="","AGGIORNATO AL MANCANTE; ","")&IF(OR($AZ17="",$BJ17="",$BO17="",ANAGRAFICA!$I14="",ANAGRAFICA!$J14=""),"DATI PREVISIONALI INCOMPLETI; ","")&IF(LEFT($C17,5)="TEMP","CODICE COMMESSA TEMPORANEO; ","")),"DATI INCOMPLETI; ") | C17: =IF(ANAGRAFICA!$B14="","",ANAGRAFICA!$B14) | D17: =IF($C17="","",ANAGRAFICA!$C14) | E17: =IF($C17="","",ANAGRAFICA!$D14) | F17: =IF($C17="","",ANAGRAFICA!$E14) | G17: =IF($C17="","",ANAGRAFICA!$F14) | H17: =IF($C17="","",ANAGRAFICA!$G14) | I17: =IF($C17="","",ANAGRAFICA!$L14) | J17: =IF($C17="","",$AZ17) | K17: =IF($C17="","",$BA17) | L17: =IF($C17="","",$BB17) | M17: =IF($C17="","",MAX($BA17-$BB17,0)) | N17: =IF(OR($C17="",$W17=""),"",MAX($W17-$BA17,0)) | O17: =IF($C17="","",MAX($BC17-$BD17,0)) | P17: =IF(OR($C17="",$BG17="",$BH17="",$BI17=""),"",TEXT($BG17,"0.0%")&" / "&TEXT($BH17,"0.0%")&" / "&TEXT($BI17,"0.0%")) | Q17: =IF(OR($C17="",'BUDGET COMMESSA'!$D14="",'BUDGET COMMESSA'!$D14<=0,ANAGRAFICA!$J14=""),"",IF(OR($I17="Finito ritenute non previste",$I17="Finito con sblocco ritenute",$I17="Finito senza sblocco ritenute"),0,IF(AND($BK17>=$BJ17,ANAGRAFICA!$R14="Ritardo produttivo FIDA"),IF(ANAGRAFICA!$T14<>"",MAX(0,ANAGRAFICA!$J14-ANAGRAFICA!$T14),MAX(0,$Y17-ANAGRAFICA!$J14)),0))) | R17: =IF(OR($C17="",$BJ17=""),"",TEXT($BJ17,"#,##0.00")&" / "&TEXT($BK17,"#,##0.00")&" / "&TEXT($BL17,"#,##0.00")) | S17: =IF(OR($C17="",$BM17="",$BG17="",$BN17=""),"",TEXT($BM17,"0.0%")&" / "&TEXT($BG17,"0.0%")&" / "&TEXT($BN17,"0.0%")) | T17: =IF(OR($C17="",$BO17=""),"",IF($BR17>0,"BUDGET € "&TEXT($BO17,"#,##0.00")&" | SOSTENUTI € "&TEXT($BP17,"#,##0.00")&" | SFORAMENTO € "&TEXT($BR17,"#,##0.00"),"BUDGET € "&TEXT($BO17,"#,##0.00")&" | SOSTENUTI € "&TEXT($BP17,"#,##0.00")&" | RESIDUO € "&TEXT($BQ17,"#,##0.00"))) | U17: =IF($C17="","",$BS17) | V17: =IF($C17="","",$BV17) | W17: =IF(OR($C17="",$AZ17=""),"",MAX($AZ17-$BV17,0)) | AZ17: =IF($C17="","",ANAGRAFICA!$P14) | BA17: =IF($C17="","",SUMIF('MOVIMENTI 2026'!$B$7:$B$4206,$C17,'MOVIMENTI 2026'!$I$7:$I$4206)+SUMIF('SALDI AL 31.12.2025'!$A$6:$A$505,$C17,'SALDI AL 31.12.2025'!$C$6:$C$505)) | BB17: =IF($C17="","",SUMIF('MOVIMENTI 2026'!$B$7:$B$4206,$C17,'MOVIMENTI 2026'!$J$7:$J$4206)+SUMIF('SALDI AL 31.12.2025'!$A$6:$A$505,$C17,'SALDI AL 31.12.2025'!$D$6:$D$505)) | BC17: =IF($C17="","",SUMIF('MOVIMENTI 2026'!$B$7:$B$4206,$C17,'MOVIMENTI 2026'!$K$7:$K$4206)+SUMIF('SALDI AL 31.12.2025'!$A$6:$A$505,$C17,'SALDI AL 31.12.2025'!$E$6:$E$505)) | BD17: =IF($C17="","",SUMIF('MOVIMENTI 2026'!$B$7:$B$4206,$C17,'MOVIMENTI 2026'!$L$7:$L$4206)+SUMIF('SALDI AL 31.12.2025'!$A$6:$A$505,$C17,'SALDI AL 31.12.2025'!$F$6:$F$505)) | BE17: =IF(OR($C17="",$W17=""),"",MAX($W17-$BB17,0)) | BF17: =IF(OR($C17="",$W17=""),"",MAX($BB17-$W17,0)) | BG17: =IF(OR($C17="",$W17<=0),"",$BA17/$W17) | BH17: =IFERROR(IF(OR($C17="",ANAGRAFICA!$I14="",ANAGRAFICA!$J14="",ANAGRAFICA!$J14<=ANAGRAFICA!$I14,$Y17=""),"",IF(OR($I17="Finito ritenute non previste",$I17="Finito con sblocco ritenute",$I17="Finito senza sblocco ritenute"),1,MAX(0,MIN(1,($Y17-ANAGRAFICA!$I14)/(ANAGRAFICA!$J14-ANAGRAFICA!$I14))))),"") | BI17: =IF(OR($C17="",$BG17="",$BH17=""),"",$BG17-$BH17) | BJ17: =IFERROR(IF($C17="","",'BUDGET COMMESSA'!$D14),"") | BK17: =IF($C17="","",SUMIF('MOVIMENTI 2026'!$B$7:$B$4206,$C17,'MOVIMENTI 2026'!$N$7:$N$4206)+SUMIF('SALDI AL 31.12.2025'!$A$6:$A$505,$C17,'SALDI AL 31.12.2025'!$H$6:$H$505)) | BL17: =IF(OR($C17="",$BJ17=""),"",MAX($BJ17-$BK17,0)) | BM17: =IF(OR($C17="",$BJ17<=0),"",$BK17/$BJ17) | BN17: =IF(OR($C17="",$BM17="",$BG17=""),"",$BM17-$BG17) | BO17: =IFERROR(IF($C17="","",'BUDGET COMMESSA'!$G14),"") | BP17: =IF($C17="","",SUMIF('COSTI DIRETTI'!$C$6:$C$505,$C17,'COSTI DIRETTI'!$H$6:$H$505)+SUMIF('SALDI AL 31.12.2025'!$A$6:$A$505,$C17,'SALDI AL 31.12.2025'!$I$6:$I$505)) | BQ17: =IF(OR($C17="",$BO17=""),"",MAX($BO17-$BP17,0)) | BR17: =IF(OR($C17="",$BO17=""),"",MAX($BP17-$BO17,0)) | BS17: =IF($C17="","",$BK17*PARAMETRI!$B$4+$BP17) | BT17: =IF($A17="CRITICO",1,0) -> 0 | BU17: =IF($A17="ATTENZIONE",1,0) -> 0 | BV17: =IF($C17="","",SUMIF('MOVIMENTI 2026'!$B$7:$B$4206,$C17,'MOVIMENTI 2026'!$P$7:$P$4206)+SUMIF('SALDI AL 31.12.2025'!$A$6:$A$505,$C17,'SALDI AL 31.12.2025'!$G$6:$G$505))
A18: =IFERROR(IF($C18="","",IF(OR($BF18>0,$V18>$J18,AND(ISNUMBER($Q18),$Q18>0),AND($BI18<>"",$BI18<-PARAMETRI!$B$6),AND($BM18<>"",$BM18>=1),AND($BN18<>"",$BN18>PARAMETRI!$B$8),AND(ISNUMBER($BR18),$BR18>0)),"CRITICO",IF(OR($AZ18="",LEFT($C18,5)="TEMP",$BJ18="",$BO18="",ANAGRAFICA!$I15="",ANAGRAFICA!$J15="",$Y18="",AND(OR($I18="Finito ritenute non previste",$I18="Finito con sblocco ritenute",$I18="Finito senza sblocco ritenute"),ANAGRAFICA!$K15=""),OR(AND(ANAGRAFICA!$T15<>"",ANAGRAFICA!$J15<>ANAGRAFICA!$T15,OR(ANAGRAFICA!$R15="",ANAGRAFICA!$R15="Nessuna variazione")),AND(ANAGRAFICA!$J15="",ANAGRAFICA!$R15<>"",ANAGRAFICA!$R15<>"Nessuna variazione")),AND($BI18<>"",$BI18<-PARAMETRI!$B$5),AND($BN18<>"",$BN18>PARAMETRI!$B$7),AND($W18>0,$M18>$W18*PARAMETRI!$B$9),AND($O18>0,OR($I18="Finito ritenute non previste",$I18="Finito con sblocco ritenute",$I18="Finito senza sblocco ritenute")),AND($BA18>0,$BO18>0,$BP18=0),AND(OR($I18="Finito ritenute non previste",$I18="Finito con sblocco ritenute",$I18="Finito senza sblocco ritenute"),$W18>0,$N18>$W18*PARAMETRI!$B$9),$V18>0),"ATTENZIONE","REGOLARE"))),"ATTENZIONE") | B18: =IFERROR(IF($C18="","",IF($BF18>0,"FATTURATO OLTRE VALORE RECUPERABILE; ","")&IF($V18>$J18,"PERDITE ACCETTATE OLTRE CONTRATTO; ","")&IF($V18>0,"PERDITA SAL ACCETTATA (€ "&TEXT($V18,"#,##0.00")&"); ","")&IF(AND(ISNUMBER($Q18),$Q18>0),"RITARDO PRODUTTIVO ("&TEXT($Q18,"0")&" GG); ","")&IF(AND($BI18<>"",$BI18<-PARAMETRI!$B$5),"AVANZAMENTO PIÙ LENTO DEL TEMPO; ","")&IF(AND($BM18<>"",$BM18>1),"ORE OLTRE BUDGET; ","")&IF(AND($BM18<>"",$BM18=1),"ORE PREVENTIVATE ESAURITE; ","")&IF(AND($BN18<>"",$BN18>PARAMETRI!$B$7),"CONSUMO ORE SUPERIORE ALL'AVANZAMENTO; ","")&IF(AND(ISNUMBER($BR18),$BR18>0),"COSTI DIRETTI OLTRE BUDGET; ","")&IF(AND($W18>0,$M18>$W18*PARAMETRI!$B$9),"SAL MATURATO NON FATTURATO; ","")&IF(AND($O18>0,OR($I18="Finito ritenute non previste",$I18="Finito con sblocco ritenute",$I18="Finito senza sblocco ritenute")),"RITENUTE DA SBLOCCARE; ","")&IF(AND($BA18>0,$BO18>0,$BP18=0),"COSTI DIRETTI NON REGISTRATI; ","")&IF(AND(OR($I18="Finito ritenute non previste",$I18="Finito con sblocco ritenute",$I18="Finito senza sblocco ritenute"),$W18>0,$N18>$W18*PARAMETRI!$B$9),"CANTIERE FINITO CON RESIDUO LAVORI; ","")&IF(AND(OR($I18="Finito ritenute non previste",$I18="Finito con sblocco ritenute",$I18="Finito senza sblocco ritenute"),ANAGRAFICA!$K15=""),"DATA FINE EFFETTIVA MANCANTE; ","")&IF(OR(AND(ANAGRAFICA!$T15<>"",ANAGRAFICA!$J15<>ANAGRAFICA!$T15,OR(ANAGRAFICA!$R15="",ANAGRAFICA!$R15="Nessuna variazione")),AND(ANAGRAFICA!$J15="",ANAGRAFICA!$R15<>"",ANAGRAFICA!$R15<>"Nessuna variazione")),"GESTIONE DATA FINE INCOMPLETA; ","")&IF($Y18="","AGGIORNATO AL MANCANTE; ","")&IF(OR($AZ18="",$BJ18="",$BO18="",ANAGRAFICA!$I15="",ANAGRAFICA!$J15=""),"DATI PREVISIONALI INCOMPLETI; ","")&IF(LEFT($C18,5)="TEMP","CODICE COMMESSA TEMPORANEO; ","")),"DATI INCOMPLETI; ") | C18: =IF(ANAGRAFICA!$B15="","",ANAGRAFICA!$B15) | D18: =IF($C18="","",ANAGRAFICA!$C15) | E18: =IF($C18="","",ANAGRAFICA!$D15) | F18: =IF($C18="","",ANAGRAFICA!$E15) | G18: =IF($C18="","",ANAGRAFICA!$F15) | H18: =IF($C18="","",ANAGRAFICA!$G15) | I18: =IF($C18="","",ANAGRAFICA!$L15) | J18: =IF($C18="","",$AZ18) | K18: =IF($C18="","",$BA18) | L18: =IF($C18="","",$BB18) | M18: =IF($C18="","",MAX($BA18-$BB18,0)) | N18: =IF(OR($C18="",$W18=""),"",MAX($W18-$BA18,0)) | O18: =IF($C18="","",MAX($BC18-$BD18,0)) | P18: =IF(OR($C18="",$BG18="",$BH18="",$BI18=""),"",TEXT($BG18,"0.0%")&" / "&TEXT($BH18,"0.0%")&" / "&TEXT($BI18,"0.0%")) | Q18: =IF(OR($C18="",'BUDGET COMMESSA'!$D15="",'BUDGET COMMESSA'!$D15<=0,ANAGRAFICA!$J15=""),"",IF(OR($I18="Finito ritenute non previste",$I18="Finito con sblocco ritenute",$I18="Finito senza sblocco ritenute"),0,IF(AND($BK18>=$BJ18,ANAGRAFICA!$R15="Ritardo produttivo FIDA"),IF(ANAGRAFICA!$T15<>"",MAX(0,ANAGRAFICA!$J15-ANAGRAFICA!$T15),MAX(0,$Y18-ANAGRAFICA!$J15)),0))) | R18: =IF(OR($C18="",$BJ18=""),"",TEXT($BJ18,"#,##0.00")&" / "&TEXT($BK18,"#,##0.00")&" / "&TEXT($BL18,"#,##0.00")) | S18: =IF(OR($C18="",$BM18="",$BG18="",$BN18=""),"",TEXT($BM18,"0.0%")&" / "&TEXT($BG18,"0.0%")&" / "&TEXT($BN18,"0.0%")) | T18: =IF(OR($C18="",$BO18=""),"",IF($BR18>0,"BUDGET € "&TEXT($BO18,"#,##0.00")&" | SOSTENUTI € "&TEXT($BP18,"#,##0.00")&" | SFORAMENTO € "&TEXT($BR18,"#,##0.00"),"BUDGET € "&TEXT($BO18,"#,##0.00")&" | SOSTENUTI € "&TEXT($BP18,"#,##0.00")&" | RESIDUO € "&TEXT($BQ18,"#,##0.00"))) | U18: =IF($C18="","",$BS18) | V18: =IF($C18="","",$BV18) | W18: =IF(OR($C18="",$AZ18=""),"",MAX($AZ18-$BV18,0)) | AZ18: =IF($C18="","",ANAGRAFICA!$P15) | BA18: =IF($C18="","",SUMIF('MOVIMENTI 2026'!$B$7:$B$4206,$C18,'MOVIMENTI 2026'!$I$7:$I$4206)+SUMIF('SALDI AL 31.12.2025'!$A$6:$A$505,$C18,'SALDI AL 31.12.2025'!$C$6:$C$505)) | BB18: =IF($C18="","",SUMIF('MOVIMENTI 2026'!$B$7:$B$4206,$C18,'MOVIMENTI 2026'!$J$7:$J$4206)+SUMIF('SALDI AL 31.12.2025'!$A$6:$A$505,$C18,'SALDI AL 31.12.2025'!$D$6:$D$505)) | BC18: =IF($C18="","",SUMIF('MOVIMENTI 2026'!$B$7:$B$4206,$C18,'MOVIMENTI 2026'!$K$7:$K$4206)+SUMIF('SALDI AL 31.12.2025'!$A$6:$A$505,$C18,'SALDI AL 31.12.2025'!$E$6:$E$505)) | BD18: =IF($C18="","",SUMIF('MOVIMENTI 2026'!$B$7:$B$4206,$C18,'MOVIMENTI 2026'!$L$7:$L$4206)+SUMIF('SALDI AL 31.12.2025'!$A$6:$A$505,$C18,'SALDI AL 31.12.2025'!$F$6:$F$505)) | BE18: =IF(OR($C18="",$W18=""),"",MAX($W18-$BB18,0)) | BF18: =IF(OR($C18="",$W18=""),"",MAX($BB18-$W18,0)) | BG18: =IF(OR($C18="",$W18<=0),"",$BA18/$W18) | BH18: =IFERROR(IF(OR($C18="",ANAGRAFICA!$I15="",ANAGRAFICA!$J15="",ANAGRAFICA!$J15<=ANAGRAFICA!$I15,$Y18=""),"",IF(OR($I18="Finito ritenute non previste",$I18="Finito con sblocco ritenute",$I18="Finito senza sblocco ritenute"),1,MAX(0,MIN(1,($Y18-ANAGRAFICA!$I15)/(ANAGRAFICA!$J15-ANAGRAFICA!$I15))))),"") | BI18: =IF(OR($C18="",$BG18="",$BH18=""),"",$BG18-$BH18) | BJ18: =IFERROR(IF($C18="","",'BUDGET COMMESSA'!$D15),"") | BK18: =IF($C18="","",SUMIF('MOVIMENTI 2026'!$B$7:$B$4206,$C18,'MOVIMENTI 2026'!$N$7:$N$4206)+SUMIF('SALDI AL 31.12.2025'!$A$6:$A$505,$C18,'SALDI AL 31.12.2025'!$H$6:$H$505)) | BL18: =IF(OR($C18="",$BJ18=""),"",MAX($BJ18-$BK18,0)) | BM18: =IF(OR($C18="",$BJ18<=0),"",$BK18/$BJ18) | BN18: =IF(OR($C18="",$BM18="",$BG18=""),"",$BM18-$BG18) | BO18: =IFERROR(IF($C18="","",'BUDGET COMMESSA'!$G15),"") | BP18: =IF($C18="","",SUMIF('COSTI DIRETTI'!$C$6:$C$505,$C18,'COSTI DIRETTI'!$H$6:$H$505)+SUMIF('SALDI AL 31.12.2025'!$A$6:$A$505,$C18,'SALDI AL 31.12.2025'!$I$6:$I$505)) | BQ18: =IF(OR($C18="",$BO18=""),"",MAX($BO18-$BP18,0)) | BR18: =IF(OR($C18="",$BO18=""),"",MAX($BP18-$BO18,0)) | BS18: =IF($C18="","",$BK18*PARAMETRI!$B$4+$BP18) | BT18: =IF($A18="CRITICO",1,0) -> 0 | BU18: =IF($A18="ATTENZIONE",1,0) -> 0 | BV18: =IF($C18="","",SUMIF('MOVIMENTI 2026'!$B$7:$B$4206,$C18,'MOVIMENTI 2026'!$P$7:$P$4206)+SUMIF('SALDI AL 31.12.2025'!$A$6:$A$505,$C18,'SALDI AL 31.12.2025'!$G$6:$G$505))
A19: =IFERROR(IF($C19="","",IF(OR($BF19>0,$V19>$J19,AND(ISNUMBER($Q19),$Q19>0),AND($BI19<>"",$BI19<-PARAMETRI!$B$6),AND($BM19<>"",$BM19>=1),AND($BN19<>"",$BN19>PARAMETRI!$B$8),AND(ISNUMBER($BR19),$BR19>0)),"CRITICO",IF(OR($AZ19="",LEFT($C19,5)="TEMP",$BJ19="",$BO19="",ANAGRAFICA!$I16="",ANAGRAFICA!$J16="",$Y19="",AND(OR($I19="Finito ritenute non previste",$I19="Finito con sblocco ritenute",$I19="Finito senza sblocco ritenute"),ANAGRAFICA!$K16=""),OR(AND(ANAGRAFICA!$T16<>"",ANAGRAFICA!$J16<>ANAGRAFICA!$T16,OR(ANAGRAFICA!$R16="",ANAGRAFICA!$R16="Nessuna variazione")),AND(ANAGRAFICA!$J16="",ANAGRAFICA!$R16<>"",ANAGRAFICA!$R16<>"Nessuna variazione")),AND($BI19<>"",$BI19<-PARAMETRI!$B$5),AND($BN19<>"",$BN19>PARAMETRI!$B$7),AND($W19>0,$M19>$W19*PARAMETRI!$B$9),AND($O19>0,OR($I19="Finito ritenute non previste",$I19="Finito con sblocco ritenute",$I19="Finito senza sblocco ritenute")),AND($BA19>0,$BO19>0,$BP19=0),AND(OR($I19="Finito ritenute non previste",$I19="Finito con sblocco ritenute",$I19="Finito senza sblocco ritenute"),$W19>0,$N19>$W19*PARAMETRI!$B$9),$V19>0),"ATTENZIONE","REGOLARE"))),"ATTENZIONE") | B19: =IFERROR(IF($C19="","",IF($BF19>0,"FATTURATO OLTRE VALORE RECUPERABILE; ","")&IF($V19>$J19,"PERDITE ACCETTATE OLTRE CONTRATTO; ","")&IF($V19>0,"PERDITA SAL ACCETTATA (€ "&TEXT($V19,"#,##0.00")&"); ","")&IF(AND(ISNUMBER($Q19),$Q19>0),"RITARDO PRODUTTIVO ("&TEXT($Q19,"0")&" GG); ","")&IF(AND($BI19<>"",$BI19<-PARAMETRI!$B$5),"AVANZAMENTO PIÙ LENTO DEL TEMPO; ","")&IF(AND($BM19<>"",$BM19>1),"ORE OLTRE BUDGET; ","")&IF(AND($BM19<>"",$BM19=1),"ORE PREVENTIVATE ESAURITE; ","")&IF(AND($BN19<>"",$BN19>PARAMETRI!$B$7),"CONSUMO ORE SUPERIORE ALL'AVANZAMENTO; ","")&IF(AND(ISNUMBER($BR19),$BR19>0),"COSTI DIRETTI OLTRE BUDGET; ","")&IF(AND($W19>0,$M19>$W19*PARAMETRI!$B$9),"SAL MATURATO NON FATTURATO; ","")&IF(AND($O19>0,OR($I19="Finito ritenute non previste",$I19="Finito con sblocco ritenute",$I19="Finito senza sblocco ritenute")),"RITENUTE DA SBLOCCARE; ","")&IF(AND($BA19>0,$BO19>0,$BP19=0),"COSTI DIRETTI NON REGISTRATI; ","")&IF(AND(OR($I19="Finito ritenute non previste",$I19="Finito con sblocco ritenute",$I19="Finito senza sblocco ritenute"),$W19>0,$N19>$W19*PARAMETRI!$B$9),"CANTIERE FINITO CON RESIDUO LAVORI; ","")&IF(AND(OR($I19="Finito ritenute non previste",$I19="Finito con sblocco ritenute",$I19="Finito senza sblocco ritenute"),ANAGRAFICA!$K16=""),"DATA FINE EFFETTIVA MANCANTE; ","")&IF(OR(AND(ANAGRAFICA!$T16<>"",ANAGRAFICA!$J16<>ANAGRAFICA!$T16,OR(ANAGRAFICA!$R16="",ANAGRAFICA!$R16="Nessuna variazione")),AND(ANAGRAFICA!$J16="",ANAGRAFICA!$R16<>"",ANAGRAFICA!$R16<>"Nessuna variazione")),"GESTIONE DATA FINE INCOMPLETA; ","")&IF($Y19="","AGGIORNATO AL MANCANTE; ","")&IF(OR($AZ19="",$BJ19="",$BO19="",ANAGRAFICA!$I16="",ANAGRAFICA!$J16=""),"DATI PREVISIONALI INCOMPLETI; ","")&IF(LEFT($C19,5)="TEMP","CODICE COMMESSA TEMPORANEO; ","")),"DATI INCOMPLETI; ") | C19: =IF(ANAGRAFICA!$B16="","",ANAGRAFICA!$B16) | D19: =IF($C19="","",ANAGRAFICA!$C16) | E19: =IF($C19="","",ANAGRAFICA!$D16) | F19: =IF($C19="","",ANAGRAFICA!$E16) | G19: =IF($C19="","",ANAGRAFICA!$F16) | H19: =IF($C19="","",ANAGRAFICA!$G16) | I19: =IF($C19="","",ANAGRAFICA!$L16) | J19: =IF($C19="","",$AZ19) | K19: =IF($C19="","",$BA19) | L19: =IF($C19="","",$BB19) | M19: =IF($C19="","",MAX($BA19-$BB19,0)) | N19: =IF(OR($C19="",$W19=""),"",MAX($W19-$BA19,0)) | O19: =IF($C19="","",MAX($BC19-$BD19,0)) | P19: =IF(OR($C19="",$BG19="",$BH19="",$BI19=""),"",TEXT($BG19,"0.0%")&" / "&TEXT($BH19,"0.0%")&" / "&TEXT($BI19,"0.0%")) | Q19: =IF(OR($C19="",'BUDGET COMMESSA'!$D16="",'BUDGET COMMESSA'!$D16<=0,ANAGRAFICA!$J16=""),"",IF(OR($I19="Finito ritenute non previste",$I19="Finito con sblocco ritenute",$I19="Finito senza sblocco ritenute"),0,IF(AND($BK19>=$BJ19,ANAGRAFICA!$R16="Ritardo produttivo FIDA"),IF(ANAGRAFICA!$T16<>"",MAX(0,ANAGRAFICA!$J16-ANAGRAFICA!$T16),MAX(0,$Y19-ANAGRAFICA!$J16)),0))) | R19: =IF(OR($C19="",$BJ19=""),"",TEXT($BJ19,"#,##0.00")&" / "&TEXT($BK19,"#,##0.00")&" / "&TEXT($BL19,"#,##0.00")) | S19: =IF(OR($C19="",$BM19="",$BG19="",$BN19=""),"",TEXT($BM19,"0.0%")&" / "&TEXT($BG19,"0.0%")&" / "&TEXT($BN19,"0.0%")) | T19: =IF(OR($C19="",$BO19=""),"",IF($BR19>0,"BUDGET € "&TEXT($BO19,"#,##0.00")&" | SOSTENUTI € "&TEXT($BP19,"#,##0.00")&" | SFORAMENTO € "&TEXT($BR19,"#,##0.00"),"BUDGET € "&TEXT($BO19,"#,##0.00")&" | SOSTENUTI € "&TEXT($BP19,"#,##0.00")&" | RESIDUO € "&TEXT($BQ19,"#,##0.00"))) | U19: =IF($C19="","",$BS19) | V19: =IF($C19="","",$BV19) | W19: =IF(OR($C19="",$AZ19=""),"",MAX($AZ19-$BV19,0)) | AZ19: =IF($C19="","",ANAGRAFICA!$P16) | BA19: =IF($C19="","",SUMIF('MOVIMENTI 2026'!$B$7:$B$4206,$C19,'MOVIMENTI 2026'!$I$7:$I$4206)+SUMIF('SALDI AL 31.12.2025'!$A$6:$A$505,$C19,'SALDI AL 31.12.2025'!$C$6:$C$505)) | BB19: =IF($C19="","",SUMIF('MOVIMENTI 2026'!$B$7:$B$4206,$C19,'MOVIMENTI 2026'!$J$7:$J$4206)+SUMIF('SALDI AL 31.12.2025'!$A$6:$A$505,$C19,'SALDI AL 31.12.2025'!$D$6:$D$505)) | BC19: =IF($C19="","",SUMIF('MOVIMENTI 2026'!$B$7:$B$4206,$C19,'MOVIMENTI 2026'!$K$7:$K$4206)+SUMIF('SALDI AL 31.12.2025'!$A$6:$A$505,$C19,'SALDI AL 31.12.2025'!$E$6:$E$505)) | BD19: =IF($C19="","",SUMIF('MOVIMENTI 2026'!$B$7:$B$4206,$C19,'MOVIMENTI 2026'!$L$7:$L$4206)+SUMIF('SALDI AL 31.12.2025'!$A$6:$A$505,$C19,'SALDI AL 31.12.2025'!$F$6:$F$505)) | BE19: =IF(OR($C19="",$W19=""),"",MAX($W19-$BB19,0)) | BF19: =IF(OR($C19="",$W19=""),"",MAX($BB19-$W19,0)) | BG19: =IF(OR($C19="",$W19<=0),"",$BA19/$W19) | BH19: =IFERROR(IF(OR($C19="",ANAGRAFICA!$I16="",ANAGRAFICA!$J16="",ANAGRAFICA!$J16<=ANAGRAFICA!$I16,$Y19=""),"",IF(OR($I19="Finito ritenute non previste",$I19="Finito con sblocco ritenute",$I19="Finito senza sblocco ritenute"),1,MAX(0,MIN(1,($Y19-ANAGRAFICA!$I16)/(ANAGRAFICA!$J16-ANAGRAFICA!$I16))))),"") | BI19: =IF(OR($C19="",$BG19="",$BH19=""),"",$BG19-$BH19) | BJ19: =IFERROR(IF($C19="","",'BUDGET COMMESSA'!$D16),"") | BK19: =IF($C19="","",SUMIF('MOVIMENTI 2026'!$B$7:$B$4206,$C19,'MOVIMENTI 2026'!$N$7:$N$4206)+SUMIF('SALDI AL 31.12.2025'!$A$6:$A$505,$C19,'SALDI AL 31.12.2025'!$H$6:$H$505)) | BL19: =IF(OR($C19="",$BJ19=""),"",MAX($BJ19-$BK19,0)) | BM19: =IF(OR($C19="",$BJ19<=0),"",$BK19/$BJ19) | BN19: =IF(OR($C19="",$BM19="",$BG19=""),"",$BM19-$BG19) | BO19: =IFERROR(IF($C19="","",'BUDGET COMMESSA'!$G16),"") | BP19: =IF($C19="","",SUMIF('COSTI DIRETTI'!$C$6:$C$505,$C19,'COSTI DIRETTI'!$H$6:$H$505)+SUMIF('SALDI AL 31.12.2025'!$A$6:$A$505,$C19,'SALDI AL 31.12.2025'!$I$6:$I$505)) | BQ19: =IF(OR($C19="",$BO19=""),"",MAX($BO19-$BP19,0)) | BR19: =IF(OR($C19="",$BO19=""),"",MAX($BP19-$BO19,0)) | BS19: =IF($C19="","",$BK19*PARAMETRI!$B$4+$BP19) | BT19: =IF($A19="CRITICO",1,0) -> 0 | BU19: =IF($A19="ATTENZIONE",1,0) -> 0 | BV19: =IF($C19="","",SUMIF('MOVIMENTI 2026'!$B$7:$B$4206,$C19,'MOVIMENTI 2026'!$P$7:$P$4206)+SUMIF('SALDI AL 31.12.2025'!$A$6:$A$505,$C19,'SALDI AL 31.12.2025'!$G$6:$G$505))
A20: =IFERROR(IF($C20="","",IF(OR($BF20>0,$V20>$J20,AND(ISNUMBER($Q20),$Q20>0),AND($BI20<>"",$BI20<-PARAMETRI!$B$6),AND($BM20<>"",$BM20>=1),AND($BN20<>"",$BN20>PARAMETRI!$B$8),AND(ISNUMBER($BR20),$BR20>0)),"CRITICO",IF(OR($AZ20="",LEFT($C20,5)="TEMP",$BJ20="",$BO20="",ANAGRAFICA!$I17="",ANAGRAFICA!$J17="",$Y20="",AND(OR($I20="Finito ritenute non previste",$I20="Finito con sblocco ritenute",$I20="Finito senza sblocco ritenute"),ANAGRAFICA!$K17=""),OR(AND(ANAGRAFICA!$T17<>"",ANAGRAFICA!$J17<>ANAGRAFICA!$T17,OR(ANAGRAFICA!$R17="",ANAGRAFICA!$R17="Nessuna variazione")),AND(ANAGRAFICA!$J17="",ANAGRAFICA!$R17<>"",ANAGRAFICA!$R17<>"Nessuna variazione")),AND($BI20<>"",$BI20<-PARAMETRI!$B$5),AND($BN20<>"",$BN20>PARAMETRI!$B$7),AND($W20>0,$M20>$W20*PARAMETRI!$B$9),AND($O20>0,OR($I20="Finito ritenute non previste",$I20="Finito con sblocco ritenute",$I20="Finito senza sblocco ritenute")),AND($BA20>0,$BO20>0,$BP20=0),AND(OR($I20="Finito ritenute non previste",$I20="Finito con sblocco ritenute",$I20="Finito senza sblocco ritenute"),$W20>0,$N20>$W20*PARAMETRI!$B$9),$V20>0),"ATTENZIONE","REGOLARE"))),"ATTENZIONE") | B20: =IFERROR(IF($C20="","",IF($BF20>0,"FATTURATO OLTRE VALORE RECUPERABILE; ","")&IF($V20>$J20,"PERDITE ACCETTATE OLTRE CONTRATTO; ","")&IF($V20>0,"PERDITA SAL ACCETTATA (€ "&TEXT($V20,"#,##0.00")&"); ","")&IF(AND(ISNUMBER($Q20),$Q20>0),"RITARDO PRODUTTIVO ("&TEXT($Q20,"0")&" GG); ","")&IF(AND($BI20<>"",$BI20<-PARAMETRI!$B$5),"AVANZAMENTO PIÙ LENTO DEL TEMPO; ","")&IF(AND($BM20<>"",$BM20>1),"ORE OLTRE BUDGET; ","")&IF(AND($BM20<>"",$BM20=1),"ORE PREVENTIVATE ESAURITE; ","")&IF(AND($BN20<>"",$BN20>PARAMETRI!$B$7),"CONSUMO ORE SUPERIORE ALL'AVANZAMENTO; ","")&IF(AND(ISNUMBER($BR20),$BR20>0),"COSTI DIRETTI OLTRE BUDGET; ","")&IF(AND($W20>0,$M20>$W20*PARAMETRI!$B$9),"SAL MATURATO NON FATTURATO; ","")&IF(AND($O20>0,OR($I20="Finito ritenute non previste",$I20="Finito con sblocco ritenute",$I20="Finito senza sblocco ritenute")),"RITENUTE DA SBLOCCARE; ","")&IF(AND($BA20>0,$BO20>0,$BP20=0),"COSTI DIRETTI NON REGISTRATI; ","")&IF(AND(OR($I20="Finito ritenute non previste",$I20="Finito con sblocco ritenute",$I20="Finito senza sblocco ritenute"),$W20>0,$N20>$W20*PARAMETRI!$B$9),"CANTIERE FINITO CON RESIDUO LAVORI; ","")&IF(AND(OR($I20="Finito ritenute non previste",$I20="Finito con sblocco ritenute",$I20="Finito senza sblocco ritenute"),ANAGRAFICA!$K17=""),"DATA FINE EFFETTIVA MANCANTE; ","")&IF(OR(AND(ANAGRAFICA!$T17<>"",ANAGRAFICA!$J17<>ANAGRAFICA!$T17,OR(ANAGRAFICA!$R17="",ANAGRAFICA!$R17="Nessuna variazione")),AND(ANAGRAFICA!$J17="",ANAGRAFICA!$R17<>"",ANAGRAFICA!$R17<>"Nessuna variazione")),"GESTIONE DATA FINE INCOMPLETA; ","")&IF($Y20="","AGGIORNATO AL MANCANTE; ","")&IF(OR($AZ20="",$BJ20="",$BO20="",ANAGRAFICA!$I17="",ANAGRAFICA!$J17=""),"DATI PREVISIONALI INCOMPLETI; ","")&IF(LEFT($C20,5)="TEMP","CODICE COMMESSA TEMPORANEO; ","")),"DATI INCOMPLETI; ") | C20: =IF(ANAGRAFICA!$B17="","",ANAGRAFICA!$B17) | D20: =IF($C20="","",ANAGRAFICA!$C17) | E20: =IF($C20="","",ANAGRAFICA!$D17) | F20: =IF($C20="","",ANAGRAFICA!$E17) | G20: =IF($C20="","",ANAGRAFICA!$F17) | H20: =IF($C20="","",ANAGRAFICA!$G17) | I20: =IF($C20="","",ANAGRAFICA!$L17) | J20: =IF($C20="","",$AZ20) | K20: =IF($C20="","",$BA20) | L20: =IF($C20="","",$BB20) | M20: =IF($C20="","",MAX($BA20-$BB20,0)) | N20: =IF(OR($C20="",$W20=""),"",MAX($W20-$BA20,0)) | O20: =IF($C20="","",MAX($BC20-$BD20,0)) | P20: =IF(OR($C20="",$BG20="",$BH20="",$BI20=""),"",TEXT($BG20,"0.0%")&" / "&TEXT($BH20,"0.0%")&" / "&TEXT($BI20,"0.0%")) | Q20: =IF(OR($C20="",'BUDGET COMMESSA'!$D17="",'BUDGET COMMESSA'!$D17<=0,ANAGRAFICA!$J17=""),"",IF(OR($I20="Finito ritenute non previste",$I20="Finito con sblocco ritenute",$I20="Finito senza sblocco ritenute"),0,IF(AND($BK20>=$BJ20,ANAGRAFICA!$R17="Ritardo produttivo FIDA"),IF(ANAGRAFICA!$T17<>"",MAX(0,ANAGRAFICA!$J17-ANAGRAFICA!$T17),MAX(0,$Y20-ANAGRAFICA!$J17)),0))) | R20: =IF(OR($C20="",$BJ20=""),"",TEXT($BJ20,"#,##0.00")&" / "&TEXT($BK20,"#,##0.00")&" / "&TEXT($BL20,"#,##0.00")) | S20: =IF(OR($C20="",$BM20="",$BG20="",$BN20=""),"",TEXT($BM20,"0.0%")&" / "&TEXT($BG20,"0.0%")&" / "&TEXT($BN20,"0.0%")) | T20: =IF(OR($C20="",$BO20=""),"",IF($BR20>0,"BUDGET € "&TEXT($BO20,"#,##0.00")&" | SOSTENUTI € "&TEXT($BP20,"#,##0.00")&" | SFORAMENTO € "&TEXT($BR20,"#,##0.00"),"BUDGET € "&TEXT($BO20,"#,##0.00")&" | SOSTENUTI € "&TEXT($BP20,"#,##0.00")&" | RESIDUO € "&TEXT($BQ20,"#,##0.00"))) | U20: =IF($C20="","",$BS20) | V20: =IF($C20="","",$BV20) | W20: =IF(OR($C20="",$AZ20=""),"",MAX($AZ20-$BV20,0)) | AZ20: =IF($C20="","",ANAGRAFICA!$P17) | BA20: =IF($C20="","",SUMIF('MOVIMENTI 2026'!$B$7:$B$4206,$C20,'MOVIMENTI 2026'!$I$7:$I$4206)+SUMIF('SALDI AL 31.12.2025'!$A$6:$A$505,$C20,'SALDI AL 31.12.2025'!$C$6:$C$505)) | BB20: =IF($C20="","",SUMIF('MOVIMENTI 2026'!$B$7:$B$4206,$C20,'MOVIMENTI 2026'!$J$7:$J$4206)+SUMIF('SALDI AL 31.12.2025'!$A$6:$A$505,$C20,'SALDI AL 31.12.2025'!$D$6:$D$505)) | BC20: =IF($C20="","",SUMIF('MOVIMENTI 2026'!$B$7:$B$4206,$C20,'MOVIMENTI 2026'!$K$7:$K$4206)+SUMIF('SALDI AL 31.12.2025'!$A$6:$A$505,$C20,'SALDI AL 31.12.2025'!$E$6:$E$505)) | BD20: =IF($C20="","",SUMIF('MOVIMENTI 2026'!$B$7:$B$4206,$C20,'MOVIMENTI 2026'!$L$7:$L$4206)+SUMIF('SALDI AL 31.12.2025'!$A$6:$A$505,$C20,'SALDI AL 31.12.2025'!$F$6:$F$505)) | BE20: =IF(OR($C20="",$W20=""),"",MAX($W20-$BB20,0)) | BF20: =IF(OR($C20="",$W20=""),"",MAX($BB20-$W20,0)) | BG20: =IF(OR($C20="",$W20<=0),"",$BA20/$W20) | BH20: =IFERROR(IF(OR($C20="",ANAGRAFICA!$I17="",ANAGRAFICA!$J17="",ANAGRAFICA!$J17<=ANAGRAFICA!$I17,$Y20=""),"",IF(OR($I20="Finito ritenute non previste",$I20="Finito con sblocco ritenute",$I20="Finito senza sblocco ritenute"),1,MAX(0,MIN(1,($Y20-ANAGRAFICA!$I17)/(ANAGRAFICA!$J17-ANAGRAFICA!$I17))))),"") | BI20: =IF(OR($C20="",$BG20="",$BH20=""),"",$BG20-$BH20) | BJ20: =IFERROR(IF($C20="","",'BUDGET COMMESSA'!$D17),"") | BK20: =IF($C20="","",SUMIF('MOVIMENTI 2026'!$B$7:$B$4206,$C20,'MOVIMENTI 2026'!$N$7:$N$4206)+SUMIF('SALDI AL 31.12.2025'!$A$6:$A$505,$C20,'SALDI AL 31.12.2025'!$H$6:$H$505)) | BL20: =IF(OR($C20="",$BJ20=""),"",MAX($BJ20-$BK20,0)) | BM20: =IF(OR($C20="",$BJ20<=0),"",$BK20/$BJ20) | BN20: =IF(OR($C20="",$BM20="",$BG20=""),"",$BM20-$BG20) | BO20: =IFERROR(IF($C20="","",'BUDGET COMMESSA'!$G17),"") | BP20: =IF($C20="","",SUMIF('COSTI DIRETTI'!$C$6:$C$505,$C20,'COSTI DIRETTI'!$H$6:$H$505)+SUMIF('SALDI AL 31.12.2025'!$A$6:$A$505,$C20,'SALDI AL 31.12.2025'!$I$6:$I$505)) | BQ20: =IF(OR($C20="",$BO20=""),"",MAX($BO20-$BP20,0)) | BR20: =IF(OR($C20="",$BO20=""),"",MAX($BP20-$BO20,0)) | BS20: =IF($C20="","",$BK20*PARAMETRI!$B$4+$BP20) | BT20: =IF($A20="CRITICO",1,0) -> 0 | BU20: =IF($A20="ATTENZIONE",1,0) -> 0 | BV20: =IF($C20="","",SUMIF('MOVIMENTI 2026'!$B$7:$B$4206,$C20,'MOVIMENTI 2026'!$P$7:$P$4206)+SUMIF('SALDI AL 31.12.2025'!$A$6:$A$505,$C20,'SALDI AL 31.12.2025'!$G$6:$G$505))
A21: =IFERROR(IF($C21="","",IF(OR($BF21>0,$V21>$J21,AND(ISNUMBER($Q21),$Q21>0),AND($BI21<>"",$BI21<-PARAMETRI!$B$6),AND($BM21<>"",$BM21>=1),AND($BN21<>"",$BN21>PARAMETRI!$B$8),AND(ISNUMBER($BR21),$BR21>0)),"CRITICO",IF(OR($AZ21="",LEFT($C21,5)="TEMP",$BJ21="",$BO21="",ANAGRAFICA!$I18="",ANAGRAFICA!$J18="",$Y21="",AND(OR($I21="Finito ritenute non previste",$I21="Finito con sblocco ritenute",$I21="Finito senza sblocco ritenute"),ANAGRAFICA!$K18=""),OR(AND(ANAGRAFICA!$T18<>"",ANAGRAFICA!$J18<>ANAGRAFICA!$T18,OR(ANAGRAFICA!$R18="",ANAGRAFICA!$R18="Nessuna variazione")),AND(ANAGRAFICA!$J18="",ANAGRAFICA!$R18<>"",ANAGRAFICA!$R18<>"Nessuna variazione")),AND($BI21<>"",$BI21<-PARAMETRI!$B$5),AND($BN21<>"",$BN21>PARAMETRI!$B$7),AND($W21>0,$M21>$W21*PARAMETRI!$B$9),AND($O21>0,OR($I21="Finito ritenute non previste",$I21="Finito con sblocco ritenute",$I21="Finito senza sblocco ritenute")),AND($BA21>0,$BO21>0,$BP21=0),AND(OR($I21="Finito ritenute non previste",$I21="Finito con sblocco ritenute",$I21="Finito senza sblocco ritenute"),$W21>0,$N21>$W21*PARAMETRI!$B$9),$V21>0),"ATTENZIONE","REGOLARE"))),"ATTENZIONE") | B21: =IFERROR(IF($C21="","",IF($BF21>0,"FATTURATO OLTRE VALORE RECUPERABILE; ","")&IF($V21>$J21,"PERDITE ACCETTATE OLTRE CONTRATTO; ","")&IF($V21>0,"PERDITA SAL ACCETTATA (€ "&TEXT($V21,"#,##0.00")&"); ","")&IF(AND(ISNUMBER($Q21),$Q21>0),"RITARDO PRODUTTIVO ("&TEXT($Q21,"0")&" GG); ","")&IF(AND($BI21<>"",$BI21<-PARAMETRI!$B$5),"AVANZAMENTO PIÙ LENTO DEL TEMPO; ","")&IF(AND($BM21<>"",$BM21>1),"ORE OLTRE BUDGET; ","")&IF(AND($BM21<>"",$BM21=1),"ORE PREVENTIVATE ESAURITE; ","")&IF(AND($BN21<>"",$BN21>PARAMETRI!$B$7),"CONSUMO ORE SUPERIORE ALL'AVANZAMENTO; ","")&IF(AND(ISNUMBER($BR21),$BR21>0),"COSTI DIRETTI OLTRE BUDGET; ","")&IF(AND($W21>0,$M21>$W21*PARAMETRI!$B$9),"SAL MATURATO NON FATTURATO; ","")&IF(AND($O21>0,OR($I21="Finito ritenute non previste",$I21="Finito con sblocco ritenute",$I21="Finito senza sblocco ritenute")),"RITENUTE DA SBLOCCARE; ","")&IF(AND($BA21>0,$BO21>0,$BP21=0),"COSTI DIRETTI NON REGISTRATI; ","")&IF(AND(OR($I21="Finito ritenute non previste",$I21="Finito con sblocco ritenute",$I21="Finito senza sblocco ritenute"),$W21>0,$N21>$W21*PARAMETRI!$B$9),"CANTIERE FINITO CON RESIDUO LAVORI; ","")&IF(AND(OR($I21="Finito ritenute non previste",$I21="Finito con sblocco ritenute",$I21="Finito senza sblocco ritenute"),ANAGRAFICA!$K18=""),"DATA FINE EFFETTIVA MANCANTE; ","")&IF(OR(AND(ANAGRAFICA!$T18<>"",ANAGRAFICA!$J18<>ANAGRAFICA!$T18,OR(ANAGRAFICA!$R18="",ANAGRAFICA!$R18="Nessuna variazione")),AND(ANAGRAFICA!$J18="",ANAGRAFICA!$R18<>"",ANAGRAFICA!$R18<>"Nessuna variazione")),"GESTIONE DATA FINE INCOMPLETA; ","")&IF($Y21="","AGGIORNATO AL MANCANTE; ","")&IF(OR($AZ21="",$BJ21="",$BO21="",ANAGRAFICA!$I18="",ANAGRAFICA!$J18=""),"DATI PREVISIONALI INCOMPLETI; ","")&IF(LEFT($C21,5)="TEMP","CODICE COMMESSA TEMPORANEO; ","")),"DATI INCOMPLETI; ") | C21: =IF(ANAGRAFICA!$B18="","",ANAGRAFICA!$B18) | D21: =IF($C21="","",ANAGRAFICA!$C18) | E21: =IF($C21="","",ANAGRAFICA!$D18) | F21: =IF($C21="","",ANAGRAFICA!$E18) | G21: =IF($C21="","",ANAGRAFICA!$F18) | H21: =IF($C21="","",ANAGRAFICA!$G18) | I21: =IF($C21="","",ANAGRAFICA!$L18) | J21: =IF($C21="","",$AZ21) | K21: =IF($C21="","",$BA21) | L21: =IF($C21="","",$BB21) | M21: =IF($C21="","",MAX($BA21-$BB21,0)) | N21: =IF(OR($C21="",$W21=""),"",MAX($W21-$BA21,0)) | O21: =IF($C21="","",MAX($BC21-$BD21,0)) | P21: =IF(OR($C21="",$BG21="",$BH21="",$BI21=""),"",TEXT($BG21,"0.0%")&" / "&TEXT($BH21,"0.0%")&" / "&TEXT($BI21,"0.0%")) | Q21: =IF(OR($C21="",'BUDGET COMMESSA'!$D18="",'BUDGET COMMESSA'!$D18<=0,ANAGRAFICA!$J18=""),"",IF(OR($I21="Finito ritenute non previste",$I21="Finito con sblocco ritenute",$I21="Finito senza sblocco ritenute"),0,IF(AND($BK21>=$BJ21,ANAGRAFICA!$R18="Ritardo produttivo FIDA"),IF(ANAGRAFICA!$T18<>"",MAX(0,ANAGRAFICA!$J18-ANAGRAFICA!$T18),MAX(0,$Y21-ANAGRAFICA!$J18)),0))) | R21: =IF(OR($C21="",$BJ21=""),"",TEXT($BJ21,"#,##0.00")&" / "&TEXT($BK21,"#,##0.00")&" / "&TEXT($BL21,"#,##0.00")) | S21: =IF(OR($C21="",$BM21="",$BG21="",$BN21=""),"",TEXT($BM21,"0.0%")&" / "&TEXT($BG21,"0.0%")&" / "&TEXT($BN21,"0.0%")) | T21: =IF(OR($C21="",$BO21=""),"",IF($BR21>0,"BUDGET € "&TEXT($BO21,"#,##0.00")&" | SOSTENUTI € "&TEXT($BP21,"#,##0.00")&" | SFORAMENTO € "&TEXT($BR21,"#,##0.00"),"BUDGET € "&TEXT($BO21,"#,##0.00")&" | SOSTENUTI € "&TEXT($BP21,"#,##0.00")&" | RESIDUO € "&TEXT($BQ21,"#,##0.00"))) | U21: =IF($C21="","",$BS21) | V21: =IF($C21="","",$BV21) | W21: =IF(OR($C21="",$AZ21=""),"",MAX($AZ21-$BV21,0)) | AZ21: =IF($C21="","",ANAGRAFICA!$P18) | BA21: =IF($C21="","",SUMIF('MOVIMENTI 2026'!$B$7:$B$4206,$C21,'MOVIMENTI 2026'!$I$7:$I$4206)+SUMIF('SALDI AL 31.12.2025'!$A$6:$A$505,$C21,'SALDI AL 31.12.2025'!$C$6:$C$505)) | BB21: =IF($C21="","",SUMIF('MOVIMENTI 2026'!$B$7:$B$4206,$C21,'MOVIMENTI 2026'!$J$7:$J$4206)+SUMIF('SALDI AL 31.12.2025'!$A$6:$A$505,$C21,'SALDI AL 31.12.2025'!$D$6:$D$505)) | BC21: =IF($C21="","",SUMIF('MOVIMENTI 2026'!$B$7:$B$4206,$C21,'MOVIMENTI 2026'!$K$7:$K$4206)+SUMIF('SALDI AL 31.12.2025'!$A$6:$A$505,$C21,'SALDI AL 31.12.2025'!$E$6:$E$505)) | BD21: =IF($C21="","",SUMIF('MOVIMENTI 2026'!$B$7:$B$4206,$C21,'MOVIMENTI 2026'!$L$7:$L$4206)+SUMIF('SALDI AL 31.12.2025'!$A$6:$A$505,$C21,'SALDI AL 31.12.2025'!$F$6:$F$505)) | BE21: =IF(OR($C21="",$W21=""),"",MAX($W21-$BB21,0)) | BF21: =IF(OR($C21="",$W21=""),"",MAX($BB21-$W21,0)) | BG21: =IF(OR($C21="",$W21<=0),"",$BA21/$W21) | BH21: =IFERROR(IF(OR($C21="",ANAGRAFICA!$I18="",ANAGRAFICA!$J18="",ANAGRAFICA!$J18<=ANAGRAFICA!$I18,$Y21=""),"",IF(OR($I21="Finito ritenute non previste",$I21="Finito con sblocco ritenute",$I21="Finito senza sblocco ritenute"),1,MAX(0,MIN(1,($Y21-ANAGRAFICA!$I18)/(ANAGRAFICA!$J18-ANAGRAFICA!$I18))))),"") | BI21: =IF(OR($C21="",$BG21="",$BH21=""),"",$BG21-$BH21) | BJ21: =IFERROR(IF($C21="","",'BUDGET COMMESSA'!$D18),"") | BK21: =IF($C21="","",SUMIF('MOVIMENTI 2026'!$B$7:$B$4206,$C21,'MOVIMENTI 2026'!$N$7:$N$4206)+SUMIF('SALDI AL 31.12.2025'!$A$6:$A$505,$C21,'SALDI AL 31.12.2025'!$H$6:$H$505)) | BL21: =IF(OR($C21="",$BJ21=""),"",MAX($BJ21-$BK21,0)) | BM21: =IF(OR($C21="",$BJ21<=0),"",$BK21/$BJ21) | BN21: =IF(OR($C21="",$BM21="",$BG21=""),"",$BM21-$BG21) | BO21: =IFERROR(IF($C21="","",'BUDGET COMMESSA'!$G18),"") | BP21: =IF($C21="","",SUMIF('COSTI DIRETTI'!$C$6:$C$505,$C21,'COSTI DIRETTI'!$H$6:$H$505)+SUMIF('SALDI AL 31.12.2025'!$A$6:$A$505,$C21,'SALDI AL 31.12.2025'!$I$6:$I$505)) | BQ21: =IF(OR($C21="",$BO21=""),"",MAX($BO21-$BP21,0)) | BR21: =IF(OR($C21="",$BO21=""),"",MAX($BP21-$BO21,0)) | BS21: =IF($C21="","",$BK21*PARAMETRI!$B$4+$BP21) | BT21: =IF($A21="CRITICO",1,0) -> 0 | BU21: =IF($A21="ATTENZIONE",1,0) -> 0 | BV21: =IF($C21="","",SUMIF('MOVIMENTI 2026'!$B$7:$B$4206,$C21,'MOVIMENTI 2026'!$P$7:$P$4206)+SUMIF('SALDI AL 31.12.2025'!$A$6:$A$505,$C21,'SALDI AL 31.12.2025'!$G$6:$G$505))
A22: =IFERROR(IF($C22="","",IF(OR($BF22>0,$V22>$J22,AND(ISNUMBER($Q22),$Q22>0),AND($BI22<>"",$BI22<-PARAMETRI!$B$6),AND($BM22<>"",$BM22>=1),AND($BN22<>"",$BN22>PARAMETRI!$B$8),AND(ISNUMBER($BR22),$BR22>0)),"CRITICO",IF(OR($AZ22="",LEFT($C22,5)="TEMP",$BJ22="",$BO22="",ANAGRAFICA!$I19="",ANAGRAFICA!$J19="",$Y22="",AND(OR($I22="Finito ritenute non previste",$I22="Finito con sblocco ritenute",$I22="Finito senza sblocco ritenute"),ANAGRAFICA!$K19=""),OR(AND(ANAGRAFICA!$T19<>"",ANAGRAFICA!$J19<>ANAGRAFICA!$T19,OR(ANAGRAFICA!$R19="",ANAGRAFICA!$R19="Nessuna variazione")),AND(ANAGRAFICA!$J19="",ANAGRAFICA!$R19<>"",ANAGRAFICA!$R19<>"Nessuna variazione")),AND($BI22<>"",$BI22<-PARAMETRI!$B$5),AND($BN22<>"",$BN22>PARAMETRI!$B$7),AND($W22>0,$M22>$W22*PARAMETRI!$B$9),AND($O22>0,OR($I22="Finito ritenute non previste",$I22="Finito con sblocco ritenute",$I22="Finito senza sblocco ritenute")),AND($BA22>0,$BO22>0,$BP22=0),AND(OR($I22="Finito ritenute non previste",$I22="Finito con sblocco ritenute",$I22="Finito senza sblocco ritenute"),$W22>0,$N22>$W22*PARAMETRI!$B$9),$V22>0),"ATTENZIONE","REGOLARE"))),"ATTENZIONE") | B22: =IFERROR(IF($C22="","",IF($BF22>0,"FATTURATO OLTRE VALORE RECUPERABILE; ","")&IF($V22>$J22,"PERDITE ACCETTATE OLTRE CONTRATTO; ","")&IF($V22>0,"PERDITA SAL ACCETTATA (€ "&TEXT($V22,"#,##0.00")&"); ","")&IF(AND(ISNUMBER($Q22),$Q22>0),"RITARDO PRODUTTIVO ("&TEXT($Q22,"0")&" GG); ","")&IF(AND($BI22<>"",$BI22<-PARAMETRI!$B$5),"AVANZAMENTO PIÙ LENTO DEL TEMPO; ","")&IF(AND($BM22<>"",$BM22>1),"ORE OLTRE BUDGET; ","")&IF(AND($BM22<>"",$BM22=1),"ORE PREVENTIVATE ESAURITE; ","")&IF(AND($BN22<>"",$BN22>PARAMETRI!$B$7),"CONSUMO ORE SUPERIORE ALL'AVANZAMENTO; ","")&IF(AND(ISNUMBER($BR22),$BR22>0),"COSTI DIRETTI OLTRE BUDGET; ","")&IF(AND($W22>0,$M22>$W22*PARAMETRI!$B$9),"SAL MATURATO NON FATTURATO; ","")&IF(AND($O22>0,OR($I22="Finito ritenute non previste",$I22="Finito con sblocco ritenute",$I22="Finito senza sblocco ritenute")),"RITENUTE DA SBLOCCARE; ","")&IF(AND($BA22>0,$BO22>0,$BP22=0),"COSTI DIRETTI NON REGISTRATI; ","")&IF(AND(OR($I22="Finito ritenute non previste",$I22="Finito con sblocco ritenute",$I22="Finito senza sblocco ritenute"),$W22>0,$N22>$W22*PARAMETRI!$B$9),"CANTIERE FINITO CON RESIDUO LAVORI; ","")&IF(AND(OR($I22="Finito ritenute non previste",$I22="Finito con sblocco ritenute",$I22="Finito senza sblocco ritenute"),ANAGRAFICA!$K19=""),"DATA FINE EFFETTIVA MANCANTE; ","")&IF(OR(AND(ANAGRAFICA!$T19<>"",ANAGRAFICA!$J19<>ANAGRAFICA!$T19,OR(ANAGRAFICA!$R19="",ANAGRAFICA!$R19="Nessuna variazione")),AND(ANAGRAFICA!$J19="",ANAGRAFICA!$R19<>"",ANAGRAFICA!$R19<>"Nessuna variazione")),"GESTIONE DATA FINE INCOMPLETA; ","")&IF($Y22="","AGGIORNATO AL MANCANTE; ","")&IF(OR($AZ22="",$BJ22="",$BO22="",ANAGRAFICA!$I19="",ANAGRAFICA!$J19=""),"DATI PREVISIONALI INCOMPLETI; ","")&IF(LEFT($C22,5)="TEMP","CODICE COMMESSA TEMPORANEO; ","")),"DATI INCOMPLETI; ") | C22: =IF(ANAGRAFICA!$B19="","",ANAGRAFICA!$B19) | D22: =IF($C22="","",ANAGRAFICA!$C19) | E22: =IF($C22="","",ANAGRAFICA!$D19) | F22: =IF($C22="","",ANAGRAFICA!$E19) | G22: =IF($C22="","",ANAGRAFICA!$F19) | H22: =IF($C22="","",ANAGRAFICA!$G19) | I22: =IF($C22="","",ANAGRAFICA!$L19) | J22: =IF($C22="","",$AZ22) | K22: =IF($C22="","",$BA22) | L22: =IF($C22="","",$BB22) | M22: =IF($C22="","",MAX($BA22-$BB22,0)) | N22: =IF(OR($C22="",$W22=""),"",MAX($W22-$BA22,0)) | O22: =IF($C22="","",MAX($BC22-$BD22,0)) | P22: =IF(OR($C22="",$BG22="",$BH22="",$BI22=""),"",TEXT($BG22,"0.0%")&" / "&TEXT($BH22,"0.0%")&" / "&TEXT($BI22,"0.0%")) | Q22: =IF(OR($C22="",'BUDGET COMMESSA'!$D19="",'BUDGET COMMESSA'!$D19<=0,ANAGRAFICA!$J19=""),"",IF(OR($I22="Finito ritenute non previste",$I22="Finito con sblocco ritenute",$I22="Finito senza sblocco ritenute"),0,IF(AND($BK22>=$BJ22,ANAGRAFICA!$R19="Ritardo produttivo FIDA"),IF(ANAGRAFICA!$T19<>"",MAX(0,ANAGRAFICA!$J19-ANAGRAFICA!$T19),MAX(0,$Y22-ANAGRAFICA!$J19)),0))) | R22: =IF(OR($C22="",$BJ22=""),"",TEXT($BJ22,"#,##0.00")&" / "&TEXT($BK22,"#,##0.00")&" / "&TEXT($BL22,"#,##0.00")) | S22: =IF(OR($C22="",$BM22="",$BG22="",$BN22=""),"",TEXT($BM22,"0.0%")&" / "&TEXT($BG22,"0.0%")&" / "&TEXT($BN22,"0.0%")) | T22: =IF(OR($C22="",$BO22=""),"",IF($BR22>0,"BUDGET € "&TEXT($BO22,"#,##0.00")&" | SOSTENUTI € "&TEXT($BP22,"#,##0.00")&" | SFORAMENTO € "&TEXT($BR22,"#,##0.00"),"BUDGET € "&TEXT($BO22,"#,##0.00")&" | SOSTENUTI € "&TEXT($BP22,"#,##0.00")&" | RESIDUO € "&TEXT($BQ22,"#,##0.00"))) | U22: =IF($C22="","",$BS22) | V22: =IF($C22="","",$BV22) | W22: =IF(OR($C22="",$AZ22=""),"",MAX($AZ22-$BV22,0)) | AZ22: =IF($C22="","",ANAGRAFICA!$P19) | BA22: =IF($C22="","",SUMIF('MOVIMENTI 2026'!$B$7:$B$4206,$C22,'MOVIMENTI 2026'!$I$7:$I$4206)+SUMIF('SALDI AL 31.12.2025'!$A$6:$A$505,$C22,'SALDI AL 31.12.2025'!$C$6:$C$505)) | BB22: =IF($C22="","",SUMIF('MOVIMENTI 2026'!$B$7:$B$4206,$C22,'MOVIMENTI 2026'!$J$7:$J$4206)+SUMIF('SALDI AL 31.12.2025'!$A$6:$A$505,$C22,'SALDI AL 31.12.2025'!$D$6:$D$505)) | BC22: =IF($C22="","",SUMIF('MOVIMENTI 2026'!$B$7:$B$4206,$C22,'MOVIMENTI 2026'!$K$7:$K$4206)+SUMIF('SALDI AL 31.12.2025'!$A$6:$A$505,$C22,'SALDI AL 31.12.2025'!$E$6:$E$505)) | BD22: =IF($C22="","",SUMIF('MOVIMENTI 2026'!$B$7:$B$4206,$C22,'MOVIMENTI 2026'!$L$7:$L$4206)+SUMIF('SALDI AL 31.12.2025'!$A$6:$A$505,$C22,'SALDI AL 31.12.2025'!$F$6:$F$505)) | BE22: =IF(OR($C22="",$W22=""),"",MAX($W22-$BB22,0)) | BF22: =IF(OR($C22="",$W22=""),"",MAX($BB22-$W22,0)) | BG22: =IF(OR($C22="",$W22<=0),"",$BA22/$W22) | BH22: =IFERROR(IF(OR($C22="",ANAGRAFICA!$I19="",ANAGRAFICA!$J19="",ANAGRAFICA!$J19<=ANAGRAFICA!$I19,$Y22=""),"",IF(OR($I22="Finito ritenute non previste",$I22="Finito con sblocco ritenute",$I22="Finito senza sblocco ritenute"),1,MAX(0,MIN(1,($Y22-ANAGRAFICA!$I19)/(ANAGRAFICA!$J19-ANAGRAFICA!$I19))))),"") | BI22: =IF(OR($C22="",$BG22="",$BH22=""),"",$BG22-$BH22) | BJ22: =IFERROR(IF($C22="","",'BUDGET COMMESSA'!$D19),"") | BK22: =IF($C22="","",SUMIF('MOVIMENTI 2026'!$B$7:$B$4206,$C22,'MOVIMENTI 2026'!$N$7:$N$4206)+SUMIF('SALDI AL 31.12.2025'!$A$6:$A$505,$C22,'SALDI AL 31.12.2025'!$H$6:$H$505)) | BL22: =IF(OR($C22="",$BJ22=""),"",MAX($BJ22-$BK22,0)) | BM22: =IF(OR($C22="",$BJ22<=0),"",$BK22/$BJ22) | BN22: =IF(OR($C22="",$BM22="",$BG22=""),"",$BM22-$BG22) | BO22: =IFERROR(IF($C22="","",'BUDGET COMMESSA'!$G19),"") | BP22: =IF($C22="","",SUMIF('COSTI DIRETTI'!$C$6:$C$505,$C22,'COSTI DIRETTI'!$H$6:$H$505)+SUMIF('SALDI AL 31.12.2025'!$A$6:$A$505,$C22,'SALDI AL 31.12.2025'!$I$6:$I$505)) | BQ22: =IF(OR($C22="",$BO22=""),"",MAX($BO22-$BP22,0)) | BR22: =IF(OR($C22="",$BO22=""),"",MAX($BP22-$BO22,0)) | BS22: =IF($C22="","",$BK22*PARAMETRI!$B$4+$BP22) | BT22: =IF($A22="CRITICO",1,0) -> 0 | BU22: =IF($A22="ATTENZIONE",1,0) -> 0 | BV22: =IF($C22="","",SUMIF('MOVIMENTI 2026'!$B$7:$B$4206,$C22,'MOVIMENTI 2026'!$P$7:$P$4206)+SUMIF('SALDI AL 31.12.2025'!$A$6:$A$505,$C22,'SALDI AL 31.12.2025'!$G$6:$G$505))
A23: =IFERROR(IF($C23="","",IF(OR($BF23>0,$V23>$J23,AND(ISNUMBER($Q23),$Q23>0),AND($BI23<>"",$BI23<-PARAMETRI!$B$6),AND($BM23<>"",$BM23>=1),AND($BN23<>"",$BN23>PARAMETRI!$B$8),AND(ISNUMBER($BR23),$BR23>0)),"CRITICO",IF(OR($AZ23="",LEFT($C23,5)="TEMP",$BJ23="",$BO23="",ANAGRAFICA!$I20="",ANAGRAFICA!$J20="",$Y23="",AND(OR($I23="Finito ritenute non previste",$I23="Finito con sblocco ritenute",$I23="Finito senza sblocco ritenute"),ANAGRAFICA!$K20=""),OR(AND(ANAGRAFICA!$T20<>"",ANAGRAFICA!$J20<>ANAGRAFICA!$T20,OR(ANAGRAFICA!$R20="",ANAGRAFICA!$R20="Nessuna variazione")),AND(ANAGRAFICA!$J20="",ANAGRAFICA!$R20<>"",ANAGRAFICA!$R20<>"Nessuna variazione")),AND($BI23<>"",$BI23<-PARAMETRI!$B$5),AND($BN23<>"",$BN23>PARAMETRI!$B$7),AND($W23>0,$M23>$W23*PARAMETRI!$B$9),AND($O23>0,OR($I23="Finito ritenute non previste",$I23="Finito con sblocco ritenute",$I23="Finito senza sblocco ritenute")),AND($BA23>0,$BO23>0,$BP23=0),AND(OR($I23="Finito ritenute non previste",$I23="Finito con sblocco ritenute",$I23="Finito senza sblocco ritenute"),$W23>0,$N23>$W23*PARAMETRI!$B$9),$V23>0),"ATTENZIONE","REGOLARE"))),"ATTENZIONE") | B23: =IFERROR(IF($C23="","",IF($BF23>0,"FATTURATO OLTRE VALORE RECUPERABILE; ","")&IF($V23>$J23,"PERDITE ACCETTATE OLTRE CONTRATTO; ","")&IF($V23>0,"PERDITA SAL ACCETTATA (€ "&TEXT($V23,"#,##0.00")&"); ","")&IF(AND(ISNUMBER($Q23),$Q23>0),"RITARDO PRODUTTIVO ("&TEXT($Q23,"0")&" GG); ","")&IF(AND($BI23<>"",$BI23<-PARAMETRI!$B$5),"AVANZAMENTO PIÙ LENTO DEL TEMPO; ","")&IF(AND($BM23<>"",$BM23>1),"ORE OLTRE BUDGET; ","")&IF(AND($BM23<>"",$BM23=1),"ORE PREVENTIVATE ESAURITE; ","")&IF(AND($BN23<>"",$BN23>PARAMETRI!$B$7),"CONSUMO ORE SUPERIORE ALL'AVANZAMENTO; ","")&IF(AND(ISNUMBER($BR23),$BR23>0),"COSTI DIRETTI OLTRE BUDGET; ","")&IF(AND($W23>0,$M23>$W23*PARAMETRI!$B$9),"SAL MATURATO NON FATTURATO; ","")&IF(AND($O23>0,OR($I23="Finito ritenute non previste",$I23="Finito con sblocco ritenute",$I23="Finito senza sblocco ritenute")),"RITENUTE DA SBLOCCARE; ","")&IF(AND($BA23>0,$BO23>0,$BP23=0),"COSTI DIRETTI NON REGISTRATI; ","")&IF(AND(OR($I23="Finito ritenute non previste",$I23="Finito con sblocco ritenute",$I23="Finito senza sblocco ritenute"),$W23>0,$N23>$W23*PARAMETRI!$B$9),"CANTIERE FINITO CON RESIDUO LAVORI; ","")&IF(AND(OR($I23="Finito ritenute non previste",$I23="Finito con sblocco ritenute",$I23="Finito senza sblocco ritenute"),ANAGRAFICA!$K20=""),"DATA FINE EFFETTIVA MANCANTE; ","")&IF(OR(AND(ANAGRAFICA!$T20<>"",ANAGRAFICA!$J20<>ANAGRAFICA!$T20,OR(ANAGRAFICA!$R20="",ANAGRAFICA!$R20="Nessuna variazione")),AND(ANAGRAFICA!$J20="",ANAGRAFICA!$R20<>"",ANAGRAFICA!$R20<>"Nessuna variazione")),"GESTIONE DATA FINE INCOMPLETA; ","")&IF($Y23="","AGGIORNATO AL MANCANTE; ","")&IF(OR($AZ23="",$BJ23="",$BO23="",ANAGRAFICA!$I20="",ANAGRAFICA!$J20=""),"DATI PREVISIONALI INCOMPLETI; ","")&IF(LEFT($C23,5)="TEMP","CODICE COMMESSA TEMPORANEO; ","")),"DATI INCOMPLETI; ") | C23: =IF(ANAGRAFICA!$B20="","",ANAGRAFICA!$B20) | D23: =IF($C23="","",ANAGRAFICA!$C20) | E23: =IF($C23="","",ANAGRAFICA!$D20) | F23: =IF($C23="","",ANAGRAFICA!$E20) | G23: =IF($C23="","",ANAGRAFICA!$F20) | H23: =IF($C23="","",ANAGRAFICA!$G20) | I23: =IF($C23="","",ANAGRAFICA!$L20) | J23: =IF($C23="","",$AZ23) | K23: =IF($C23="","",$BA23) | L23: =IF($C23="","",$BB23) | M23: =IF($C23="","",MAX($BA23-$BB23,0)) | N23: =IF(OR($C23="",$W23=""),"",MAX($W23-$BA23,0)) | O23: =IF($C23="","",MAX($BC23-$BD23,0)) | P23: =IF(OR($C23="",$BG23="",$BH23="",$BI23=""),"",TEXT($BG23,"0.0%")&" / "&TEXT($BH23,"0.0%")&" / "&TEXT($BI23,"0.0%")) | Q23: =IF(OR($C23="",'BUDGET COMMESSA'!$D20="",'BUDGET COMMESSA'!$D20<=0,ANAGRAFICA!$J20=""),"",IF(OR($I23="Finito ritenute non previste",$I23="Finito con sblocco ritenute",$I23="Finito senza sblocco ritenute"),0,IF(AND($BK23>=$BJ23,ANAGRAFICA!$R20="Ritardo produttivo FIDA"),IF(ANAGRAFICA!$T20<>"",MAX(0,ANAGRAFICA!$J20-ANAGRAFICA!$T20),MAX(0,$Y23-ANAGRAFICA!$J20)),0))) | R23: =IF(OR($C23="",$BJ23=""),"",TEXT($BJ23,"#,##0.00")&" / "&TEXT($BK23,"#,##0.00")&" / "&TEXT($BL23,"#,##0.00")) | S23: =IF(OR($C23="",$BM23="",$BG23="",$BN23=""),"",TEXT($BM23,"0.0%")&" / "&TEXT($BG23,"0.0%")&" / "&TEXT($BN23,"0.0%")) | T23: =IF(OR($C23="",$BO23=""),"",IF($BR23>0,"BUDGET € "&TEXT($BO23,"#,##0.00")&" | SOSTENUTI € "&TEXT($BP23,"#,##0.00")&" | SFORAMENTO € "&TEXT($BR23,"#,##0.00"),"BUDGET € "&TEXT($BO23,"#,##0.00")&" | SOSTENUTI € "&TEXT($BP23,"#,##0.00")&" | RESIDUO € "&TEXT($BQ23,"#,##0.00"))) | U23: =IF($C23="","",$BS23) | V23: =IF($C23="","",$BV23) | W23: =IF(OR($C23="",$AZ23=""),"",MAX($AZ23-$BV23,0)) | AZ23: =IF($C23="","",ANAGRAFICA!$P20) | BA23: =IF($C23="","",SUMIF('MOVIMENTI 2026'!$B$7:$B$4206,$C23,'MOVIMENTI 2026'!$I$7:$I$4206)+SUMIF('SALDI AL 31.12.2025'!$A$6:$A$505,$C23,'SALDI AL 31.12.2025'!$C$6:$C$505)) | BB23: =IF($C23="","",SUMIF('MOVIMENTI 2026'!$B$7:$B$4206,$C23,'MOVIMENTI 2026'!$J$7:$J$4206)+SUMIF('SALDI AL 31.12.2025'!$A$6:$A$505,$C23,'SALDI AL 31.12.2025'!$D$6:$D$505)) | BC23: =IF($C23="","",SUMIF('MOVIMENTI 2026'!$B$7:$B$4206,$C23,'MOVIMENTI 2026'!$K$7:$K$4206)+SUMIF('SALDI AL 31.12.2025'!$A$6:$A$505,$C23,'SALDI AL 31.12.2025'!$E$6:$E$505)) | BD23: =IF($C23="","",SUMIF('MOVIMENTI 2026'!$B$7:$B$4206,$C23,'MOVIMENTI 2026'!$L$7:$L$4206)+SUMIF('SALDI AL 31.12.2025'!$A$6:$A$505,$C23,'SALDI AL 31.12.2025'!$F$6:$F$505)) | BE23: =IF(OR($C23="",$W23=""),"",MAX($W23-$BB23,0)) | BF23: =IF(OR($C23="",$W23=""),"",MAX($BB23-$W23,0)) | BG23: =IF(OR($C23="",$W23<=0),"",$BA23/$W23) | BH23: =IFERROR(IF(OR($C23="",ANAGRAFICA!$I20="",ANAGRAFICA!$J20="",ANAGRAFICA!$J20<=ANAGRAFICA!$I20,$Y23=""),"",IF(OR($I23="Finito ritenute non previste",$I23="Finito con sblocco ritenute",$I23="Finito senza sblocco ritenute"),1,MAX(0,MIN(1,($Y23-ANAGRAFICA!$I20)/(ANAGRAFICA!$J20-ANAGRAFICA!$I20))))),"") | BI23: =IF(OR($C23="",$BG23="",$BH23=""),"",$BG23-$BH23) | BJ23: =IFERROR(IF($C23="","",'BUDGET COMMESSA'!$D20),"") | BK23: =IF($C23="","",SUMIF('MOVIMENTI 2026'!$B$7:$B$4206,$C23,'MOVIMENTI 2026'!$N$7:$N$4206)+SUMIF('SALDI AL 31.12.2025'!$A$6:$A$505,$C23,'SALDI AL 31.12.2025'!$H$6:$H$505)) | BL23: =IF(OR($C23="",$BJ23=""),"",MAX($BJ23-$BK23,0)) | BM23: =IF(OR($C23="",$BJ23<=0),"",$BK23/$BJ23) | BN23: =IF(OR($C23="",$BM23="",$BG23=""),"",$BM23-$BG23) | BO23: =IFERROR(IF($C23="","",'BUDGET COMMESSA'!$G20),"") | BP23: =IF($C23="","",SUMIF('COSTI DIRETTI'!$C$6:$C$505,$C23,'COSTI DIRETTI'!$H$6:$H$505)+SUMIF('SALDI AL 31.12.2025'!$A$6:$A$505,$C23,'SALDI AL 31.12.2025'!$I$6:$I$505)) | BQ23: =IF(OR($C23="",$BO23=""),"",MAX($BO23-$BP23,0)) | BR23: =IF(OR($C23="",$BO23=""),"",MAX($BP23-$BO23,0)) | BS23: =IF($C23="","",$BK23*PARAMETRI!$B$4+$BP23) | BT23: =IF($A23="CRITICO",1,0) -> 0 | BU23: =IF($A23="ATTENZIONE",1,0) -> 0 | BV23: =IF($C23="","",SUMIF('MOVIMENTI 2026'!$B$7:$B$4206,$C23,'MOVIMENTI 2026'!$P$7:$P$4206)+SUMIF('SALDI AL 31.12.2025'!$A$6:$A$505,$C23,'SALDI AL 31.12.2025'!$G$6:$G$505))
A24: =IFERROR(IF($C24="","",IF(OR($BF24>0,$V24>$J24,AND(ISNUMBER($Q24),$Q24>0),AND($BI24<>"",$BI24<-PARAMETRI!$B$6),AND($BM24<>"",$BM24>=1),AND($BN24<>"",$BN24>PARAMETRI!$B$8),AND(ISNUMBER($BR24),$BR24>0)),"CRITICO",IF(OR($AZ24="",LEFT($C24,5)="TEMP",$BJ24="",$BO24="",ANAGRAFICA!$I21="",ANAGRAFICA!$J21="",$Y24="",AND(OR($I24="Finito ritenute non previste",$I24="Finito con sblocco ritenute",$I24="Finito senza sblocco ritenute"),ANAGRAFICA!$K21=""),OR(AND(ANAGRAFICA!$T21<>"",ANAGRAFICA!$J21<>ANAGRAFICA!$T21,OR(ANAGRAFICA!$R21="",ANAGRAFICA!$R21="Nessuna variazione")),AND(ANAGRAFICA!$J21="",ANAGRAFICA!$R21<>"",ANAGRAFICA!$R21<>"Nessuna variazione")),AND($BI24<>"",$BI24<-PARAMETRI!$B$5),AND($BN24<>"",$BN24>PARAMETRI!$B$7),AND($W24>0,$M24>$W24*PARAMETRI!$B$9),AND($O24>0,OR($I24="Finito ritenute non previste",$I24="Finito con sblocco ritenute",$I24="Finito senza sblocco ritenute")),AND($BA24>0,$BO24>0,$BP24=0),AND(OR($I24="Finito ritenute non previste",$I24="Finito con sblocco ritenute",$I24="Finito senza sblocco ritenute"),$W24>0,$N24>$W24*PARAMETRI!$B$9),$V24>0),"ATTENZIONE","REGOLARE"))),"ATTENZIONE") | B24: =IFERROR(IF($C24="","",IF($BF24>0,"FATTURATO OLTRE VALORE RECUPERABILE; ","")&IF($V24>$J24,"PERDITE ACCETTATE OLTRE CONTRATTO; ","")&IF($V24>0,"PERDITA SAL ACCETTATA (€ "&TEXT($V24,"#,##0.00")&"); ","")&IF(AND(ISNUMBER($Q24),$Q24>0),"RITARDO PRODUTTIVO ("&TEXT($Q24,"0")&" GG); ","")&IF(AND($BI24<>"",$BI24<-PARAMETRI!$B$5),"AVANZAMENTO PIÙ LENTO DEL TEMPO; ","")&IF(AND($BM24<>"",$BM24>1),"ORE OLTRE BUDGET; ","")&IF(AND($BM24<>"",$BM24=1),"ORE PREVENTIVATE ESAURITE; ","")&IF(AND($BN24<>"",$BN24>PARAMETRI!$B$7),"CONSUMO ORE SUPERIORE ALL'AVANZAMENTO; ","")&IF(AND(ISNUMBER($BR24),$BR24>0),"COSTI DIRETTI OLTRE BUDGET; ","")&IF(AND($W24>0,$M24>$W24*PARAMETRI!$B$9),"SAL MATURATO NON FATTURATO; ","")&IF(AND($O24>0,OR($I24="Finito ritenute non previste",$I24="Finito con sblocco ritenute",$I24="Finito senza sblocco ritenute")),"RITENUTE DA SBLOCCARE; ","")&IF(AND($BA24>0,$BO24>0,$BP24=0),"COSTI DIRETTI NON REGISTRATI; ","")&IF(AND(OR($I24="Finito ritenute non previste",$I24="Finito con sblocco ritenute",$I24="Finito senza sblocco ritenute"),$W24>0,$N24>$W24*PARAMETRI!$B$9),"CANTIERE FINITO CON RESIDUO LAVORI; ","")&IF(AND(OR($I24="Finito ritenute non previste",$I24="Finito con sblocco ritenute",$I24="Finito senza sblocco ritenute"),ANAGRAFICA!$K21=""),"DATA FINE EFFETTIVA MANCANTE; ","")&IF(OR(AND(ANAGRAFICA!$T21<>"",ANAGRAFICA!$J21<>ANAGRAFICA!$T21,OR(ANAGRAFICA!$R21="",ANAGRAFICA!$R21="Nessuna variazione")),AND(ANAGRAFICA!$J21="",ANAGRAFICA!$R21<>"",ANAGRAFICA!$R21<>"Nessuna variazione")),"GESTIONE DATA FINE INCOMPLETA; ","")&IF($Y24="","AGGIORNATO AL MANCANTE; ","")&IF(OR($AZ24="",$BJ24="",$BO24="",ANAGRAFICA!$I21="",ANAGRAFICA!$J21=""),"DATI PREVISIONALI INCOMPLETI; ","")&IF(LEFT($C24,5)="TEMP","CODICE COMMESSA TEMPORANEO; ","")),"DATI INCOMPLETI; ") | C24: =IF(ANAGRAFICA!$B21="","",ANAGRAFICA!$B21) | D24: =IF($C24="","",ANAGRAFICA!$C21) | E24: =IF($C24="","",ANAGRAFICA!$D21) | F24: =IF($C24="","",ANAGRAFICA!$E21) | G24: =IF($C24="","",ANAGRAFICA!$F21) | H24: =IF($C24="","",ANAGRAFICA!$G21) | I24: =IF($C24="","",ANAGRAFICA!$L21) | J24: =IF($C24="","",$AZ24) | K24: =IF($C24="","",$BA24) | L24: =IF($C24="","",$BB24) | M24: =IF($C24="","",MAX($BA24-$BB24,0)) | N24: =IF(OR($C24="",$W24=""),"",MAX($W24-$BA24,0)) | O24: =IF($C24="","",MAX($BC24-$BD24,0)) | P24: =IF(OR($C24="",$BG24="",$BH24="",$BI24=""),"",TEXT($BG24,"0.0%")&" / "&TEXT($BH24,"0.0%")&" / "&TEXT($BI24,"0.0%")) | Q24: =IF(OR($C24="",'BUDGET COMMESSA'!$D21="",'BUDGET COMMESSA'!$D21<=0,ANAGRAFICA!$J21=""),"",IF(OR($I24="Finito ritenute non previste",$I24="Finito con sblocco ritenute",$I24="Finito senza sblocco ritenute"),0,IF(AND($BK24>=$BJ24,ANAGRAFICA!$R21="Ritardo produttivo FIDA"),IF(ANAGRAFICA!$T21<>"",MAX(0,ANAGRAFICA!$J21-ANAGRAFICA!$T21),MAX(0,$Y24-ANAGRAFICA!$J21)),0))) | R24: =IF(OR($C24="",$BJ24=""),"",TEXT($BJ24,"#,##0.00")&" / "&TEXT($BK24,"#,##0.00")&" / "&TEXT($BL24,"#,##0.00")) | S24: =IF(OR($C24="",$BM24="",$BG24="",$BN24=""),"",TEXT($BM24,"0.0%")&" / "&TEXT($BG24,"0.0%")&" / "&TEXT($BN24,"0.0%")) | T24: =IF(OR($C24="",$BO24=""),"",IF($BR24>0,"BUDGET € "&TEXT($BO24,"#,##0.00")&" | SOSTENUTI € "&TEXT($BP24,"#,##0.00")&" | SFORAMENTO € "&TEXT($BR24,"#,##0.00"),"BUDGET € "&TEXT($BO24,"#,##0.00")&" | SOSTENUTI € "&TEXT($BP24,"#,##0.00")&" | RESIDUO € "&TEXT($BQ24,"#,##0.00"))) | U24: =IF($C24="","",$BS24) | V24: =IF($C24="","",$BV24) | W24: =IF(OR($C24="",$AZ24=""),"",MAX($AZ24-$BV24,0)) | AZ24: =IF($C24="","",ANAGRAFICA!$P21) | BA24: =IF($C24="","",SUMIF('MOVIMENTI 2026'!$B$7:$B$4206,$C24,'MOVIMENTI 2026'!$I$7:$I$4206)+SUMIF('SALDI AL 31.12.2025'!$A$6:$A$505,$C24,'SALDI AL 31.12.2025'!$C$6:$C$505)) | BB24: =IF($C24="","",SUMIF('MOVIMENTI 2026'!$B$7:$B$4206,$C24,'MOVIMENTI 2026'!$J$7:$J$4206)+SUMIF('SALDI AL 31.12.2025'!$A$6:$A$505,$C24,'SALDI AL 31.12.2025'!$D$6:$D$505)) | BC24: =IF($C24="","",SUMIF('MOVIMENTI 2026'!$B$7:$B$4206,$C24,'MOVIMENTI 2026'!$K$7:$K$4206)+SUMIF('SALDI AL 31.12.2025'!$A$6:$A$505,$C24,'SALDI AL 31.12.2025'!$E$6:$E$505)) | BD24: =IF($C24="","",SUMIF('MOVIMENTI 2026'!$B$7:$B$4206,$C24,'MOVIMENTI 2026'!$L$7:$L$4206)+SUMIF('SALDI AL 31.12.2025'!$A$6:$A$505,$C24,'SALDI AL 31.12.2025'!$F$6:$F$505)) | BE24: =IF(OR($C24="",$W24=""),"",MAX($W24-$BB24,0)) | BF24: =IF(OR($C24="",$W24=""),"",MAX($BB24-$W24,0)) | BG24: =IF(OR($C24="",$W24<=0),"",$BA24/$W24) | BH24: =IFERROR(IF(OR($C24="",ANAGRAFICA!$I21="",ANAGRAFICA!$J21="",ANAGRAFICA!$J21<=ANAGRAFICA!$I21,$Y24=""),"",IF(OR($I24="Finito ritenute non previste",$I24="Finito con sblocco ritenute",$I24="Finito senza sblocco ritenute"),1,MAX(0,MIN(1,($Y24-ANAGRAFICA!$I21)/(ANAGRAFICA!$J21-ANAGRAFICA!$I21))))),"") | BI24: =IF(OR($C24="",$BG24="",$BH24=""),"",$BG24-$BH24) | BJ24: =IFERROR(IF($C24="","",'BUDGET COMMESSA'!$D21),"") | BK24: =IF($C24="","",SUMIF('MOVIMENTI 2026'!$B$7:$B$4206,$C24,'MOVIMENTI 2026'!$N$7:$N$4206)+SUMIF('SALDI AL 31.12.2025'!$A$6:$A$505,$C24,'SALDI AL 31.12.2025'!$H$6:$H$505)) | BL24: =IF(OR($C24="",$BJ24=""),"",MAX($BJ24-$BK24,0)) | BM24: =IF(OR($C24="",$BJ24<=0),"",$BK24/$BJ24) | BN24: =IF(OR($C24="",$BM24="",$BG24=""),"",$BM24-$BG24) | BO24: =IFERROR(IF($C24="","",'BUDGET COMMESSA'!$G21),"") | BP24: =IF($C24="","",SUMIF('COSTI DIRETTI'!$C$6:$C$505,$C24,'COSTI DIRETTI'!$H$6:$H$505)+SUMIF('SALDI AL 31.12.2025'!$A$6:$A$505,$C24,'SALDI AL 31.12.2025'!$I$6:$I$505)) | BQ24: =IF(OR($C24="",$BO24=""),"",MAX($BO24-$BP24,0)) | BR24: =IF(OR($C24="",$BO24=""),"",MAX($BP24-$BO24,0)) | BS24: =IF($C24="","",$BK24*PARAMETRI!$B$4+$BP24) | BT24: =IF($A24="CRITICO",1,0) -> 0 | BU24: =IF($A24="ATTENZIONE",1,0) -> 0 | BV24: =IF($C24="","",SUMIF('MOVIMENTI 2026'!$B$7:$B$4206,$C24,'MOVIMENTI 2026'!$P$7:$P$4206)+SUMIF('SALDI AL 31.12.2025'!$A$6:$A$505,$C24,'SALDI AL 31.12.2025'!$G$6:$G$505))
A25: =IFERROR(IF($C25="","",IF(OR($BF25>0,$V25>$J25,AND(ISNUMBER($Q25),$Q25>0),AND($BI25<>"",$BI25<-PARAMETRI!$B$6),AND($BM25<>"",$BM25>=1),AND($BN25<>"",$BN25>PARAMETRI!$B$8),AND(ISNUMBER($BR25),$BR25>0)),"CRITICO",IF(OR($AZ25="",LEFT($C25,5)="TEMP",$BJ25="",$BO25="",ANAGRAFICA!$I22="",ANAGRAFICA!$J22="",$Y25="",AND(OR($I25="Finito ritenute non previste",$I25="Finito con sblocco ritenute",$I25="Finito senza sblocco ritenute"),ANAGRAFICA!$K22=""),OR(AND(ANAGRAFICA!$T22<>"",ANAGRAFICA!$J22<>ANAGRAFICA!$T22,OR(ANAGRAFICA!$R22="",ANAGRAFICA!$R22="Nessuna variazione")),AND(ANAGRAFICA!$J22="",ANAGRAFICA!$R22<>"",ANAGRAFICA!$R22<>"Nessuna variazione")),AND($BI25<>"",$BI25<-PARAMETRI!$B$5),AND($BN25<>"",$BN25>PARAMETRI!$B$7),AND($W25>0,$M25>$W25*PARAMETRI!$B$9),AND($O25>0,OR($I25="Finito ritenute non previste",$I25="Finito con sblocco ritenute",$I25="Finito senza sblocco ritenute")),AND($BA25>0,$BO25>0,$BP25=0),AND(OR($I25="Finito ritenute non previste",$I25="Finito con sblocco ritenute",$I25="Finito senza sblocco ritenute"),$W25>0,$N25>$W25*PARAMETRI!$B$9),$V25>0),"ATTENZIONE","REGOLARE"))),"ATTENZIONE") | B25: =IFERROR(IF($C25="","",IF($BF25>0,"FATTURATO OLTRE VALORE RECUPERABILE; ","")&IF($V25>$J25,"PERDITE ACCETTATE OLTRE CONTRATTO; ","")&IF($V25>0,"PERDITA SAL ACCETTATA (€ "&TEXT($V25,"#,##0.00")&"); ","")&IF(AND(ISNUMBER($Q25),$Q25>0),"RITARDO PRODUTTIVO ("&TEXT($Q25,"0")&" GG); ","")&IF(AND($BI25<>"",$BI25<-PARAMETRI!$B$5),"AVANZAMENTO PIÙ LENTO DEL TEMPO; ","")&IF(AND($BM25<>"",$BM25>1),"ORE OLTRE BUDGET; ","")&IF(AND($BM25<>"",$BM25=1),"ORE PREVENTIVATE ESAURITE; ","")&IF(AND($BN25<>"",$BN25>PARAMETRI!$B$7),"CONSUMO ORE SUPERIORE ALL'AVANZAMENTO; ","")&IF(AND(ISNUMBER($BR25),$BR25>0),"COSTI DIRETTI OLTRE BUDGET; ","")&IF(AND($W25>0,$M25>$W25*PARAMETRI!$B$9),"SAL MATURATO NON FATTURATO; ","")&IF(AND($O25>0,OR($I25="Finito ritenute non previste",$I25="Finito con sblocco ritenute",$I25="Finito senza sblocco ritenute")),"RITENUTE DA SBLOCCARE; ","")&IF(AND($BA25>0,$BO25>0,$BP25=0),"COSTI DIRETTI NON REGISTRATI; ","")&IF(AND(OR($I25="Finito ritenute non previste",$I25="Finito con sblocco ritenute",$I25="Finito senza sblocco ritenute"),$W25>0,$N25>$W25*PARAMETRI!$B$9),"CANTIERE FINITO CON RESIDUO LAVORI; ","")&IF(AND(OR($I25="Finito ritenute non previste",$I25="Finito con sblocco ritenute",$I25="Finito senza sblocco ritenute"),ANAGRAFICA!$K22=""),"DATA FINE EFFETTIVA MANCANTE; ","")&IF(OR(AND(ANAGRAFICA!$T22<>"",ANAGRAFICA!$J22<>ANAGRAFICA!$T22,OR(ANAGRAFICA!$R22="",ANAGRAFICA!$R22="Nessuna variazione")),AND(ANAGRAFICA!$J22="",ANAGRAFICA!$R22<>"",ANAGRAFICA!$R22<>"Nessuna variazione")),"GESTIONE DATA FINE INCOMPLETA; ","")&IF($Y25="","AGGIORNATO AL MANCANTE; ","")&IF(OR($AZ25="",$BJ25="",$BO25="",ANAGRAFICA!$I22="",ANAGRAFICA!$J22=""),"DATI PREVISIONALI INCOMPLETI; ","")&IF(LEFT($C25,5)="TEMP","CODICE COMMESSA TEMPORANEO; ","")),"DATI INCOMPLETI; ") | C25: =IF(ANAGRAFICA!$B22="","",ANAGRAFICA!$B22) | D25: =IF($C25="","",ANAGRAFICA!$C22) | E25: =IF($C25="","",ANAGRAFICA!$D22) | F25: =IF($C25="","",ANAGRAFICA!$E22) | G25: =IF($C25="","",ANAGRAFICA!$F22) | H25: =IF($C25="","",ANAGRAFICA!$G22) | I25: =IF($C25="","",ANAGRAFICA!$L22) | J25: =IF($C25="","",$AZ25) | K25: =IF($C25="","",$BA25) | L25: =IF($C25="","",$BB25) | M25: =IF($C25="","",MAX($BA25-$BB25,0)) | N25: =IF(OR($C25="",$W25=""),"",MAX($W25-$BA25,0)) | O25: =IF($C25="","",MAX($BC25-$BD25,0)) | P25: =IF(OR($C25="",$BG25="",$BH25="",$BI25=""),"",TEXT($BG25,"0.0%")&" / "&TEXT($BH25,"0.0%")&" / "&TEXT($BI25,"0.0%")) | Q25: =IF(OR($C25="",'BUDGET COMMESSA'!$D22="",'BUDGET COMMESSA'!$D22<=0,ANAGRAFICA!$J22=""),"",IF(OR($I25="Finito ritenute non previste",$I25="Finito con sblocco ritenute",$I25="Finito senza sblocco ritenute"),0,IF(AND($BK25>=$BJ25,ANAGRAFICA!$R22="Ritardo produttivo FIDA"),IF(ANAGRAFICA!$T22<>"",MAX(0,ANAGRAFICA!$J22-ANAGRAFICA!$T22),MAX(0,$Y25-ANAGRAFICA!$J22)),0))) | R25: =IF(OR($C25="",$BJ25=""),"",TEXT($BJ25,"#,##0.00")&" / "&TEXT($BK25,"#,##0.00")&" / "&TEXT($BL25,"#,##0.00")) | S25: =IF(OR($C25="",$BM25="",$BG25="",$BN25=""),"",TEXT($BM25,"0.0%")&" / "&TEXT($BG25,"0.0%")&" / "&TEXT($BN25,"0.0%")) | T25: =IF(OR($C25="",$BO25=""),"",IF($BR25>0,"BUDGET € "&TEXT($BO25,"#,##0.00")&" | SOSTENUTI € "&TEXT($BP25,"#,##0.00")&" | SFORAMENTO € "&TEXT($BR25,"#,##0.00"),"BUDGET € "&TEXT($BO25,"#,##0.00")&" | SOSTENUTI € "&TEXT($BP25,"#,##0.00")&" | RESIDUO € "&TEXT($BQ25,"#,##0.00"))) | U25: =IF($C25="","",$BS25) | V25: =IF($C25="","",$BV25) | W25: =IF(OR($C25="",$AZ25=""),"",MAX($AZ25-$BV25,0)) | AZ25: =IF($C25="","",ANAGRAFICA!$P22) | BA25: =IF($C25="","",SUMIF('MOVIMENTI 2026'!$B$7:$B$4206,$C25,'MOVIMENTI 2026'!$I$7:$I$4206)+SUMIF('SALDI AL 31.12.2025'!$A$6:$A$505,$C25,'SALDI AL 31.12.2025'!$C$6:$C$505)) | BB25: =IF($C25="","",SUMIF('MOVIMENTI 2026'!$B$7:$B$4206,$C25,'MOVIMENTI 2026'!$J$7:$J$4206)+SUMIF('SALDI AL 31.12.2025'!$A$6:$A$505,$C25,'SALDI AL 31.12.2025'!$D$6:$D$505)) | BC25: =IF($C25="","",SUMIF('MOVIMENTI 2026'!$B$7:$B$4206,$C25,'MOVIMENTI 2026'!$K$7:$K$4206)+SUMIF('SALDI AL 31.12.2025'!$A$6:$A$505,$C25,'SALDI AL 31.12.2025'!$E$6:$E$505)) | BD25: =IF($C25="","",SUMIF('MOVIMENTI 2026'!$B$7:$B$4206,$C25,'MOVIMENTI 2026'!$L$7:$L$4206)+SUMIF('SALDI AL 31.12.2025'!$A$6:$A$505,$C25,'SALDI AL 31.12.2025'!$F$6:$F$505)) | BE25: =IF(OR($C25="",$W25=""),"",MAX($W25-$BB25,0)) | BF25: =IF(OR($C25="",$W25=""),"",MAX($BB25-$W25,0)) | BG25: =IF(OR($C25="",$W25<=0),"",$BA25/$W25) | BH25: =IFERROR(IF(OR($C25="",ANAGRAFICA!$I22="",ANAGRAFICA!$J22="",ANAGRAFICA!$J22<=ANAGRAFICA!$I22,$Y25=""),"",IF(OR($I25="Finito ritenute non previste",$I25="Finito con sblocco ritenute",$I25="Finito senza sblocco ritenute"),1,MAX(0,MIN(1,($Y25-ANAGRAFICA!$I22)/(ANAGRAFICA!$J22-ANAGRAFICA!$I22))))),"") | BI25: =IF(OR($C25="",$BG25="",$BH25=""),"",$BG25-$BH25) | BJ25: =IFERROR(IF($C25="","",'BUDGET COMMESSA'!$D22),"") | BK25: =IF($C25="","",SUMIF('MOVIMENTI 2026'!$B$7:$B$4206,$C25,'MOVIMENTI 2026'!$N$7:$N$4206)+SUMIF('SALDI AL 31.12.2025'!$A$6:$A$505,$C25,'SALDI AL 31.12.2025'!$H$6:$H$505)) | BL25: =IF(OR($C25="",$BJ25=""),"",MAX($BJ25-$BK25,0)) | BM25: =IF(OR($C25="",$BJ25<=0),"",$BK25/$BJ25) | BN25: =IF(OR($C25="",$BM25="",$BG25=""),"",$BM25-$BG25) | BO25: =IFERROR(IF($C25="","",'BUDGET COMMESSA'!$G22),"") | BP25: =IF($C25="","",SUMIF('COSTI DIRETTI'!$C$6:$C$505,$C25,'COSTI DIRETTI'!$H$6:$H$505)+SUMIF('SALDI AL 31.12.2025'!$A$6:$A$505,$C25,'SALDI AL 31.12.2025'!$I$6:$I$505)) | BQ25: =IF(OR($C25="",$BO25=""),"",MAX($BO25-$BP25,0)) | BR25: =IF(OR($C25="",$BO25=""),"",MAX($BP25-$BO25,0)) | BS25: =IF($C25="","",$BK25*PARAMETRI!$B$4+$BP25) | BT25: =IF($A25="CRITICO",1,0) -> 0 | BU25: =IF($A25="ATTENZIONE",1,0) -> 0 | BV25: =IF($C25="","",SUMIF('MOVIMENTI 2026'!$B$7:$B$4206,$C25,'MOVIMENTI 2026'!$P$7:$P$4206)+SUMIF('SALDI AL 31.12.2025'!$A$6:$A$505,$C25,'SALDI AL 31.12.2025'!$G$6:$G$505))
A26: =IFERROR(IF($C26="","",IF(OR($BF26>0,$V26>$J26,AND(ISNUMBER($Q26),$Q26>0),AND($BI26<>"",$BI26<-PARAMETRI!$B$6),AND($BM26<>"",$BM26>=1),AND($BN26<>"",$BN26>PARAMETRI!$B$8),AND(ISNUMBER($BR26),$BR26>0)),"CRITICO",IF(OR($AZ26="",LEFT($C26,5)="TEMP",$BJ26="",$BO26="",ANAGRAFICA!$I23="",ANAGRAFICA!$J23="",$Y26="",AND(OR($I26="Finito ritenute non previste",$I26="Finito con sblocco ritenute",$I26="Finito senza sblocco ritenute"),ANAGRAFICA!$K23=""),OR(AND(ANAGRAFICA!$T23<>"",ANAGRAFICA!$J23<>ANAGRAFICA!$T23,OR(ANAGRAFICA!$R23="",ANAGRAFICA!$R23="Nessuna variazione")),AND(ANAGRAFICA!$J23="",ANAGRAFICA!$R23<>"",ANAGRAFICA!$R23<>"Nessuna variazione")),AND($BI26<>"",$BI26<-PARAMETRI!$B$5),AND($BN26<>"",$BN26>PARAMETRI!$B$7),AND($W26>0,$M26>$W26*PARAMETRI!$B$9),AND($O26>0,OR($I26="Finito ritenute non previste",$I26="Finito con sblocco ritenute",$I26="Finito senza sblocco ritenute")),AND($BA26>0,$BO26>0,$BP26=0),AND(OR($I26="Finito ritenute non previste",$I26="Finito con sblocco ritenute",$I26="Finito senza sblocco ritenute"),$W26>0,$N26>$W26*PARAMETRI!$B$9),$V26>0),"ATTENZIONE","REGOLARE"))),"ATTENZIONE") | B26: =IFERROR(IF($C26="","",IF($BF26>0,"FATTURATO OLTRE VALORE RECUPERABILE; ","")&IF($V26>$J26,"PERDITE ACCETTATE OLTRE CONTRATTO; ","")&IF($V26>0,"PERDITA SAL ACCETTATA (€ "&TEXT($V26,"#,##0.00")&"); ","")&IF(AND(ISNUMBER($Q26),$Q26>0),"RITARDO PRODUTTIVO ("&TEXT($Q26,"0")&" GG); ","")&IF(AND($BI26<>"",$BI26<-PARAMETRI!$B$5),"AVANZAMENTO PIÙ LENTO DEL TEMPO; ","")&IF(AND($BM26<>"",$BM26>1),"ORE OLTRE BUDGET; ","")&IF(AND($BM26<>"",$BM26=1),"ORE PREVENTIVATE ESAURITE; ","")&IF(AND($BN26<>"",$BN26>PARAMETRI!$B$7),"CONSUMO ORE SUPERIORE ALL'AVANZAMENTO; ","")&IF(AND(ISNUMBER($BR26),$BR26>0),"COSTI DIRETTI OLTRE BUDGET; ","")&IF(AND($W26>0,$M26>$W26*PARAMETRI!$B$9),"SAL MATURATO NON FATTURATO; ","")&IF(AND($O26>0,OR($I26="Finito ritenute non previste",$I26="Finito con sblocco ritenute",$I26="Finito senza sblocco ritenute")),"RITENUTE DA SBLOCCARE; ","")&IF(AND($BA26>0,$BO26>0,$BP26=0),"COSTI DIRETTI NON REGISTRATI; ","")&IF(AND(OR($I26="Finito ritenute non previste",$I26="Finito con sblocco ritenute",$I26="Finito senza sblocco ritenute"),$W26>0,$N26>$W26*PARAMETRI!$B$9),"CANTIERE FINITO CON RESIDUO LAVORI; ","")&IF(AND(OR($I26="Finito ritenute non previste",$I26="Finito con sblocco ritenute",$I26="Finito senza sblocco ritenute"),ANAGRAFICA!$K23=""),"DATA FINE EFFETTIVA MANCANTE; ","")&IF(OR(AND(ANAGRAFICA!$T23<>"",ANAGRAFICA!$J23<>ANAGRAFICA!$T23,OR(ANAGRAFICA!$R23="",ANAGRAFICA!$R23="Nessuna variazione")),AND(ANAGRAFICA!$J23="",ANAGRAFICA!$R23<>"",ANAGRAFICA!$R23<>"Nessuna variazione")),"GESTIONE DATA FINE INCOMPLETA; ","")&IF($Y26="","AGGIORNATO AL MANCANTE; ","")&IF(OR($AZ26="",$BJ26="",$BO26="",ANAGRAFICA!$I23="",ANAGRAFICA!$J23=""),"DATI PREVISIONALI INCOMPLETI; ","")&IF(LEFT($C26,5)="TEMP","CODICE COMMESSA TEMPORANEO; ","")),"DATI INCOMPLETI; ") | C26: =IF(ANAGRAFICA!$B23="","",ANAGRAFICA!$B23) | D26: =IF($C26="","",ANAGRAFICA!$C23) | E26: =IF($C26="","",ANAGRAFICA!$D23) | F26: =IF($C26="","",ANAGRAFICA!$E23) | G26: =IF($C26="","",ANAGRAFICA!$F23) | H26: =IF($C26="","",ANAGRAFICA!$G23) | I26: =IF($C26="","",ANAGRAFICA!$L23) | J26: =IF($C26="","",$AZ26) | K26: =IF($C26="","",$BA26) | L26: =IF($C26="","",$BB26) | M26: =IF($C26="","",MAX($BA26-$BB26,0)) | N26: =IF(OR($C26="",$W26=""),"",MAX($W26-$BA26,0)) | O26: =IF($C26="","",MAX($BC26-$BD26,0)) | P26: =IF(OR($C26="",$BG26="",$BH26="",$BI26=""),"",TEXT($BG26,"0.0%")&" / "&TEXT($BH26,"0.0%")&" / "&TEXT($BI26,"0.0%")) | Q26: =IF(OR($C26="",'BUDGET COMMESSA'!$D23="",'BUDGET COMMESSA'!$D23<=0,ANAGRAFICA!$J23=""),"",IF(OR($I26="Finito ritenute non previste",$I26="Finito con sblocco ritenute",$I26="Finito senza sblocco ritenute"),0,IF(AND($BK26>=$BJ26,ANAGRAFICA!$R23="Ritardo produttivo FIDA"),IF(ANAGRAFICA!$T23<>"",MAX(0,ANAGRAFICA!$J23-ANAGRAFICA!$T23),MAX(0,$Y26-ANAGRAFICA!$J23)),0))) | R26: =IF(OR($C26="",$BJ26=""),"",TEXT($BJ26,"#,##0.00")&" / "&TEXT($BK26,"#,##0.00")&" / "&TEXT($BL26,"#,##0.00")) | S26: =IF(OR($C26="",$BM26="",$BG26="",$BN26=""),"",TEXT($BM26,"0.0%")&" / "&TEXT($BG26,"0.0%")&" / "&TEXT($BN26,"0.0%")) | T26: =IF(OR($C26="",$BO26=""),"",IF($BR26>0,"BUDGET € "&TEXT($BO26,"#,##0.00")&" | SOSTENUTI € "&TEXT($BP26,"#,##0.00")&" | SFORAMENTO € "&TEXT($BR26,"#,##0.00"),"BUDGET € "&TEXT($BO26,"#,##0.00")&" | SOSTENUTI € "&TEXT($BP26,"#,##0.00")&" | RESIDUO € "&TEXT($BQ26,"#,##0.00"))) | U26: =IF($C26="","",$BS26) | V26: =IF($C26="","",$BV26) | W26: =IF(OR($C26="",$AZ26=""),"",MAX($AZ26-$BV26,0)) | AZ26: =IF($C26="","",ANAGRAFICA!$P23) | BA26: =IF($C26="","",SUMIF('MOVIMENTI 2026'!$B$7:$B$4206,$C26,'MOVIMENTI 2026'!$I$7:$I$4206)+SUMIF('SALDI AL 31.12.2025'!$A$6:$A$505,$C26,'SALDI AL 31.12.2025'!$C$6:$C$505)) | BB26: =IF($C26="","",SUMIF('MOVIMENTI 2026'!$B$7:$B$4206,$C26,'MOVIMENTI 2026'!$J$7:$J$4206)+SUMIF('SALDI AL 31.12.2025'!$A$6:$A$505,$C26,'SALDI AL 31.12.2025'!$D$6:$D$505)) | BC26: =IF($C26="","",SUMIF('MOVIMENTI 2026'!$B$7:$B$4206,$C26,'MOVIMENTI 2026'!$K$7:$K$4206)+SUMIF('SALDI AL 31.12.2025'!$A$6:$A$505,$C26,'SALDI AL 31.12.2025'!$E$6:$E$505)) | BD26: =IF($C26="","",SUMIF('MOVIMENTI 2026'!$B$7:$B$4206,$C26,'MOVIMENTI 2026'!$L$7:$L$4206)+SUMIF('SALDI AL 31.12.2025'!$A$6:$A$505,$C26,'SALDI AL 31.12.2025'!$F$6:$F$505)) | BE26: =IF(OR($C26="",$W26=""),"",MAX($W26-$BB26,0)) | BF26: =IF(OR($C26="",$W26=""),"",MAX($BB26-$W26,0)) | BG26: =IF(OR($C26="",$W26<=0),"",$BA26/$W26) | BH26: =IFERROR(IF(OR($C26="",ANAGRAFICA!$I23="",ANAGRAFICA!$J23="",ANAGRAFICA!$J23<=ANAGRAFICA!$I23,$Y26=""),"",IF(OR($I26="Finito ritenute non previste",$I26="Finito con sblocco ritenute",$I26="Finito senza sblocco ritenute"),1,MAX(0,MIN(1,($Y26-ANAGRAFICA!$I23)/(ANAGRAFICA!$J23-ANAGRAFICA!$I23))))),"") | BI26: =IF(OR($C26="",$BG26="",$BH26=""),"",$BG26-$BH26) | BJ26: =IFERROR(IF($C26="","",'BUDGET COMMESSA'!$D23),"") | BK26: =IF($C26="","",SUMIF('MOVIMENTI 2026'!$B$7:$B$4206,$C26,'MOVIMENTI 2026'!$N$7:$N$4206)+SUMIF('SALDI AL 31.12.2025'!$A$6:$A$505,$C26,'SALDI AL 31.12.2025'!$H$6:$H$505)) | BL26: =IF(OR($C26="",$BJ26=""),"",MAX($BJ26-$BK26,0)) | BM26: =IF(OR($C26="",$BJ26<=0),"",$BK26/$BJ26) | BN26: =IF(OR($C26="",$BM26="",$BG26=""),"",$BM26-$BG26) | BO26: =IFERROR(IF($C26="","",'BUDGET COMMESSA'!$G23),"") | BP26: =IF($C26="","",SUMIF('COSTI DIRETTI'!$C$6:$C$505,$C26,'COSTI DIRETTI'!$H$6:$H$505)+SUMIF('SALDI AL 31.12.2025'!$A$6:$A$505,$C26,'SALDI AL 31.12.2025'!$I$6:$I$505)) | BQ26: =IF(OR($C26="",$BO26=""),"",MAX($BO26-$BP26,0)) | BR26: =IF(OR($C26="",$BO26=""),"",MAX($BP26-$BO26,0)) | BS26: =IF($C26="","",$BK26*PARAMETRI!$B$4+$BP26) | BT26: =IF($A26="CRITICO",1,0) -> 0 | BU26: =IF($A26="ATTENZIONE",1,0) -> 0 | BV26: =IF($C26="","",SUMIF('MOVIMENTI 2026'!$B$7:$B$4206,$C26,'MOVIMENTI 2026'!$P$7:$P$4206)+SUMIF('SALDI AL 31.12.2025'!$A$6:$A$505,$C26,'SALDI AL 31.12.2025'!$G$6:$G$505))
... A308: =IFERROR(IF($C308="","",IF(OR($BF308>0,$V308>$J308,AND(ISNUMBER($Q308),$Q308>0),AND($BI308<>"",$BI308<-PARAMETRI!$B$6),AND($BM308<>"",$BM308>=1),AND($BN308<>"",$BN308>PARAMETRI!$B$8),AND(ISNUMBER($BR308),$BR308>0)),"CRITICO",IF(OR($AZ308="",LEFT($C308,5)="TEMP",$BJ308="",$BO308="",ANAGRAFICA!$I305="",ANAGRAFICA!$J305="",$Y308="",AND(OR($I308="Finito ritenute non previste",$I308="Finito con sblocco ritenute",$I308="Finito senza sblocco ritenute"),ANAGRAFICA!$K305=""),OR(AND(ANAGRAFICA!$T305<>"",ANAGRAFICA!$J305<>ANAGRAFICA!$T305,OR(ANAGRAFICA!$R305="",ANAGRAFICA!$R305="Nessuna variazione")),AND(ANAGRAFICA!$J305="",ANAGRAFICA!$R305<>"",ANAGRAFICA!$R305<>"Nessuna variazione")),AND($BI308<>"",$BI308<-PARAMETRI!$B$5),AND($BN308<>"",$BN308>PARAMETRI!$B$7),AND($W308>0,$M308>$W308*PARAMETRI!$B$9),AND($O308>0,OR($I308="Finito ritenute non previste",$I308="Finito con sblocco ritenute",$I308="Finito senza sblocco ritenute")),AND($BA308>0,$BO308>0,$BP308=0),AND(OR($I308="Finito ritenute non previste",$I308="Finito con sblocco ritenute",$I308="Finito senza sblocco ritenute"),$W308>0,$N308>$W308*PARAMETRI!$B$9),$V308>0),"ATTENZIONE","REGOLARE"))),"ATTENZIONE") | B308: =IFERROR(IF($C308="","",IF($BF308>0,"FATTURATO OLTRE VALORE RECUPERABILE; ","")&IF($V308>$J308,"PERDITE ACCETTATE OLTRE CONTRATTO; ","")&IF($V308>0,"PERDITA SAL ACCETTATA (€ "&TEXT($V308,"#,##0.00")&"); ","")&IF(AND(ISNUMBER($Q308),$Q308>0),"RITARDO PRODUTTIVO ("&TEXT($Q308,"0")&" GG); ","")&IF(AND($BI308<>"",$BI308<-PARAMETRI!$B$5),"AVANZAMENTO PIÙ LENTO DEL TEMPO; ","")&IF(AND($BM308<>"",$BM308>1),"ORE OLTRE BUDGET; ","")&IF(AND($BM308<>"",$BM308=1),"ORE PREVENTIVATE ESAURITE; ","")&IF(AND($BN308<>"",$BN308>PARAMETRI!$B$7),"CONSUMO ORE SUPERIORE ALL'AVANZAMENTO; ","")&IF(AND(ISNUMBER($BR308),$BR308>0),"COSTI DIRETTI OLTRE BUDGET; ","")&IF(AND($W308>0,$M308>$W308*PARAMETRI!$B$9),"SAL MATURATO NON FATTURATO; ","")&IF(AND($O308>0,OR($I308="Finito ritenute non previste",$I308="Finito con sblocco ritenute",$I308="Finito senza sblocco ritenute")),"RITENUTE DA SBLOCCARE; ","")&IF(AND($BA308>0,$BO308>0,$BP308=0),"COSTI DIRETTI NON REGISTRATI; ","")&IF(AND(OR($I308="Finito ritenute non previste",$I308="Finito con sblocco ritenute",$I308="Finito senza sblocco ritenute"),$W308>0,$N308>$W308*PARAMETRI!$B$9),"CANTIERE FINITO CON RESIDUO LAVORI; ","")&IF(AND(OR($I308="Finito ritenute non previste",$I308="Finito con sblocco ritenute",$I308="Finito senza sblocco ritenute"),ANAGRAFICA!$K305=""),"DATA FINE EFFETTIVA MANCANTE; ","")&IF(OR(AND(ANAGRAFICA!$T305<>"",ANAGRAFICA!$J305<>ANAGRAFICA!$T305,OR(ANAGRAFICA!$R305="",ANAGRAFICA!$R305="Nessuna variazione")),AND(ANAGRAFICA!$J305="",ANAGRAFICA!$R305<>"",ANAGRAFICA!$R305<>"Nessuna variazione")),"GESTIONE DATA FINE INCOMPLETA; ","")&IF($Y308="","AGGIORNATO AL MANCANTE; ","")&IF(OR($AZ308="",$BJ308="",$BO308="",ANAGRAFICA!$I305="",ANAGRAFICA!$J305=""),"DATI PREVISIONALI INCOMPLETI; ","")&IF(LEFT($C308,5)="TEMP","CODICE COMMESSA TEMPORANEO; ","")),"DATI INCOMPLETI; ") | C308: =IF(ANAGRAFICA!$B305="","",ANAGRAFICA!$B305) | D308: =IF($C308="","",ANAGRAFICA!$C305) | E308: =IF($C308="","",ANAGRAFICA!$D305) | F308: =IF($C308="","",ANAGRAFICA!$E305) | G308: =IF($C308="","",ANAGRAFICA!$F305) | H308: =IF($C308="","",ANAGRAFICA!$G305) | I308: =IF($C308="","",ANAGRAFICA!$L305) | J308: =IF($C308="","",$AZ308) | K308: =IF($C308="","",$BA308) | L308: =IF($C308="","",$BB308) | M308: =IF($C308="","",MAX($BA308-$BB308,0)) | N308: =IF(OR($C308="",$W308=""),"",MAX($W308-$BA308,0)) | O308: =IF($C308="","",MAX($BC308-$BD308,0)) | P308: =IF(OR($C308="",$BG308="",$BH308="",$BI308=""),"",TEXT($BG308,"0.0%")&" / "&TEXT($BH308,"0.0%")&" / "&TEXT($BI308,"0.0%")) | Q308: =IF(OR($C308="",'BUDGET COMMESSA'!$D305="",'BUDGET COMMESSA'!$D305<=0,ANAGRAFICA!$J305=""),"",IF(OR($I308="Finito ritenute non previste",$I308="Finito con sblocco ritenute",$I308="Finito senza sblocco ritenute"),0,IF(AND($BK308>=$BJ308,ANAGRAFICA!$R305="Ritardo produttivo FIDA"),IF(ANAGRAFICA!$T305<>"",MAX(0,ANAGRAFICA!$J305-ANAGRAFICA!$T305),MAX(0,$Y308-ANAGRAFICA!$J305)),0))) | R308: =IF(OR($C308="",$BJ308=""),"",TEXT($BJ308,"#,##0.00")&" / "&TEXT($BK308,"#,##0.00")&" / "&TEXT($BL308,"#,##0.00")) | S308: =IF(OR($C308="",$BM308="",$BG308="",$BN308=""),"",TEXT($BM308,"0.0%")&" / "&TEXT($BG308,"0.0%")&" / "&TEXT($BN308,"0.0%")) | T308: =IF(OR($C308="",$BO308=""),"",IF($BR308>0,"BUDGET € "&TEXT($BO308,"#,##0.00")&" | SOSTENUTI € "&TEXT($BP308,"#,##0.00")&" | SFORAMENTO € "&TEXT($BR308,"#,##0.00"),"BUDGET € "&TEXT($BO308,"#,##0.00")&" | SOSTENUTI € "&TEXT($BP308,"#,##0.00")&" | RESIDUO € "&TEXT($BQ308,"#,##0.00"))) | U308: =IF($C308="","",$BS308) | V308: =IF($C308="","",$BV308) | W308: =IF(OR($C308="",$AZ308=""),"",MAX($AZ308-$BV308,0)) | AZ308: =IF($C308="","",ANAGRAFICA!$P305) | BA308: =IF($C308="","",SUMIF('MOVIMENTI 2026'!$B$7:$B$4206,$C308,'MOVIMENTI 2026'!$I$7:$I$4206)+SUMIF('SALDI AL 31.12.2025'!$A$6:$A$505,$C308,'SALDI AL 31.12.2025'!$C$6:$C$505)) | BB308: =IF($C308="","",SUMIF('MOVIMENTI 2026'!$B$7:$B$4206,$C308,'MOVIMENTI 2026'!$J$7:$J$4206)+SUMIF('SALDI AL 31.12.2025'!$A$6:$A$505,$C308,'SALDI AL 31.12.2025'!$D$6:$D$505)) | BC308: =IF($C308="","",SUMIF('MOVIMENTI 2026'!$B$7:$B$4206,$C308,'MOVIMENTI 2026'!$K$7:$K$4206)+SUMIF('SALDI AL 31.12.2025'!$A$6:$A$505,$C308,'SALDI AL 31.12.2025'!$E$6:$E$505)) | BD308: =IF($C308="","",SUMIF('MOVIMENTI 2026'!$B$7:$B$4206,$C308,'MOVIMENTI 2026'!$L$7:$L$4206)+SUMIF('SALDI AL 31.12.2025'!$A$6:$A$505,$C308,'SALDI AL 31.12.2025'!$F$6:$F$505)) | BE308: =IF(OR($C308="",$W308=""),"",MAX($W308-$BB308,0)) | BF308: =IF(OR($C308="",$W308=""),"",MAX($BB308-$W308,0)) | BG308: =IF(OR($C308="",$W308<=0),"",$BA308/$W308) | BH308: =IFERROR(IF(OR($C308="",ANAGRAFICA!$I305="",ANAGRAFICA!$J305="",ANAGRAFICA!$J305<=ANAGRAFICA!$I305,$Y308=""),"",IF(OR($I308="Finito ritenute non previste",$I308="Finito con sblocco ritenute",$I308="Finito senza sblocco ritenute"),1,MAX(0,MIN(1,($Y308-ANAGRAFICA!$I305)/(ANAGRAFICA!$J305-ANAGRAFICA!$I305))))),"") | BI308: =IF(OR($C308="",$BG308="",$BH308=""),"",$BG308-$BH308) | BJ308: =IFERROR(IF($C308="","",'BUDGET COMMESSA'!$D305),"") | BK308: =IF($C308="","",SUMIF('MOVIMENTI 2026'!$B$7:$B$4206,$C308,'MOVIMENTI 2026'!$N$7:$N$4206)+SUMIF('SALDI AL 31.12.2025'!$A$6:$A$505,$C308,'SALDI AL 31.12.2025'!$H$6:$H$505)) | BL308: =IF(OR($C308="",$BJ308=""),"",MAX($BJ308-$BK308,0)) | BM308: =IF(OR($C308="",$BJ308<=0),"",$BK308/$BJ308) | BN308: =IF(OR($C308="",$BM308="",$BG308=""),"",$BM308-$BG308) | BO308: =IFERROR(IF($C308="","",'BUDGET COMMESSA'!$G305),"") | BP308: =IF($C308="","",SUMIF('COSTI DIRETTI'!$C$6:$C$505,$C308,'COSTI DIRETTI'!$H$6:$H$505)+SUMIF('SALDI AL 31.12.2025'!$A$6:$A$505,$C308,'SALDI AL 31.12.2025'!$I$6:$I$505)) | BQ308: =IF(OR($C308="",$BO308=""),"",MAX($BO308-$BP308,0)) | BR308: =IF(OR($C308="",$BO308=""),"",MAX($BP308-$BO308,0)) | BS308: =IF($C308="","",$BK308*PARAMETRI!$B$4+$BP308) | BT308: =IF($A308="CRITICO",1,0) -> 0 | BU308: =IF($A308="ATTENZIONE",1,0) -> 0 | BV308: =IF($C308="","",SUMIF('MOVIMENTI 2026'!$B$7:$B$4206,$C308,'MOVIMENTI 2026'!$P$7:$P$4206)+SUMIF('SALDI AL 31.12.2025'!$A$6:$A$505,$C308,'SALDI AL 31.12.2025'!$G$6:$G$505))

Sheet PARAMETRI
A1: PARAMETRI DI CONTROLLO – REV.14
D2: COMMESSE | E2: SELEZIONE RIGHE | F2: COMMESSE PREGRESSE | G2: MESI | H2: TIPI MOVIMENTO | I2: RIGHE PREGRESSE
A3: PARAMETRO | B3: VALORE | C3: NOTA / FUNZIONE DEL PARAMETRO | D3: TUTTE | F3: TUTTE | G3: Gennaio | H3: SAL
A4: Costo strutturale aziendale corrente | B4: 45.79 | C4: Parametro unico FIDA EDILE utilizzato per valorizzare economicamente le ore effettive delle commesse. Il costo effettivo cumulato è determinato da: ore effettive cumulative × costo strutturale corrente + costi diretti cumulativi. | D4: =IF(ANAGRAFICA!$B6="","",ANAGRAFICA!$B6) -> C042 | F4: =IFERROR(INDEX(ANAGRAFICA!$B$6:$B$305,SMALL($I$4:$I$303,ROWS($F$4:F4))),"") | G4: Febbraio | H4: FATTURA | I4: =IF(ANAGRAFICA!$B6="","",IF(ANAGRAFICA!$I6="","",IF(ANAGRAFICA!$I6<DATE($B$11,1,1),1,"")))
A5: Scarto tempo – attenzione | B5: 0.07 | C5: Soglia di attenzione quando la % di SAL maturato risulta inferiore alla % di avanzamento temporale della commessa oltre questo scostamento. | D5: =IF(ANAGRAFICA!$B7="","",ANAGRAFICA!$B7) -> C011 | F5: =IFERROR(INDEX(ANAGRAFICA!$B$6:$B$305,SMALL($I$4:$I$303,ROWS($F$4:F5))),"") | G5: Marzo | H5: SAL + FATTURA | I5: =IF(ANAGRAFICA!$B7="","",IF(ANAGRAFICA!$I7="","",IF(ANAGRAFICA!$I7<DATE($B$11,1,1),2,"")))
A6: Scarto tempo – critico | B6: 0.15 | C6: Soglia critica quando la % di SAL maturato risulta inferiore alla % di avanzamento temporale della commessa oltre questo scostamento. | D6: =IF(ANAGRAFICA!$B8="","",ANAGRAFICA!$B8) -> TEST10 | F6: =IFERROR(INDEX(ANAGRAFICA!$B$6:$B$305,SMALL($I$4:$I$303,ROWS($F$4:F6))),"") | G6: Aprile | H6: SVINCOLO RITENUTA | I6: =IF(ANAGRAFICA!$B8="","",IF(ANAGRAFICA!$I8="","",IF(ANAGRAFICA!$I8<DATE($B$11,1,1),3,"")))
A7: Scarto ore – attenzione | B7: 0.07 | C7: Soglia di attenzione quando la % di ore consumate supera la % di SAL maturato oltre questo scostamento. | D7: =IF(ANAGRAFICA!$B9="","",ANAGRAFICA!$B9) -> C042 | F7: =IFERROR(INDEX(ANAGRAFICA!$B$6:$B$305,SMALL($I$4:$I$303,ROWS($F$4:F7))),"") | G7: Maggio | H7: ORE | I7: =IF(ANAGRAFICA!$B9="","",IF(ANAGRAFICA!$I9="","",IF(ANAGRAFICA!$I9<DATE($B$11,1,1),4,"")))
A8: Scarto ore – critico | B8: 0.15 | C8: Soglia critica quando la % di ore consumate supera la % di SAL maturato oltre questo scostamento. | D8: =IF(ANAGRAFICA!$B10="","",ANAGRAFICA!$B10) | F8: =IFERROR(INDEX(ANAGRAFICA!$B$6:$B$305,SMALL($I$4:$I$303,ROWS($F$4:F8))),"") | G8: Giugno | H8: PERDITA SAL ACCETTATA | I8: =IF(ANAGRAFICA!$B10="","",IF(ANAGRAFICA!$I10="","",IF(ANAGRAFICA!$I10<DATE($B$11,1,1),5,"")))
A9: Soglia SAL non fatturato | B9: 0.05 | C9: Percentuale del valore contrattuale utilizzata come soglia per segnalare un SAL maturato non ancora fatturato di importo significativo. | D9: =IF(ANAGRAFICA!$B11="","",ANAGRAFICA!$B11) | F9: =IFERROR(INDEX(ANAGRAFICA!$B$6:$B$305,SMALL($I$4:$I$303,ROWS($F$4:F9))),"") | G9: Luglio | H9: ALTRO | I9: =IF(ANAGRAFICA!$B11="","",IF(ANAGRAFICA!$I11="","",IF(ANAGRAFICA!$I11<DATE($B$11,1,1),6,"")))
D10: =IF(ANAGRAFICA!$B12="","",ANAGRAFICA!$B12) | F10: =IFERROR(INDEX(ANAGRAFICA!$B$6:$B$305,SMALL($I$4:$I$303,ROWS($F$4:F10))),"") | G10: Agosto | I10: =IF(ANAGRAFICA!$B12="","",IF(ANAGRAFICA!$I12="","",IF(ANAGRAFICA!$I12<DATE($B$11,1,1),7,"")))
A11: Anno di gestione | B11: 2026 | C11: Anno di riferimento del Database. Determina l'esercizio considerato dalla dashboard MOVIMENTI, il limite temporale per individuare le commesse pregresse da riportare nei SALDI e le elaborazioni annuali collegate ai costi diretti. | D11: =IF(ANAGRAFICA!$B13="","",ANAGRAFICA!$B13) | F11: =IFERROR(INDEX(ANAGRAFICA!$B$6:$B$305,SMALL($I$4:$I$303,ROWS($F$4:F11))),"") | G11: Settembre | I11: =IF(ANAGRAFICA!$B13="","",IF(ANAGRAFICA!$I13="","",IF(ANAGRAFICA!$I13<DATE($B$11,1,1),8,"")))
D12: =IF(ANAGRAFICA!$B14="","",ANAGRAFICA!$B14) | F12: =IFERROR(INDEX(ANAGRAFICA!$B$6:$B$305,SMALL($I$4:$I$303,ROWS($F$4:F12))),"") | G12: Ottobre | I12: =IF(ANAGRAFICA!$B14="","",IF(ANAGRAFICA!$I14="","",IF(ANAGRAFICA!$I14<DATE($B$11,1,1),9,"")))
D13: =IF(ANAGRAFICA!$B15="","",ANAGRAFICA!$B15) | F13: =IFERROR(INDEX(ANAGRAFICA!$B$6:$B$305,SMALL($I$4:$I$303,ROWS($F$4:F13))),"") | G13: Novembre | I13: =IF(ANAGRAFICA!$B15="","",IF(ANAGRAFICA!$I15="","",IF(ANAGRAFICA!$I15<DATE($B$11,1,1),10,"")))
D14: =IF(ANAGRAFICA!$B16="","",ANAGRAFICA!$B16) | F14: =IFERROR(INDEX(ANAGRAFICA!$B$6:$B$305,SMALL($I$4:$I$303,ROWS($F$4:F14))),"") | G14: Dicembre | I14: =IF(ANAGRAFICA!$B16="","",IF(ANAGRAFICA!$I16="","",IF(ANAGRAFICA!$I16<DATE($B$11,1,1),11,"")))
D15: =IF(ANAGRAFICA!$B17="","",ANAGRAFICA!$B17) | F15: =IFERROR(INDEX(ANAGRAFICA!$B$6:$B$305,SMALL($I$4:$I$303,ROWS($F$4:F15))),"") | I15: =IF(ANAGRAFICA!$B17="","",IF(ANAGRAFICA!$I17="","",IF(ANAGRAFICA!$I17<DATE($B$11,1,1),12,"")))
D16: =IF(ANAGRAFICA!$B18="","",ANAGRAFICA!$B18) | F16: =IFERROR(INDEX(ANAGRAFICA!$B$6:$B$305,SMALL($I$4:$I$303,ROWS($F$4:F16))),"") | I16: =IF(ANAGRAFICA!$B18="","",IF(ANAGRAFICA!$I18="","",IF(ANAGRAFICA!$I18<DATE($B$11,1,1),13,"")))
D17: =IF(ANAGRAFICA!$B19="","",ANAGRAFICA!$B19) | F17: =IFERROR(INDEX(ANAGRAFICA!$B$6:$B$305,SMALL($I$4:$I$303,ROWS($F$4:F17))),"") | I17: =IF(ANAGRAFICA!$B19="","",IF(ANAGRAFICA!$I19="","",IF(ANAGRAFICA!$I19<DATE($B$11,1,1),14,"")))
D18: =IF(ANAGRAFICA!$B20="","",ANAGRAFICA!$B20) | F18: =IFERROR(INDEX(ANAGRAFICA!$B$6:$B$305,SMALL($I$4:$I$303,ROWS($F$4:F18))),"") | I18: =IF(ANAGRAFICA!$B20="","",IF(ANAGRAFICA!$I20="","",IF(ANAGRAFICA!$I20<DATE($B$11,1,1),15,"")))
D19: =IF(ANAGRAFICA!$B21="","",ANAGRAFICA!$B21) | F19: =IFERROR(INDEX(ANAGRAFICA!$B$6:$B$305,SMALL($I$4:$I$303,ROWS($F$4:F19))),"") | I19: =IF(ANAGRAFICA!$B21="","",IF(ANAGRAFICA!$I21="","",IF(ANAGRAFICA!$I21<DATE($B$11,1,1),16,"")))
D20: =IF(ANAGRAFICA!$B22="","",ANAGRAFICA!$B22) | F20: =IFERROR(INDEX(ANAGRAFICA!$B$6:$B$305,SMALL($I$4:$I$303,ROWS($F$4:F20))),"") | I20: =IF(ANAGRAFICA!$B22="","",IF(ANAGRAFICA!$I22="","",IF(ANAGRAFICA!$I22<DATE($B$11,1,1),17,"")))
D21: =IF(ANAGRAFICA!$B23="","",ANAGRAFICA!$B23) | F21: =IFERROR(INDEX(ANAGRAFICA!$B$6:$B$305,SMALL($I$4:$I$303,ROWS($F$4:F21))),"") | I21: =IF(ANAGRAFICA!$B23="","",IF(ANAGRAFICA!$I23="","",IF(ANAGRAFICA!$I23<DATE($B$11,1,1),18,"")))
D22: =IF(ANAGRAFICA!$B24="","",ANAGRAFICA!$B24) | F22: =IFERROR(INDEX(ANAGRAFICA!$B$6:$B$305,SMALL($I$4:$I$303,ROWS($F$4:F22))),"") | I22: =IF(ANAGRAFICA!$B24="","",IF(ANAGRAFICA!$I24="","",IF(ANAGRAFICA!$I24<DATE($B$11,1,1),19,"")))
D23: =IF(ANAGRAFICA!$B25="","",ANAGRAFICA!$B25) | F23: =IFERROR(INDEX(ANAGRAFICA!$B$6:$B$305,SMALL($I$4:$I$303,ROWS($F$4:F23))),"") | I23: =IF(ANAGRAFICA!$B25="","",IF(ANAGRAFICA!$I25="","",IF(ANAGRAFICA!$I25<DATE($B$11,1,1),20,"")))
D24: =IF(ANAGRAFICA!$B26="","",ANAGRAFICA!$B26) | F24: =IFERROR(INDEX(ANAGRAFICA!$B$6:$B$305,SMALL($I$4:$I$303,ROWS($F$4:F24))),"") | I24: =IF(ANAGRAFICA!$B26="","",IF(ANAGRAFICA!$I26="","",IF(ANAGRAFICA!$I26<DATE($B$11,1,1),21,"")))
D25: =IF(ANAGRAFICA!$B27="","",ANAGRAFICA!$B27) | F25: =IFERROR(INDEX(ANAGRAFICA!$B$6:$B$305,SMALL($I$4:$I$303,ROWS($F$4:F25))),"") | I25: =IF(ANAGRAFICA!$B27="","",IF(ANAGRAFICA!$I27="","",IF(ANAGRAFICA!$I27<DATE($B$11,1,1),22,"")))
D26: =IF(ANAGRAFICA!$B28="","",ANAGRAFICA!$B28) | F26: =IFERROR(INDEX(ANAGRAFICA!$B$6:$B$305,SMALL($I$4:$I$303,ROWS($F$4:F26))),"") | I26: =IF(ANAGRAFICA!$B28="","",IF(ANAGRAFICA!$I28="","",IF(ANAGRAFICA!$I28<DATE($B$11,1,1),23,"")))
D27: =IF(ANAGRAFICA!$B29="","",ANAGRAFICA!$B29) | F27: =IFERROR(INDEX(ANAGRAFICA!$B$6:$B$305,SMALL($I$4:$I$303,ROWS($F$4:F27))),"") | I27: =IF(ANAGRAFICA!$B29="","",IF(ANAGRAFICA!$I29="","",IF(ANAGRAFICA!$I29<DATE($B$11,1,1),24,"")))
D28: =IF(ANAGRAFICA!$B30="","",ANAGRAFICA!$B30) | F28: =IFERROR(INDEX(ANAGRAFICA!$B$6:$B$305,SMALL($I$4:$I$303,ROWS($F$4:F28))),"") | I28: =IF(ANAGRAFICA!$B30="","",IF(ANAGRAFICA!$I30="","",IF(ANAGRAFICA!$I30<DATE($B$11,1,1),25,"")))
D29: =IF(ANAGRAFICA!$B31="","",ANAGRAFICA!$B31) | F29: =IFERROR(INDEX(ANAGRAFICA!$B$6:$B$305,SMALL($I$4:$I$303,ROWS($F$4:F29))),"") | I29: =IF(ANAGRAFICA!$B31="","",IF(ANAGRAFICA!$I31="","",IF(ANAGRAFICA!$I31<DATE($B$11,1,1),26,"")))
D30: =IF(ANAGRAFICA!$B32="","",ANAGRAFICA!$B32) | F30: =IFERROR(INDEX(ANAGRAFICA!$B$6:$B$305,SMALL($I$4:$I$303,ROWS($F$4:F30))),"") | I30: =IF(ANAGRAFICA!$B32="","",IF(ANAGRAFICA!$I32="","",IF(ANAGRAFICA!$I32<DATE($B$11,1,1),27,"")))
D31: =IF(ANAGRAFICA!$B33="","",ANAGRAFICA!$B33) | F31: =IFERROR(INDEX(ANAGRAFICA!$B$6:$B$305,SMALL($I$4:$I$303,ROWS($F$4:F31))),"") | I31: =IF(ANAGRAFICA!$B33="","",IF(ANAGRAFICA!$I33="","",IF(ANAGRAFICA!$I33<DATE($B$11,1,1),28,"")))
D32: =IF(ANAGRAFICA!$B34="","",ANAGRAFICA!$B34) | F32: =IFERROR(INDEX(ANAGRAFICA!$B$6:$B$305,SMALL($I$4:$I$303,ROWS($F$4:F32))),"") | I32: =IF(ANAGRAFICA!$B34="","",IF(ANAGRAFICA!$I34="","",IF(ANAGRAFICA!$I34<DATE($B$11,1,1),29,"")))
D33: =IF(ANAGRAFICA!$B35="","",ANAGRAFICA!$B35) | F33: =IFERROR(INDEX(ANAGRAFICA!$B$6:$B$305,SMALL($I$4:$I$303,ROWS($F$4:F33))),"") | I33: =IF(ANAGRAFICA!$B35="","",IF(ANAGRAFICA!$I35="","",IF(ANAGRAFICA!$I35<DATE($B$11,1,1),30,"")))
D34: =IF(ANAGRAFICA!$B36="","",ANAGRAFICA!$B36) | F34: =IFERROR(INDEX(ANAGRAFICA!$B$6:$B$305,SMALL($I$4:$I$303,ROWS($F$4:F34))),"") | I34: =IF(ANAGRAFICA!$B36="","",IF(ANAGRAFICA!$I36="","",IF(ANAGRAFICA!$I36<DATE($B$11,1,1),31,"")))
D35: =IF(ANAGRAFICA!$B37="","",ANAGRAFICA!$B37) | F35: =IFERROR(INDEX(ANAGRAFICA!$B$6:$B$305,SMALL($I$4:$I$303,ROWS($F$4:F35))),"") | I35: =IF(ANAGRAFICA!$B37="","",IF(ANAGRAFICA!$I37="","",IF(ANAGRAFICA!$I37<DATE($B$11,1,1),32,"")))
D36: =IF(ANAGRAFICA!$B38="","",ANAGRAFICA!$B38) | F36: =IFERROR(INDEX(ANAGRAFICA!$B$6:$B$305,SMALL($I$4:$I$303,ROWS($F$4:F36))),"") | I36: =IF(ANAGRAFICA!$B38="","",IF(ANAGRAFICA!$I38="","",IF(ANAGRAFICA!$I38<DATE($B$11,1,1),33,"")))
D37: =IF(ANAGRAFICA!$B39="","",ANAGRAFICA!$B39) | F37: =IFERROR(INDEX(ANAGRAFICA!$B$6:$B$305,SMALL($I$4:$I$303,ROWS($F$4:F37))),"") | I37: =IF(ANAGRAFICA!$B39="","",IF(ANAGRAFICA!$I39="","",IF(ANAGRAFICA!$I39<DATE($B$11,1,1),34,"")))
D38: =IF(ANAGRAFICA!$B40="","",ANAGRAFICA!$B40) | F38: =IFERROR(INDEX(ANAGRAFICA!$B$6:$B$305,SMALL($I$4:$I$303,ROWS($F$4:F38))),"") | I38: =IF(ANAGRAFICA!$B40="","",IF(ANAGRAFICA!$I40="","",IF(ANAGRAFICA!$I40<DATE($B$11,1,1),35,"")))
D39: =IF(ANAGRAFICA!$B41="","",ANAGRAFICA!$B41) | F39: =IFERROR(INDEX(ANAGRAFICA!$B$6:$B$305,SMALL($I$4:$I$303,ROWS($F$4:F39))),"") | I39: =IF(ANAGRAFICA!$B41="","",IF(ANAGRAFICA!$I41="","",IF(ANAGRAFICA!$I41<DATE($B$11,1,1),36,"")))
D40: =IF(ANAGRAFICA!$B42="","",ANAGRAFICA!$B42) | F40: =IFERROR(INDEX(ANAGRAFICA!$B$6:$B$305,SMALL($I$4:$I$303,ROWS($F$4:F40))),"") | I40: =IF(ANAGRAFICA!$B42="","",IF(ANAGRAFICA!$I42="","",IF(ANAGRAFICA!$I42<DATE($B$11,1,1),37,"")))
D41: =IF(ANAGRAFICA!$B43="","",ANAGRAFICA!$B43) | F41: =IFERROR(INDEX(ANAGRAFICA!$B$6:$B$305,SMALL($I$4:$I$303,ROWS($F$4:F41))),"") | I41: =IF(ANAGRAFICA!$B43="","",IF(ANAGRAFICA!$I43="","",IF(ANAGRAFICA!$I43<DATE($B$11,1,1),38,"")))
D42: =IF(ANAGRAFICA!$B44="","",ANAGRAFICA!$B44) | F42: =IFERROR(INDEX(ANAGRAFICA!$B$6:$B$305,SMALL($I$4:$I$303,ROWS($F$4:F42))),"") | I42: =IF(ANAGRAFICA!$B44="","",IF(ANAGRAFICA!$I44="","",IF(ANAGRAFICA!$I44<DATE($B$11,1,1),39,"")))
D43: =IF(ANAGRAFICA!$B45="","",ANAGRAFICA!$B45) | F43: =IFERROR(INDEX(ANAGRAFICA!$B$6:$B$305,SMALL($I$4:$I$303,ROWS($F$4:F43))),"") | I43: =IF(ANAGRAFICA!$B45="","",IF(ANAGRAFICA!$I45="","",IF(ANAGRAFICA!$I45<DATE($B$11,1,1),40,"")))
D44: =IF(ANAGRAFICA!$B46="","",ANAGRAFICA!$B46) | F44: =IFERROR(INDEX(ANAGRAFICA!$B$6:$B$305,SMALL($I$4:$I$303,ROWS($F$4:F44))),"") | I44: =IF(ANAGRAFICA!$B46="","",IF(ANAGRAFICA!$I46="","",IF(ANAGRAFICA!$I46<DATE($B$11,1,1),41,"")))
D45: =IF(ANAGRAFICA!$B47="","",ANAGRAFICA!$B47) | F45: =IFERROR(INDEX(ANAGRAFICA!$B$6:$B$305,SMALL($I$4:$I$303,ROWS($F$4:F45))),"") | I45: =IF(ANAGRAFICA!$B47="","",IF(ANAGRAFICA!$I47="","",IF(ANAGRAFICA!$I47<DATE($B$11,1,1),42,"")))
D46: =IF(ANAGRAFICA!$B48="","",ANAGRAFICA!$B48) | F46: =IFERROR(INDEX(ANAGRAFICA!$B$6:$B$305,SMALL($I$4:$I$303,ROWS($F$4:F46))),"") | I46: =IF(ANAGRAFICA!$B48="","",IF(ANAGRAFICA!$I48="","",IF(ANAGRAFICA!$I48<DATE($B$11,1,1),43,"")))
D47: =IF(ANAGRAFICA!$B49="","",ANAGRAFICA!$B49) | F47: =IFERROR(INDEX(ANAGRAFICA!$B$6:$B$305,SMALL($I$4:$I$303,ROWS($F$4:F47))),"") | I47: =IF(ANAGRAFICA!$B49="","",IF(ANAGRAFICA!$I49="","",IF(ANAGRAFICA!$I49<DATE($B$11,1,1),44,"")))
D48: =IF(ANAGRAFICA!$B50="","",ANAGRAFICA!$B50) | F48: =IFERROR(INDEX(ANAGRAFICA!$B$6:$B$305,SMALL($I$4:$I$303,ROWS($F$4:F48))),"") | I48: =IF(ANAGRAFICA!$B50="","",IF(ANAGRAFICA!$I50="","",IF(ANAGRAFICA!$I50<DATE($B$11,1,1),45,"")))
D49: =IF(ANAGRAFICA!$B51="","",ANAGRAFICA!$B51) | F49: =IFERROR(INDEX(ANAGRAFICA!$B$6:$B$305,SMALL($I$4:$I$303,ROWS($F$4:F49))),"") | I49: =IF(ANAGRAFICA!$B51="","",IF(ANAGRAFICA!$I51="","",IF(ANAGRAFICA!$I51<DATE($B$11,1,1),46,"")))
D50: =IF(ANAGRAFICA!$B52="","",ANAGRAFICA!$B52) | F50: =IFERROR(INDEX(ANAGRAFICA!$B$6:$B$305,SMALL($I$4:$I$303,ROWS($F$4:F50))),"") | I50: =IF(ANAGRAFICA!$B52="","",IF(ANAGRAFICA!$I52="","",IF(ANAGRAFICA!$I52<DATE($B$11,1,1),47,"")))
D51: =IF(ANAGRAFICA!$B53="","",ANAGRAFICA!$B53) | F51: =IFERROR(INDEX(ANAGRAFICA!$B$6:$B$305,SMALL($I$4:$I$303,ROWS($F$4:F51))),"") | I51: =IF(ANAGRAFICA!$B53="","",IF(ANAGRAFICA!$I53="","",IF(ANAGRAFICA!$I53<DATE($B$11,1,1),48,"")))
D52: =IF(ANAGRAFICA!$B54="","",ANAGRAFICA!$B54) | F52: =IFERROR(INDEX(ANAGRAFICA!$B$6:$B$305,SMALL($I$4:$I$303,ROWS($F$4:F52))),"") | I52: =IF(ANAGRAFICA!$B54="","",IF(ANAGRAFICA!$I54="","",IF(ANAGRAFICA!$I54<DATE($B$11,1,1),49,"")))
D53: =IF(ANAGRAFICA!$B55="","",ANAGRAFICA!$B55) | F53: =IFERROR(INDEX(ANAGRAFICA!$B$6:$B$305,SMALL($I$4:$I$303,ROWS($F$4:F53))),"") | I53: =IF(ANAGRAFICA!$B55="","",IF(ANAGRAFICA!$I55="","",IF(ANAGRAFICA!$I55<DATE($B$11,1,1),50,"")))
D54: =IF(ANAGRAFICA!$B56="","",ANAGRAFICA!$B56) | F54: =IFERROR(INDEX(ANAGRAFICA!$B$6:$B$305,SMALL($I$4:$I$303,ROWS($F$4:F54))),"") | I54: =IF(ANAGRAFICA!$B56="","",IF(ANAGRAFICA!$I56="","",IF(ANAGRAFICA!$I56<DATE($B$11,1,1),51,"")))
D55: =IF(ANAGRAFICA!$B57="","",ANAGRAFICA!$B57) | F55: =IFERROR(INDEX(ANAGRAFICA!$B$6:$B$305,SMALL($I$4:$I$303,ROWS($F$4:F55))),"") | I55: =IF(ANAGRAFICA!$B57="","",IF(ANAGRAFICA!$I57="","",IF(ANAGRAFICA!$I57<DATE($B$11,1,1),52,"")))
D56: =IF(ANAGRAFICA!$B58="","",ANAGRAFICA!$B58) | F56: =IFERROR(INDEX(ANAGRAFICA!$B$6:$B$305,SMALL($I$4:$I$303,ROWS($F$4:F56))),"") | I56: =IF(ANAGRAFICA!$B58="","",IF(ANAGRAFICA!$I58="","",IF(ANAGRAFICA!$I58<DATE($B$11,1,1),53,"")))
D57: =IF(ANAGRAFICA!$B59="","",ANAGRAFICA!$B59) | F57: =IFERROR(INDEX(ANAGRAFICA!$B$6:$B$305,SMALL($I$4:$I$303,ROWS($F$4:F57))),"") | I57: =IF(ANAGRAFICA!$B59="","",IF(ANAGRAFICA!$I59="","",IF(ANAGRAFICA!$I59<DATE($B$11,1,1),54,"")))
D58: =IF(ANAGRAFICA!$B60="","",ANAGRAFICA!$B60) | F58: =IFERROR(INDEX(ANAGRAFICA!$B$6:$B$305,SMALL($I$4:$I$303,ROWS($F$4:F58))),"") | I58: =IF(ANAGRAFICA!$B60="","",IF(ANAGRAFICA!$I60="","",IF(ANAGRAFICA!$I60<DATE($B$11,1,1),55,"")))
D59: =IF(ANAGRAFICA!$B61="","",ANAGRAFICA!$B61) | F59: =IFERROR(INDEX(ANAGRAFICA!$B$6:$B$305,SMALL($I$4:$I$303,ROWS($F$4:F59))),"") | I59: =IF(ANAGRAFICA!$B61="","",IF(ANAGRAFICA!$I61="","",IF(ANAGRAFICA!$I61<DATE($B$11,1,1),56,"")))
D60: =IF(ANAGRAFICA!$B62="","",ANAGRAFICA!$B62) | F60: =IFERROR(INDEX(ANAGRAFICA!$B$6:$B$305,SMALL($I$4:$I$303,ROWS($F$4:F60))),"") | I60: =IF(ANAGRAFICA!$B62="","",IF(ANAGRAFICA!$I62="","",IF(ANAGRAFICA!$I62<DATE($B$11,1,1),57,"")))
D61: =IF(ANAGRAFICA!$B63="","",ANAGRAFICA!$B63) | F61: =IFERROR(INDEX(ANAGRAFICA!$B$6:$B$305,SMALL($I$4:$I$303,ROWS($F$4:F61))),"") | I61: =IF(ANAGRAFICA!$B63="","",IF(ANAGRAFICA!$I63="","",IF(ANAGRAFICA!$I63<DATE($B$11,1,1),58,"")))
D62: =IF(ANAGRAFICA!$B64="","",ANAGRAFICA!$B64) | F62: =IFERROR(INDEX(ANAGRAFICA!$B$6:$B$305,SMALL($I$4:$I$303,ROWS($F$4:F62))),"") | I62: =IF(ANAGRAFICA!$B64="","",IF(ANAGRAFICA!$I64="","",IF(ANAGRAFICA!$I64<DATE($B$11,1,1),59,"")))
D63: =IF(ANAGRAFICA!$B65="","",ANAGRAFICA!$B65) | F63: =IFERROR(INDEX(ANAGRAFICA!$B$6:$B$305,SMALL($I$4:$I$303,ROWS($F$4:F63))),"") | I63: =IF(ANAGRAFICA!$B65="","",IF(ANAGRAFICA!$I65="","",IF(ANAGRAFICA!$I65<DATE($B$11,1,1),60,"")))
D64: =IF(ANAGRAFICA!$B66="","",ANAGRAFICA!$B66) | F64: =IFERROR(INDEX(ANAGRAFICA!$B$6:$B$305,SMALL($I$4:$I$303,ROWS($F$4:F64))),"") | I64: =IF(ANAGRAFICA!$B66="","",IF(ANAGRAFICA!$I66="","",IF(ANAGRAFICA!$I66<DATE($B$11,1,1),61,"")))
D65: =IF(ANAGRAFICA!$B67="","",ANAGRAFICA!$B67) | F65: =IFERROR(INDEX(ANAGRAFICA!$B$6:$B$305,SMALL($I$4:$I$303,ROWS($F$4:F65))),"") | I65: =IF(ANAGRAFICA!$B67="","",IF(ANAGRAFICA!$I67="","",IF(ANAGRAFICA!$I67<DATE($B$11,1,1),62,"")))
D66: =IF(ANAGRAFICA!$B68="","",ANAGRAFICA!$B68) | F66: =IFERROR(INDEX(ANAGRAFICA!$B$6:$B$305,SMALL($I$4:$I$303,ROWS($F$4:F66))),"") | I66: =IF(ANAGRAFICA!$B68="","",IF(ANAGRAFICA!$I68="","",IF(ANAGRAFICA!$I68<DATE($B$11,1,1),63,"")))
D67: =IF(ANAGRAFICA!$B69="","",ANAGRAFICA!$B69) | F67: =IFERROR(INDEX(ANAGRAFICA!$B$6:$B$305,SMALL($I$4:$I$303,ROWS($F$4:F67))),"") | I67: =IF(ANAGRAFICA!$B69="","",IF(ANAGRAFICA!$I69="","",IF(ANAGRAFICA!$I69<DATE($B$11,1,1),64,"")))
D68: =IF(ANAGRAFICA!$B70="","",ANAGRAFICA!$B70) | F68: =IFERROR(INDEX(ANAGRAFICA!$B$6:$B$305,SMALL($I$4:$I$303,ROWS($F$4:F68))),"") | I68: =IF(ANAGRAFICA!$B70="","",IF(ANAGRAFICA!$I70="","",IF(ANAGRAFICA!$I70<DATE($B$11,1,1),65,"")))
D69: =IF(ANAGRAFICA!$B71="","",ANAGRAFICA!$B71) | F69: =IFERROR(INDEX(ANAGRAFICA!$B$6:$B$305,SMALL($I$4:$I$303,ROWS($F$4:F69))),"") | I69: =IF(ANAGRAFICA!$B71="","",IF(ANAGRAFICA!$I71="","",IF(ANAGRAFICA!$I71<DATE($B$11,1,1),66,"")))
D70: =IF(ANAGRAFICA!$B72="","",ANAGRAFICA!$B72) | F70: =IFERROR(INDEX(ANAGRAFICA!$B$6:$B$305,SMALL($I$4:$I$303,ROWS($F$4:F70))),"") | I70: =IF(ANAGRAFICA!$B72="","",IF(ANAGRAFICA!$I72="","",IF(ANAGRAFICA!$I72<DATE($B$11,1,1),67,"")))
D71: =IF(ANAGRAFICA!$B73="","",ANAGRAFICA!$B73) | F71: =IFERROR(INDEX(ANAGRAFICA!$B$6:$B$305,SMALL($I$4:$I$303,ROWS($F$4:F71))),"") | I71: =IF(ANAGRAFICA!$B73="","",IF(ANAGRAFICA!$I73="","",IF(ANAGRAFICA!$I73<DATE($B$11,1,1),68,"")))
D72: =IF(ANAGRAFICA!$B74="","",ANAGRAFICA!$B74) | F72: =IFERROR(INDEX(ANAGRAFICA!$B$6:$B$305,SMALL($I$4:$I$303,ROWS($F$4:F72))),"") | I72: =IF(ANAGRAFICA!$B74="","",IF(ANAGRAFICA!$I74="","",IF(ANAGRAFICA!$I74<DATE($B$11,1,1),69,"")))
D73: =IF(ANAGRAFICA!$B75="","",ANAGRAFICA!$B75) | F73: =IFERROR(INDEX(ANAGRAFICA!$B$6:$B$305,SMALL($I$4:$I$303,ROWS($F$4:F73))),"") | I73: =IF(ANAGRAFICA!$B75="","",IF(ANAGRAFICA!$I75="","",IF(ANAGRAFICA!$I75<DATE($B$11,1,1),70,"")))
D74: =IF(ANAGRAFICA!$B76="","",ANAGRAFICA!$B76) | F74: =IFERROR(INDEX(ANAGRAFICA!$B$6:$B$305,SMALL($I$4:$I$303,ROWS($F$4:F74))),"") | I74: =IF(ANAGRAFICA!$B76="","",IF(ANAGRAFICA!$I76="","",IF(ANAGRAFICA!$I76<DATE($B$11,1,1),71,"")))
D75: =IF(ANAGRAFICA!$B77="","",ANAGRAFICA!$B77) | F75: =IFERROR(INDEX(ANAGRAFICA!$B$6:$B$305,SMALL($I$4:$I$303,ROWS($F$4:F75))),"") | I75: =IF(ANAGRAFICA!$B77="","",IF(ANAGRAFICA!$I77="","",IF(ANAGRAFICA!$I77<DATE($B$11,1,1),72,"")))
D76: =IF(ANAGRAFICA!$B78="","",ANAGRAFICA!$B78) | F76: =IFERROR(INDEX(ANAGRAFICA!$B$6:$B$305,SMALL($I$4:$I$303,ROWS($F$4:F76))),"") | I76: =IF(ANAGRAFICA!$B78="","",IF(ANAGRAFICA!$I78="","",IF(ANAGRAFICA!$I78<DATE($B$11,1,1),73,"")))
D77: =IF(ANAGRAFICA!$B79="","",ANAGRAFICA!$B79) | F77: =IFERROR(INDEX(ANAGRAFICA!$B$6:$B$305,SMALL($I$4:$I$303,ROWS($F$4:F77))),"") | I77: =IF(ANAGRAFICA!$B79="","",IF(ANAGRAFICA!$I79="","",IF(ANAGRAFICA!$I79<DATE($B$11,1,1),74,"")))
